Workbook
Name \0: #REF!
Name \A: #REF!
Name \B: #REF!
Name \c: #REF!
Name \D: #REF!
Name \f: #REF!
Name \g: #REF!
Name \k: #REF!
Name \n: #REF!
Name \P: #REF!
Name \Q: #REF!
Name \s: #REF!
Name \X: #REF!
Name \y: #REF!
Name \z: #REF!
Name _.._The_Oaks: #REF!
Name _\A: #REF!
Name _\L: #REF!
Name _\P: #REF!
Name _\s: #REF!
Name _\w: #N/A
Name _\z: #REF!
Name __\a: #REF!
Name __\b: #REF!
Name __\c: #REF!
Name __\m: #REF!
Name __\q: #REF!
Name __\w: #N/A
Name __\z: #REF!
Name _________\a: #REF!
Name _________\b: #REF!
Name _________\c: #REF!
Name _________\m: #REF!
Name __________\z: #REF!
Name ___________\q: #REF!
Name ___________________\q: #REF!
Name __________________________________\a: #REF!
Name __________________________________\b: #REF!
Name _______________________________________\c: #REF!
Name _______________________________________\m: #REF!
Name __________________________a1: #REF!
Name _________________________a1: #REF!
Name ________________________a1: #REF!
Name ________________________RET1: #REF!
Name ________________________RET2: #REF!
Name ________________________RET3: #REF!
Name ________________________RET4: #REF!
Name ________________________RET5: #REF!
Name ________________________RET6: #REF!
Name _______________________a1: #REF!
Name _______________________RET1: #REF!
Name _______________________RET2: #REF!
Name _______________________RET3: #REF!
Name _______________________RET4: #REF!
Name _______________________RET5: #REF!
Name _______________________RET6: #REF!
Name ______________________a1: #REF!
Name ______________________i1: #REF!
Name ______________________RET1: #REF!
Name ______________________RET2: #REF!

Sheet Resumen
F2: Formato Informe Semanal Proyectos Contratistas | L2: Contrato nro W381147
F4: Ecopetrol Desarrollo de Proyectos Vicepresidencias De Desarrollo y Proyectos
F6: EDP-F-052 | G6: Elaborado 02/11/2023 | K6: Versión 4
B10: 1. DATOS GENERALES
B12: Contratista | D12: CONSORCIO IIWA KAI | G12: Fecha de Reporte | H12: De | I12: 46256 | K12: Fechas | L12: Plan | M12: Real / Proyectada
B13: Contrato / Orden de Servicio No. | D13: W381147 – VEE - 002 | H13: Hasta | I13: =+I12+6 -> 46262 | K13: Inicio | L13: 46218 | M13: 46218
G14: Reporte No. | I14: 7 | K14: Finalización | L14: 46617 | M14: 46617
B15: DESCRIPCIÓN OBJETO DEL CONTRATO U ODS | K15: RESUMEN PROGRESO DE CONTRATO U ODS
B16: ONSTRUCCIÓN DE PLATAFORMAS Y CIMENTACIONES DE AEROGENERADORES DEL PARQUE EÓLICO WINDPESHI | K16: PLANEADO | L16: EJECUTADO | M16: DIFERENCIA
K17: =+'C3'!I13 -> 0.0041150005 | L17: =+'C3'!I14 -> 0.000333753 | M17: =+L17-K17 -> -0.0037812475
B19: 2. INDICADORES HSE, PERSONAL Y TIEMPOS
B21: PERSONAL EN CAMPO | D21: DIRECTOS (INCLUYE SUBCONTRATISTAS) | G21: PERSONAL STAFF DEL CONTRATISTA | K21: HH ACUM. CORTE ANTERIOR | L21: HH SEMANA ACTUAL | M21: HH ACUM. SEMANA ACTUAL
D22: REGIÓN | E22: NO REGIÓN | F22: TOTAL | G22: REGIÓN | H22: NO REGIÓN | I22: TOTAL
B23: CALIFICADO | D23: =2+3 -> 5 | E23: 0 | F23: =SUM(D23:E23) -> 5 | G23: 16 | H23: 5 | I23: =SUM(G23:H23) -> 21 | K23: 4249 | L23: 1204 | M23: =+K23+L23 -> 5453
B24: NO CALIFICADO | D24: 3 | E24: 0 | F24: =SUM(D24:E24) -> 3 | G24: 1 | H24: 0 | I24: =SUM(G24:H24) -> 1 | K24: KM ACUM. ANTERIOR | L24: KM SEMANAL ACTUAL | M24: KM. ACUM. ACTUAL
B25: TOTAL | D25: =SUM(D23:D24) -> 8 | E25: =SUM(E23:E24) -> 0 | F25: =SUM(F23:F24) -> 8 | G25: =SUM(G23:G24) -> 17 | H25: =SUM(H23:H24) -> 5 | I25: =SUM(I23:J24) -> 22 | K25: 3440 | L25: 700 | M25: =+IFERROR(SUM(K25:L25),"-") -> 4140
B28: ASPECTOS HSE | F28: ACUMULADO ANTERIORES | G28: SEMANA ACTUAL | H28: ACUMULADO ACTUAL
B29: Indicadores Reactivos | C29: Accidentes con perdida de tiempo | F29: 0 | G29: 0 | H29: =SUM(F29:G29) -> 0
C30: Accidentes sin perdida de tiempo (tratamiento médico y trabajo restringido) | F30: 0 | G30: 0 | H30: =SUM(F30:G30) -> 0 | K30: TRIF | L30: 0
C31: Primeros Auxilios | F31: 0 | G31: 0 | H31: =SUM(F31:G31) -> 0
C32: Derrames | F32: 0 | G32: 0 | H32: =SUM(F32:G32) -> 0
C33: Incidentes viales | F33: 0 | G33: 0 | H33: =SUM(F33:G33) -> 0
B34: Indicadores de Liderazgo | C34: Casi Accidentes | F34: 0 | G34: 0 | H34: =SUM(F34:G34) -> 0
C35: Fallas de control (condiciones inseguras) | F35: 0 | G35: 0 | H35: =SUM(F35:G35) -> 0 | K35: TAV | L35: 0
C36: Aseguramento comportamientos | F36: 0 | G36: 0 | H36: =SUM(F36:G36) -> 0
C37: Visitas Gerenciales | F37: 0 | G37: 0 | H37: =SUM(F37:G37) -> 0
C38: Alcoholimetrías positivas | F38: 0 | G38: 0 | H38: =SUM(F38:G38) -> 0
B43: 3. BALANCE DE COSTOS
B45: BALANCE DE COSTOS DEL CONTRATO | E45: ACUMULADO CORTE ANTERIOR | G45: IVA | I45: TOTAL
B47: Valor del contrato CD | E47: 151047896473 | G47: =(E47*5%)*19% -> 1.434955e+09 | I47: =SUM(E47:H47) -> 1.5248285e+11
B48: AIU 38% | E48: =+E47*0.38 -> 5.7398201e+10 | I48: =SUM(E48:H48) -> 5.7398201e+10
B49: Valor del contrato CD+AIU | E49: =+E47+E48 -> 2.084461e+11 | I49: =SUM(E49:H49) -> 2.084461e+11
B50: Gastos Reembolsables | E50: =+E49*10% -> 2.084461e+10 | I50: =SUM(E50:H50) -> 2.084461e+10
B51: Administracion Gastos Reembolsables | E51: =+E50*1% -> 2.084461e+08 | I51: =SUM(E51:H51) -> 2.084461e+08
B52: Cambios de Alcance Aprobados | E52: 0 | I52: =SUM(E52:H52) -> 0
B53: Total costo directo + AIU + ADM GR | E53: =+E49+E51 -> 2.0865454e+11 | G53: =SUM(G47:H52) -> 1.434955e+09 | I53: =SUM(E53:H53) -> 2.100895e+11
B54: Valor facturado | E54: 0 | G54: 0 | I54: =SUM(E54:H54) -> 0
B56: ESTATUS DE EJECUCIÓN | E56: EJECUTADO ACUMULADO SEMANA ANTERIOR | H56: EJECUTADO SEMANA ACTUAL | K56: EJECUTADO ACUMULADO SEMANA ACTUAL
B57: COSTO DIRECTO | E57: =+'C3'!I19/1.38 -> 50412689 | H57: =+'C3'!J20/1.38 -> 10293807 | K57: =+E57+H57 -> 60706495
B58: COSTO DIRECTO + AIU | E58: =+E57*1.38 -> 69569510 | H58: =+H57*1.38 -> 14205453 | K58: =+E58+H58 -> 83774963
B59: IVA | E59: =(E57*5%)*19% -> 478920.54 | H59: =(H57*5%)*19% -> 97791.163 | K59: =+E59+H59 -> 576711.71
B60: TOTAL CD+AIU+IVA | E60: =SUM(E58:G59) -> 70048431 | H60: =+H58+H59 -> 14303244 | K60: =+E60+H60 -> 84351675
B63: 4. CURVA S
B87: 4. CURVA S
B111: 5. RESUMEN PROGRESO DEL CONTRATO
B113: ACTIVIDAD / PAQUETE | E113: Peso % Relativo | F113: Fecha Comienzo Planeado | G113: Fecha Fin Planeado | H113: Fecha Fin Real o Pronóstico | I113: PLAN | K113: REAL | M113: DIFERENCIAS
I114: % Plan Acumulado semana Actual | K114: % Real Semana Actual | L114: % Real Acumulado semana Actual | M114: % Diferencia Acumulada
B115: =+'PDT ODS02 EARLY'!C34 -> PISCINA INDUSTRIAL | E115: =+'PDT ODS02 EARLY'!F34 -> 0.0022153966 | F115: =+'PDT ODS02 EARLY'!G34 -> 46240 | G115: =+'PDT ODS02 EARLY'!H34 -> 46276 | H115: =+G115 -> 46276 | I115: =+'PDT ODS02 EARLY'!P34 -> 0 | K115: =+REAL!P34-REAL!O34 -> 0 | L115: =+REAL!P34 -> 0 | M115: =+L115-I115 -> 0
B116: =+'PDT ODS02 EARLY'!C39 -> ZONAS DE CAMPAMENTOS - FAENAS | E116: =+'PDT ODS02 EARLY'!F39 -> 0.040123744 | F116: =+'PDT ODS02 EARLY'!G39 -> 46256 | G116: =+'PDT ODS02 EARLY'!H39 -> 46596 | H116: =+G116 -> 46596 | I116: =+'PDT ODS02 EARLY'!P39 -> 0.00042802934 | K116: =+REAL!P39-REAL!O39 -> 0.00074752953 | L116: =+REAL!P39 -> 0.00099844328 | M116: =+L116-I116 -> 0.00057041394
B117: =+'PDT ODS02 EARLY'!C44 -> EJECUCIÓN DE ACTIVIDADES DE CIMENTACIONES EXISTENTES | E117: =+'PDT ODS02 EARLY'!F44 -> 0.030994405 | F117: =+'PDT ODS02 EARLY'!G44 -> 46244 | G117: =+'PDT ODS02 EARLY'!H44 -> 46352 | H117: =+G117 -> 46352 | I117: =+'PDT ODS02 EARLY'!P44 -> 0.12988095 | K117: =+REAL!P44-REAL!O44 -> 0 | L117: =+REAL!P44 -> 0.14571429 | M117: =+L117-I117 -> 0.015833333
B118: =+'PDT ODS02 EARLY'!C109 -> EJECUCIÓN DE ACTIVIDADES DE CIMENTACIONES NUEVAS | E118: =+'PDT ODS02 EARLY'!F109 -> 0.86603385 | F118: =+'PDT ODS02 EARLY'!G109 -> 46240 | G118: =+'PDT ODS02 EARLY'!H109 -> 46606 | H118: =+G118 -> 46606 | I118: =+'PDT ODS02 EARLY'!P109 -> 0.0047857084 | K118: =+REAL!P109-REAL!O109 -> 9.2256976e-05 | L118: =+REAL!P109 -> 0.0014761116 | M118: =+L118-I118 -> -0.0033095968
B119: =+'PDT ODS02 EARLY'!C689 -> EJECUCIÓN DE ACTIVIDADES CONFORMACIÓN DE ZODMES | E119: =+'PDT ODS02 EARLY'!F689 -> 0.0043622719 | F119: =+'PDT ODS02 EARLY'!G689 -> 46246 | G119: =+'PDT ODS02 EARLY'!H689 -> 46604 | H119: =+G119 -> 46604 | I119: =+'PDT ODS02 EARLY'!P689 -> 0.030433226 | K119: =+REAL!P689-REAL!O689 -> 0 | L119: =+REAL!P689 -> 0 | M119: =+L119-I119 -> -0.030433226
B120: =+'PDT ODS02 EARLY'!C695 -> EJECUCIÓN DE ACTIVIDADES POR LLAMADO DE MAQUINARIA, EQUIPOS Y PERSONAL | E120: =+'PDT ODS02 EARLY'!F695 -> 0.056270334 | F120: =+'PDT ODS02 EARLY'!G695 -> 46534 | G120: =+'PDT ODS02 EARLY'!H695 -> 46603 | H120: =+G120 -> 46603 | I120: =+'PDT ODS02 EARLY'!P695 -> 0 | K120: =+REAL!P695-REAL!O695 -> 0 | L120: =+REAL!P695 -> 0 | M120: =+L120-I120 -> 0
B121: =+'PDT ODS02 EARLY'!C699 -> ACTIVIDADES FINALES | E121: =+'PDT ODS02 EARLY'!F699 -> 0 | F121: =+'PDT ODS02 EARLY'!G699 -> 46606 | G121: =+'PDT ODS02 EARLY'!H699 -> 46617 | H121: =+G121 -> 46617 | I121: =+'PDT ODS02 EARLY'!O699 -> 0 | K121: =+REAL!P699-REAL!O699 -> 0 | L121: =+REAL!P699 -> 0 | M121: =+L121-I121 -> 0
M122: =+L122-I122 -> 0
M123: =+L123-I123 -> 0
M124: =+L124-I124 -> 0
M125: =+L125-I125 -> 0
M126: =+L126-I126 -> 0
M127: =+L127-I127 -> 0
M128: =+L128-I128 -> 0
M129: =+L129-I129 -> 0
M130: =+L130-I130 -> 0
M131: =+L131-I131 -> 0
M132: =+L132-I132 -> 0
M133: =+L133-I133 -> 0
... M137: =+L137-I137 -> 0
E138: =SUM(E115:E137) -> 1 | I138: =+SUMPRODUCT(I115:I137,$E$115:$E$137) -> 0.0083201005 | K138: =+SUMPRODUCT(K115:K137,$E$115:$E$137) -> 0.00010989135 | L138: =+SUMPRODUCT(L115:L137,$E$115:$E$137) -> 0.0058347515 | M138: =+L138-I138 -> -0.002485349
B141: 6. ACTIVIDADES REALIZADAS Y A REALIZAR
B143: ACTIVIDADES DEL PERIODO | H143: ACTIVIDADES DEL PROXIMO PERIODO
B144: Topografía: Avance en la localización, replanteo y levantamiento de los ZODME 16, 1, 3 y 2, así como materialización de puntos de control en las plataformas WP-44, WP-45, WP-48 y WP-49. Adicionalmente, se realizó la georreferenciación de límites comunitarios y el replanteo para la ubicación de contenedores en faena. Obras civiles / Faena: Avance en la habilitación de la faena, con el replanteo y posterior descargue de contenedores de oficinas y dormitorio, además de un tanque de almacenamiento de 125.000 litros y un generador de 45 kVA. Ingeniería: Continuidad en la revisión de la ingeniería del proyecto, incluyendo la revisión del sistema eléctrico de las plataformas y coordinación de aspectos técnicos asociados al desarrollo de las obras. Ambiental: Ejecución de actividades de ahuyentamiento de fauna y aprovechamiento forestal en las áreas destinadas a faena y piscina industrial, además de inducciones y sensibilizaciones ambientales al personal. Gestión social: Avance en la socialización e inicio de obra con las comunidades, acompañamiento a las comisiones topográficas y coordinación de guías comunitarios para facilitar el acceso a los sectores de trabajo. Gestión técnica: Seguimiento a la entrega de los manuales de instalación de los anchor cages, requeridos para continuar con la gestión técnica y de calidad. | H144: Continuar con las actividades de revisión de la ingeniería, así como la consolidación de la documentación técnica requerida para la ejecución. Dar continuidad a las actividades de topografía, completando el levantamiento y replanteo de las plataformas y ZODME priorizados para habilitar los primeros frentes de obra. Continuar con la gestión y seguimiento al suministro de materiales críticos, especialmente los requeridos para el inicio de las cimentaciones. Ejecutar las actividades de socialización y relacionamiento comunitario programadas, dando continuidad a los compromisos establecidos con las comunidades del área de influencia.
B161: ACTIVIDADES CLAVES A 15 DÍAS
B162: Topografía: Continuidad de levantamientos y replanteos en WP-34, WP-35 y WP-42. Ambiental: Continuidad de ahuyentamiento de fauna silvestre y aprovechamiento forestal en WP-44, WP-45, WP-46, WP-50, WP-51, WP-52 y WP-53, junto con las áreas de faena y piscina industrial. Obra civil – Piscina y recalces: Avance en cerramiento, excavación, instalación de geomembrana y escaneo de aceros en WP-44, WP-45 y WP-46, incluyendo el alistamiento para los recalces. Adecuación de faena: Continuidad de la adecuación del campamento y preparación de las áreas asociadas a WP-44, WP-45 y WP-46. Cimentaciones nuevas: Inicio de actividades de cimentaciones en WP-50 y WP-53, constituyéndose como una de las principales actividades de ejecución previstas para el período.
B179: 7. HITOS RELEVANTES
B181: HITOS | F181: FECHA PLAN | G181: ESTADO | H181: FECHA PROYECTADA / REAL
B182: HITO 1: ACTA DE INICIO | F182: mié 15/07/26 | H182: mié 15/07/26 | K182: A Tiempo
B183: HITO 2: INICIO DE ACTIVIDADES EN CAMPO | F183: jue 6/08/26 | H183: jue 16/07/26 | K183: Con Atraso
B184: HITO 3: FIN DE ACTIVIDADES DE RECALCE | F184: mar 17/11/26 | H184: mar 17/11/26 | K184: En Alerta
B185: HITO 4: FIN DE CIMENTACIONES | F185: lun 2/08/27 | H185: lun 2/08/27 | K185: Cumplido a Tiempo
B186: HITO 5: FIN DE ACTIVIDADES DE OBA | F186: lun 2/08/27 | H186: lun 2/08/27 | K186: Cumplido fuera de Tiempo
B187: HITO 6: ACTA DE TERMINACIÓN DE LA ODS | F187: mié 18/08/27 | H187: mié 18/08/27
B192: 8. ALERTAS, RIESGOS Y RUTA CRÍTICA
B194: ANÁLISIS DE DESVIACIONES Y ACCIONES PARA VOLVER AL PLAN
B195: Durante el período reportado se evidencia un avance progresivo en la habilitación de los frentes de trabajo, con la reactivación de las actividades topográficas y el inicio de la adecuación y dotación de la faena. No obstante, se presentó una restricción puntual en el acceso a las plataformas WP-14 y WP-15 por condiciones asociadas a la delimitación comunitaria, generando la reprogramación de las actividades previstas en estas áreas. Como acciones para mantener la recuperación frente al plan, se prioriza la continuidad de los levantamientos y replanteos topográficos en sectores habilitados, la culminación de la instalación y puesta en operación de la infraestructura de faena y el seguimiento a la gestión social requerida para garantizar el acceso a las áreas de intervención. De manera paralela, se mantiene la revisión de ingeniería y documentación técnica, con el fin de asegurar la disponibilidad de los habilitadores necesarios y evitar nuevas afectaciones sobre la programación.
B203: ALERTAS Y RIEGOS IDENTIFICADOOS
B204: Acceso a frentes: Se mantiene como principal alerta la gestión de acceso a las áreas de intervención, evidenciada por la restricción presentada en las plataformas WP-14 y WP-15 debido a condiciones asociadas a la delimitación comunitaria. Gestión social: Existe riesgo de nuevas restricciones si no se consolidan previamente los acuerdos y acompañamientos requeridos con las comunidades para el ingreso a los diferentes sectores.
B214: 9. FOTOGRAFÍAS
B229: Fecha: 24/08/2026 Ubicación: WP-44 y WP-45 Descripción: Materializacion Puntos de control WP-44 y WP-45 | G229: Fecha: 24/08/2026 Ubicación: Piscina industrial Descripción: Replanteo de piscina industrial | K229: Fecha: 24/08/2026 Ubicación: WP-48 Descripción: Materializacion Puntos de control WP-48
B245: Fecha: 25/08/2026 Ubicación: Zodme 3 Descripción: Replanteo y levantamiento Zodme 3 | G245: Fecha: 26/08/2026 Ubicación: Base Uribia Descripción: Induccion personal nuevo ingreso | K245: Fecha: 27/08/2026 Ubicación: Comunidad kalincho sector cañaveral Descripción: Reunion incio de obra comunidad kalincho sector cañaveral
B250: Este documento hace parte del procedimiento EDP-P-016 Procedimiento de Control y Seguimiento para Contratistas. Todos los derechos reservados para Ecopetrol S.A. Ninguna reproducción externa copia o transmisión digital de esta publicación puede ser hecha sin permiso escrito. Ningún párrafo de esta publicación puede ser reproducido, copiado o transmitido digitalmente sin un consentimiento escrito o de acuerdo con las leyes que regulan los derechos de autor y con base en la regulación vigente. Este formato se diligencia electrónicamente y no requiere firmas (Se considera validado una vez se envié por correo electrónico por parte del responsable). 1/2

Sheet C3
E2: Formato Informe Semanal Proyectos Contratistas | M2: Contrato nro W381147
E4: Ecopetrol Desarrollo de Proyectos Vicepresidencias De Desarrollo y Proyectos
E6: EDP-F-052 | G6: Elaborado 02/11/2023 | K6: Versión 4
A9: En esta pestaña se debe incluir el detalle del C3 del contratitsta para el cálculo del progreso.
C10: S0 | D10: S1 | E10: S2 | F10: S3 | G10: S4 | H10: S5 | I10: S6 | J10: S7 | K10: S8 | L10: S9 | M10: S10 | N10: S11 | O10: S12 | P10: S13 | Q10: S14 | R10: S15 | S10: S16 | T10: S17 | U10: S18 | V10: S19 | W10: S20 | X10: S21 | Y10: S22 | Z10: S23 | AA10: S24 | AB10: S25 | AC10: S26 | AD10: S27 | AE10: S28 | AF10: S29 | AG10: S30 | AH10: S31 | AI10: S32 | AJ10: S33 | AK10: S34 | AL10: S35 | AM10: S36 | AN10: S37 | AO10: S38 | AP10: S39 | AQ10: S40 | AR10: S41 | AS10: S42 | AT10: S43 | AU10: S44 | AV10: S45 | AW10: S46 | AX10: S47 | AY10: S48 | AZ10: S49 | BA10: S50 | BB10: S51 | BC10: S52 | BD10: S53 | BE10: S54 | BF10: S55 | BG10: S56 | BH10: S57 | BI10: S58
C11: S0 | D11: =+C12 -> 46218 | E11: =+D12 -> 46220 | F11: =+E12 -> 46227 | G11: =+F12 -> 46234 | H11: =+G12 -> 46241 | I11: =+H12 -> 46248 | J11: =+I12 -> 46255 | K11: =+J12 -> 46262 | ... BI11: =+BH12 -> 46612
C12: 46218 | D12: =+D11+2 -> 46220 | E12: =+D12+7 -> 46227 | F12: =+E12+7 -> 46234 | G12: =+F12+7 -> 46241 | H12: =+G12+7 -> 46248 | I12: =+H12+7 -> 46255 | J12: =+I12+7 -> 46262 | K12: =+J12+7 -> 46269 | L12: =+K12+7 -> 46276 | ... BI12: =+BH12+7 -> 46619
A13: Plan Acum. Semana | C13: =+'PDT ODS02 EARLY'!I7 -> 0 | D13: =+'PDT ODS02 EARLY'!J7 -> 0 | E13: =+'PDT ODS02 EARLY'!K7 -> 0 | F13: =+'PDT ODS02 EARLY'!L7 -> 0 | G13: =+'PDT ODS02 EARLY'!M7 -> 7.9897664e-05 | H13: =+'PDT ODS02 EARLY'!N7 -> 0.0013001487 | I13: =+'PDT ODS02 EARLY'!O7 -> 0.0041150005 | J13: =+'PDT ODS02 EARLY'!P7 -> 0.0083201005 | ... BI13: =+'PDT ODS02 EARLY'!BO7 -> 1
A14: Real Acum. Semana | C14: =+REAL!I7 -> 1.3902875e-05 | D14: =+REAL!J7 -> 4.1708625e-05 | E14: =+REAL!K7 -> 0.00012512587 | F14: =+REAL!L7 -> 0.00017310339 | G14: =+REAL!M7 -> 0.00023988759 | H14: =+REAL!N7 -> 0.00029899581 | I14: =+REAL!O7 -> 0.000333753 | J14: =+REAL!P7 -> 0.00040190229 | K14: 0.00040190229
A15: Plan Semana | C15: =+C13 -> 0 | D15: =+D13-C13 -> 0 | E15: =+E13-D13 -> 0 | F15: =+F13-E13 -> 0 | G15: =+G13-F13 -> 7.9897664e-05 | H15: =+H13-G13 -> 0.0012202511 | I15: =+I13-H13 -> 0.0028148518 | J15: =+J13-I13 -> 0.0042050999 | K15: =+K13-J13 -> 0.0056878277 | ... BI15: =+BI13-BH13 -> 0
A16: Real Semana | C16: =+REAL!I7 -> 1.3902875e-05 | D16: =+REAL!J7-REAL!I7 -> 2.780575e-05 | E16: =+REAL!K7-REAL!J7 -> 8.3417249e-05 | F16: =+REAL!L9-REAL!K9 -> 0 | G16: =+REAL!M9-REAL!L9 -> 0 | H16: =+REAL!N9-REAL!M9 -> 0 | I16: =+REAL!O9-REAL!N9 -> 0 | J16: =+REAL!P9-REAL!O9 -> 0
A17: Pronóstico Acum. | K17: 0.0004 | L17: =+'PDT ODS02 EARLY'!R7 -> 0.022352659 | M17: =+'PDT ODS02 EARLY'!S7 -> 0.03131998 | N17: =+'PDT ODS02 EARLY'!T7 -> 0.045385517 | O17: =+'PDT ODS02 EARLY'!U7 -> 0.060855714 | P17: =+'PDT ODS02 EARLY'!V7 -> 0.087795191 | Q17: =+'PDT ODS02 EARLY'!W7 -> 0.10764759 | R17: =+'PDT ODS02 EARLY'!X7 -> 0.13055656 | S17: =+'PDT ODS02 EARLY'!Y7 -> 0.16313478 | ... BI17: =+'PDT ODS02 EARLY'!BO7 -> 1
A18: Presupuesto Plan Acum. Semana | C18: =+'PDT ODS02 EARLY'!I5 -> 0 | D18: =+'PDT ODS02 EARLY'!J5 -> 0 | E18: =+'PDT ODS02 EARLY'!K5 -> 0 | F18: =+'PDT ODS02 EARLY'!L5 -> 0 | G18: =+'PDT ODS02 EARLY'!M5 -> 16654356 | H18: =+'PDT ODS02 EARLY'!N5 -> 2.7101093e+08 | I18: =+'PDT ODS02 EARLY'!O5 -> 8.577558e+08 | J18: =+'PDT ODS02 EARLY'!P5 -> 1.7342925e+09 | ... BI18: =+'PDT ODS02 EARLY'!BO5 -> 2.084461e+11
A19: Presupuesto Real Acum. Semana | C19: =+REAL!I5 -> 2898000 | D19: =+REAL!J5 -> 8694000 | E19: =+REAL!K5 -> 26082000 | F19: =+REAL!L5 -> 36082727 | G19: =+REAL!M5 -> 50003633 | H19: =+REAL!N5 -> 62324510 | I19: =+REAL!O5 -> 69569510 | J19: =+REAL!P5 -> 83774963 | K19: 83774963
A20: Presupuesto Real Semana | C20: =+REAL!I5 -> 2898000 | D20: =+REAL!J5-REAL!I5 -> 5796000 | E20: =+REAL!K5-REAL!J5 -> 17388000 | F20: =+REAL!L5-REAL!K5 -> 10000727 | G20: =+REAL!M5-REAL!L5 -> 13920906 | H20: =+REAL!N5-REAL!M5 -> 12320878 | I20: =+REAL!O5-REAL!N5 -> 7245000 | J20: =+REAL!P5-REAL!O5 -> 14205453
A21: Este documento hace parte del procedimiento EDP-P-016 Procedimiento de Control y Seguimiento para Contratistas. Todos los derechos reservados para Ecopetrol S.A. Ninguna reproducción externa copia o transmisión digital de esta publicación puede ser hecha sin permiso escrito. Ningún párrafo de esta publicación puede ser reproducido, copiado o transmitido digitalmente sin un consentimiento escrito o de acuerdo con las leyes que regulan los derechos de autor y con base en la regulación vigente. Este formato se diligencia electrónicamente y no requiere firmas (Se considera validado una vez se envié por correo electrónico por parte del responsable). 2/2

Sheet Alcance Cimentaciones
A1: “CONTRATOS MARCO PARA OBRAS ASOCIADAS A LOS PROYECTOS EÓLICOS EN EL DEPARTAMENTO DE LA GUAJIRA PARA ECOPETROL Y SU GRUPO EMPRESARIAL” Alcance 2: Cimentaciones de gran volumen
H2: 1.510479e+11
H3: 5.7398201e+10
H4: 2.084461e+11
A5: ESPECIALIDAD | B5: ITEM | C5: DESCRIPCIÓN DE PARTIDA ASOCIADA | D5: DESCRIPCIÓN | E5: UND PAGO | F5: CANTIDAD CIMENTACIONES | G5: VR UNIT | H5: Vr TOTAL CIMENTACIONES | I5: 1
A6: CIV | B6: 1. OBRAS CIVILES
A7: CIV | B7: 1.1. PRELIMINARES
A8: CIV | B8: 1.1.1 | C8: 6.1. DMP DESBROCE Y LIMPIEZA | D8: DESBROCE Y LIMPIEZA | E8: m2 | F8: 163167 | G8: 4140 | H8: 675511380
A9: CIV | B9: 1.1.2 | C9: 6.2 DMP ROCERÍA, INCLUYE TALA DE ARBOLES CON DAP ≤ A 0.15 m, INCLUYE TRANSPORTE Y DISPOSICIÓN FINAL | D9: ROCERÍA, INCLUYE TALA DE ARBOLES CON DAP ≤ A 0.15 m, INCLUYE TRANSPORTE Y DISPOSICIÓN FINAL | E9: m2 | F9: 0 | G9: 12785 | H9: 0
A10: CIV | B10: 1.1.3 | C10: 6.3 DMP TALA DE ÁRBOLES CON DAP>0.15M, INCLUYE TRANSPORTE Y DISPOSICIÓN FINAL | D10: DMP TALA DE ÁRBOLES CON DAP>0.15M, INCLUYE TRANSPORTE Y DISPOSICIÓN FINAL | E10: Und | F10: 0 | G10: 680000 | H10: 0
A11: CIV | B11: 1.1.4 | C11: 6.4. DMP DESMONTE, DESCAPOTE Y LIMPIEZA | D11: DESMONTE, DESCAPOTE Y LIMPIEZA INCLUYE TALA DE ARBOLES CON DAP ≤0.15M, TRANSPORTE Y DISPOSICIÓN FINAL | E11: m2 | F11: 163167 | G11: 7121 | H11: 1161912207
A12: CIV | B12: 1.1.5 | C12: 6.5. DMP CAMPAMENTOS (ZONA DE FAENAS) | D12: CAMPAMENTOS ( ZONA DE FAENAS) | E12: MES
A13: CIV | B13: 1.1.5.1 | C13: 6.5.1. DMP ALQUILER DE CONTENEDOR 40 FT SALA REUINIONES / OFICINA | D13: ALQUILER DE CONTENEDOR 40 FT SALA REUINIONES / OFICINA | E13: MES | F13: 405 | G13: 4252868 | H13: 1722411540
A14: CIV | B14: 1.1.5.2 | C14: 6.5.2. DMP ALQUILER DE CONTENEDOR 40 FT CAFETERIA | D14: ALQUILER DE CONTENEDOR 40 FT CAFETERIA | E14: MES | F14: 75 | G14: 4252868 | H14: 318965100
A15: CIV | B15: 1.1.5.3 | C15: 6.5.3. DMP ALQUILER DE CONTENEDOR 40 FT ATENCIÓN EMERGENCIA | D15: ALQUILER DE CONTENEDOR 40 FT ATENCIÓN EMERGENCIA | E15: MES | F15: 15 | G15: 4473440 | H15: 67101600
A16: CIV | B16: 1.1.5.4 | C16: 6.5.4. DMP ALQUILER DE CONTENEDOR 40 FT BODEGA | D16: ALQUILER DE CONTENEDOR 40 FT BODEGA | E16: MES | F16: 15 | G16: 3811724 | H16: 57175860
A17: CIV | B17: 1.1.5.5 | C17: 6.5.5 DMP ALQUILER DE CONTENEDOR 40 FT CASILLEROS Y VESTIERES | D17: ALQUILER DE CONTENEDOR 40 FT CASILLEROS Y VESTIERES | E17: MES | F17: 30 | G17: 3811724 | H17: 114351720
A18: CIV | B18: 1.1.5.6 | C18: 6.5.6. DMP ALQUILER GENERADOR ELECTRICO 150 KVA | D18: ALQUILER GENERADOR ELECTRICO 150 KVA | E18: MES | F18: 15 | G18: 48667800 | H18: 730017000
A19: CIV | B19: 1.1.5.7 | C19: 6.5.7. DMP ALQUILER BATERÍA DE BAÑOS CON SERVICIO DE ASEO | D19: ALQUILER BATERÍA DE BAÑOS CON SERVICIO DE ASEO | E19: MES | F19: 30 | G19: 2704032 | H19: 81120960
A20: CIV | B20: 1.1.5.8 | C20: 6.5.8. DMP SERVICIO DE AMBULANCIA TIPO TAM | D20: SERVICIO DE AMBULANCIA TIPO TAM | E20: MES | F20: 15 | G20: 75157500 | H20: 1127362500
A21: CIV | B21: 1.1.5.9 | C21: 6.5.9. DMP ALQUILER TANQUE ALMACENAMIENTO AGUA 50 M3 | D21: ALQUILER TANQUE ALMACENAMIENTO AGUA 50 M3 | E21: MES | F21: 30 | G21: 6743000 | H21: 202290000
A22: CIV | B22: 1.1.5.10 | C22: 6.5.10. DMP SUMINISTRO DE AGUA PARA CAMPAMENTO | D22: SUMINISTRO DE AGUA PARA CAMPAMENTO | E22: m3 | F22: 2700 | G22: 360618 | H22: 973668600
A23: CIV | B23: 1.1.5.11 | C23: 6.5.11. DMP SERVICIO DE VIGILACIA DEL CAMPAMENTO 24 HORAS EN EL AREA DE FAENAS | D23: SERVICIO DE VIGILACIA DEL CAMPAMENTO 24 HORAS EN EL AREA DE FAENAS | E23: MES | F23: 15 | G23: 33500000 | H23: 502500000
A24: CIV | B24: 1.1.5.12 | C24: 6.5.12. DMP SERVICIO DE ASEO EN EL AREA DE CAMPAMENTOS (FAENAS) | D24: SERVICIO DE ASEO EN EL AREA DE CAMPAMENTOS (FAENAS) | E24: MES | F24: 15 | G24: 10489481 | H24: 157342215
A25: CIV | B25: 1.2. MOVIMIENTO DE TIERRA
A26: CIV | B26: 1.2.1 | C26: 6.6. DMP EXCAVACIÓN MANUAL EN MATERIAL COMÚN | D26: EXCAVACIÓN MANUAL EN MATERIAL COMÚN | E26: m3 | F26: 0 | G26: 397150 | H26: 0
A27: CIV | B27: 1.2.2 | C27: 6.7. DMP EXCAVACIÓN MECÁNICA EN MATERIAL COMÚN | D27: EXCAVACIÓN MECÁNICA EN MATERIAL COMÚN | E27: m3 | F27: 163167 | G27: 35495 | H27: 5791612665
A28: CIV | B28: 1.2.3 | C28: 6.8. DMP EXCAVACIÓN MANUAL EN MATERIAL COMÚN CON NIVEL FREÁTICO. INCLUYE TRANSPORTE A UNA DISTANCIA ≤ A 1KM | D28: EXCAVACIÓN MANUAL EN MATERIAL COMÚN CON NIVEL FREÁTICO. INCLUYE TRANSPORTE A UNA DISTANCIA ≤ A 1KM | E28: m3 | G28: 420000 | H28: 0
A29: CIV | B29: 1.2.4 | C29: 6.9. DMP EXCAVACIÓN PARA REPARACIÓN DE PAVIMENTO ASFALTICO EXISTENTE, INCLUYE EL CORTE Y LA REMOCIÓN DE LAS CAPAS ASFÁLTICA SUBYACENTES | D29: EXCAVACIÓN PARA REPARACIÓN DE PAVIMENTO ASFALTICO EXISTENTE, INCLUYE EL CORTE Y LA REMOCIÓN DE LAS CAPAS ASFÁLTICA SUBYACENTES | E29: m3 | F29: 0 | G29: 825364 | H29: 0
A30: CIV | B30: 1.2.5 | C30: 6.10. DMP EXCAVACIÓN EN ROCA | D30: EXCAVACIÓN EN ROCA | E30: m3 | F30: 14088 | G30: 135191 | H30: 1904570808
A31: CIV | B31: 1.2.6 | C31: 6.11. DMP EXCAVACIÓN Y RELLENO COMPENSADO | D31: EXCAVACIÓN Y RELLENO COMPENSADO | E31: m3 | F31: 0 | G31: 67508 | H31: 0
A32: CIV | B32: 1.2.7 | C32: 6.12. DMP DEMOLICIÓN MANUAL Y MECÁNICA | D32: DEMOLICIÓN MANUAL Y TRITURACIÓN DE ELEMENTOS Y ESTRUCTURAS DE CONCRETO | E32: m3 | F32: 0 | G32: 1010418 | H32: 0
A33: CIV | B33: 1.2.7A | C33: 6.12. DMP DEMOLICIÓN MANUAL Y MECÁNICA | D33: DEMOLICIÓN MECÁNICA Y TRITURACIÓN DE ELEMENTOS Y ESTRUCTURAS DE CONCRETO | E33: m3 | F33: 0 | G33: 671437 | H33: 0
A34: CIV | B34: 1.2.8 | C34: 6.13. DMP DEMOLICIÓN MANUAL DE CONCRETO | D34: DEMOLICIÓN MANUAL DE CONCRETO | E34: m3 | F34: 0 | G34: 1013292 | H34: 0
A35: CIV | B35: 1.2.9 | C35: 6.14. DMP DEMOLICIÓN MECÁNICA DE CONCRETO | D35: DEMOLICIÓN MECÁNICA DE CONCRETO | E35: m3 | F35: 0 | G35: 559531 | H35: 0
A36: CIV | B36: 1.2.10 | C36: 6.14. DMP DEMOLICIÓN DE PAVIMENTO FLEXIBLE | D36: DEMOLICIÓN DE PAVIMENTO FLEXIBLE | E36: m3 | F36: 0 | G36: 510299 | H36: 0
A37: CIV | B37: 1.2.11 | C37: 6.16. DMP DEMOLICIÓN MUROS EN MAMPOSTERÍA | D37: DEMOLICIÓN MUROS EN MAMPOSTERÍA | E37: m2 | F37: 0 | G37: 70953 | H37: 0
A38: CIV | B38: 1.2.12 | C38: 6.17. DMP DESMANTELAMIENTO CERRAMIENTO EN ALAMBRE DE PÚAS | D38: DESMANTELAMIENTO CERRAMIENTO EN ALAMBRE DE PÚAS | E38: ml | F38: 0 | G38: 17208 | H38: 0
A39: CIV | B39: 1.2.13 | C39: 6.18. DMP ACARREO DE MATERIAL. DISTANCIA > 2.0 km, INCLUYE CARGUE | D39: ACARREO DE MATERIAL. DISTANCIA > 2.0 km, INCLUYE CARGUE | E39: m3-Km | F39: 0 | G39: 2800 | H39: 0
A40: CIV | B40: 1.2.14 | C40: 6.19. DMP COMPACTACIÓN MANUAL | D40: COMPACTACIÓN MANUAL | E40: m3 | F40: 0 | G40: 198575 | H40: 0
... A75: CIV | B75: 1.2.47 | C75: 6.44. DMP CONFORMACIÓN DE ZODME CON RETROEXCAVADORA O BULLDOZER | D75: CONFORMACIÓN DE ZODME CON RETROEXCAVADORA O BULLDOZER INCLUYE LA MAQUINARIA REQUERIDA PARA LA CONFORMACION Y COMPACTACION. | E75: m3 | F75: 22336 | G75: 29500 | H75: 658912000
A76: CIV | B76: 1.3. SUMINISTRO E INSTALACIÓN DE GEOTEXTILES
A77: CIV | B77: 1.3.1 | C77: 6.45. DMP SUMINISTRO E INSTALACIÓN DE GEOTEXTILES | D77: SUMINISTRO E INSTALACIÓN DE GEOTEXTILES | E77: m2 | F77: 30164 | G77: 54177 | H77: 1634195028
A78: CIV | B78: 1.3.2 | C78: 6.46. DMP SUMINISTRO Y CONSTRUCCIÓN DE FILTRO FRANCÉS | D78: SUMINISTRO Y CONSTRUCCIÓN DE FILTRO FRANCÉS | E78: m3 | F78: 0 | G78: 937187 | H78: 0
A79: CIV | B79: 1.4. SUMINISTRO. CONSTRUCCION E INSTALACION DE OBRAS DE PROTECCIÓN
A80: CIV | B80: 1.4.1 | C80: 6.47. DMP ENROCADOS | D80: ENROCADO PROTECCIÓN TALUD PLATAFORMAS PROTECCIÓN CON ENROCADO DE PIEDRA DEL TALUD DE LAS PLATAFORMAS EN TERRAPLÉN CON 30 CM DE PIEDRA DE 6-10 CM DE DIÁMETRO, PESO ESPECÍFICO DE LAS PIEDRAS DE 2,64 G/CM3 (INCLUYE TRANSPORTE DESDE LAS CANTERAS LICENCIADAS HASTA EL SITIO DE INSTALACIÓN) | E80: m3 | F80: 1440 | G80: 276393 | H80: 398005920
A81: CIV | B81: 1.4.2 | C81: 6.47. DMP ENROCADOS | D81: ENROCADO PROTECCIÓN TALUD CIMENTACION PROTECCIÓN CON ENROCADO DE PIEDRA DEL TALUD DE LAS CIMENTACIONES EN TERRAPLÉN CON 30 CM DE PIEDRA DE 6-10 CM DE DIÁMETRO, PESO ESPECÍFICO DE LAS PIEDRAS DE 2,64 G/CM3 (INCLUYE TRANSPORTE DESDE LAS CANTERAS LICENCIADAS HASTA EL SITIO DE INSTALACIÓN) | E81: m3 | F81: 868 | G81: 286818 | H81: 248958024
A82: CIV | B82: 1.5. CONSTRUCCIÓN PARA PREPARACIÓN. SUMINISTRO E INSTALACION DE ESTRUCTURAS Y OBRAS EN CONCRETO.
A83: CIV | B83: 1.5.1 | C83: 6.48. DMP CONCRETOS | D83: CONCRETO ESTRUCTURAL 35 MPa(350 kg/cm2 Ó 5000 psi) | E83: m3 | F83: 14587 | G83: 1926653 | H83: 28104087311
A84: CIV | B84: 1.5.2 | C84: 6.48. DMP CONCRETOS | D84: CONCRETO ESTRUCTURAL 45 MPa(457 kg/cm2 Ó 6500psi) | E84: m3 | F84: 1088 | G84: 2040759 | H84: 2220345792
A85: CIV | B85: 1.5.2.A | C85: 6.48. DMP CONCRETOS | D85: CONCRETO CLASE C (280 kg/cm2 Ó 4000 psi) | E85: m3 | F85: 0 | G85: 2150811 | H85: 0
A86: CIV | B86: 1.5.2.B | C86: 6.48. DMP CONCRETOS | D86: CONCRETO CLASE D (210 kg/cm2 Ó 3000 psi) | E86: m3 | F86: 0 | G86: 2029072 | H86: 0
A87: CIV | B87: 1.5.2.C | C87: 6.48. DMP CONCRETOS | D87: CONCRETO CLASE E (175 kg/cm2 Ó 2500 psi) | E87: m3 | F87: 0 | G87: 1976698 | H87: 0
A88: CIV | B88: 1.5.3 | C88: 6.48. DMP CONCRETOS | D88: CONCRETO CLASE F (140 kg/cm2 Ó 2000 psi) | E88: m3 | F88: 1494 | G88: 1555169 | H88: 2323422486
A89: CIV | B89: 1.5.4 | C89: 6.49. DMP GROUT Y MORTERO AUTOCOMPACTANTE DE ALTA RESISTENCIA C80/95 (EN206-1) | D89: GROUT Y MORTERO AUTOCOMPACTANTE DE ALTA RESISTENCIA C80/95 (EN206-1) | E89: lt | F89: 21760 | G89: 63367 | H89: 1378865920
A90: CIV | B90: 1.5.5 | C90: 6.50. DMP SUMINISTRO E INSTALACIÓN DE ADITIVO EPÓXICO PARA CONCRETO | D90: SUMINISTRO E INSTALACIÓN DE ADITIVO EPÓXICO PARA CONCRETO | E90: lt | F90: 0 | G90: 250481 | H90: 0
A91: CIV | B91: 1.5.6 | C91: 6.51. DMP SUMINISTRO E INSTALACIÓN DE CINTA PVC PARA JUNTAS | D91: SUMINISTRO E INSTALACIÓN DE CINTA PVC PARA JUNTAS | E91: ml | F91: 0 | G91: 89776 | H91: 0
A92: CIV | B92: 1.5.7 | C92: 6.52. DMP SUMINISTRO E INSTALACIÓN DE MORTERO FLUIDO PARA SELLO DE FISURAS (3000 psi) INCLUYE EQUIPO Y PERSONAL | D92: SUMINISTRO E INSTALACIÓN DE MORTERO FLUIDO PARA SELLO DE FISURAS (3000 psi) INCLUYE EQUIPO Y PERSONAL | E92: m3 | F92: 0 | G92: 45168227 | H92: 0
A93: CIV | B93: 1.5.8 | C93: 6.53. DMP GROUTING CEMENTOSO | D93: GROUTING CEMENTOSO | E93: lt | F93: 0 | G93: 50187 | H93: 0
A94: CIV | B94: 1.5.9 | C94: 6.54. DMP GROUTING EPÓXICO | D94: GROUTING EPÓXICO | E94: lt | F94: 0 | G94: 146782 | H94: 0
... A96: CIV | B96: 1.5.11 | C96: 6.56. DMP RECALCE 7 AEROGENERADORES CONSTRUIDOS | D96: RECALCE DE CIMENTACIONES AEROGENERADORES EXISTENTES | E96: Und | F96: 7 | G96: 597250360 | H96: 4180752520
A97: CIV | B97: 1.6. INSTALACION DE ACEROS DE REFUERZO PARA CONCRETO ESTRUCTURAL
A98: CIV | B98: 1.6.1 | C98: 6.57. DMP ACEROS | D98: ACERO FY: 60000 psi (4.200 kg/cm2) | E98: kg | F98: 2337733 | G98: 12780 | H98: 29876227740
A99: CIV | B99: 1.6.2 | C99: 6.57. DMP ACEROS | D99: ACERO DE REFUERZO CORRUGADO FIGURADO FY: 37.000 PSI (2400KG/CM²) | E99: kg | F99: 0 | G99: 16557 | H99: 0
A100: CIV | B100: 1.6.3 | C100: 6.57. DMP ACEROS | D100: MALLA ELECTROSOLDADA 60.000 PSI | E100: kg | F100: 0 | G100: 17067 | H100: 0
A101: CIV | B101: 1.7. INSTALACION DE ESTRUCTURAS METÁLICAS5.
A102: CIV | B102: 1.7.1 | C102: 6.58. DMP MONTAJE Y NIVELACIÓN JAULA DE ANCLAJES | D102: MONTAJE Y NIVELACION DE LA JAULA DE ANCLAJES INCLUYE LA PREPARACIÓN DEL ÁREA, LA NIVELACIÓN Y POSICIONAMIENTO DE LOS COMPONENTES (COMO PLANTILLAS Y VARILLAS), EL ENSAMBLAJE DE LA ESTRUCTURA, LA FIJACIÓN FINAL A LA CIMENTACIÓN CON PERNOS DE ANCLAJE, MONTAJE DE BRIDAS, TORQUE Y LIBERACIÓN DE LA CESTA, INCLUYE LA HERRAMIENTA Y EQUIPO DE INSTALACIÓN (peso estimado por jaula 13896 kg) | E102: Und | F102: 34 | G102: 99908619 | H102: 3396893046
A103: CIV | B103: 8. PISCINA INDUSTRIAL / INSPECCION . REPARACION Y MANTENIMEINTO
A104: CIV | B104: 1.8.1 | C104: 6.59. DMP INSPECCION, REPARACION Y MANTENIMIENTO DE PISCINA INDUSTRIAL | D104: INSPECCION, REPARACION Y MANTENIMIENTO DE PISCINA INDUSTRIAL | E104: GB | F104: 1 | G104: 334631000 | H104: 334631000
A105: CIV | B105: 9. OBRAS DE DRENAJE
A106: CIV | B106: 1.9.1 | C106: 6.60. DMP OBRAS DE DRENAJE | D106: OBRA DE DRENAJE TRANSVERSAL CON BATERÍA DE 1 MARCOS RECTANGULARES (BOX CULVERT) DE HORMIGÓN ARMADO DE 4,0 M DE ANCHO Y 2,50 METROS DE ALTURA ÚTIL, INCLUIDO EXCAVACIÓN DE LA CAJA QUE REQUIERE EL MARCO, LA NIVELACIÓN, REFINO Y PREPARACIÓN DEL LECHO DE ASIENTO. INCLUSO PARTE PROPORCIONAL DE ALETAS DE HORMIGÓN ARMADO PARA CONTENCIÓN DE TALUDES Y PROTECCIÓN DE ENTRADA Y SALIDA MEDIANTE RASTRILLO DE HORMIGÓN. | E106: ml | F106: 0 | G106: 44512209 | H106: 0
A107: CIV | B107: 1.9.2 | C107: 6.60. DMP OBRAS DE DRENAJE | D107: OBRA DE DRENAJE TRANSVERSAL CON BATERÍA DE 2 MARCOS RECTANGULARES (BOX CULVERT) DE HORMIGÓN ARMADO DE 4,0 M DE ANCHO Y 2,50 METROS DE ALTURA ÚTIL, INCLUIDO EXCAVACIÓN DE LA CAJA QUE REQUIERE EL MARCO, LA NIVELACIÓN, REFINO Y PREPARACIÓN DEL LECHO DE ASIENTO. INCLUSO PARTE PROPORCIONAL DE ALETAS DE HORMIGÓN ARMADO PARA CONTENCIÓN DE TALUDES Y PROTECCIÓN DE ENTRADA Y SALIDA MEDIANTE RASTRILLO DE HORMIGÓN. | E107: ml | F107: 0 | G107: 62426188 | H107: 0
A108: CIV | B108: 1.9.3 | C108: 6.60. DMP OBRAS DE DRENAJE | D108: OBRA DE DRENAJE TRANSVERSAL CON BATERÍA DE 3 MARCOS RECTANGULARES (BOX CULVERT) DE HORMIGÓN ARMADO DE 4,0 M DE ANCHO Y 2,50 METROS DE ALTURA ÚTIL, INCLUSO EXCAVACIÓN DE LA CAJA QUE REQUIERE EL MARCO, LA NIVELACIÓN, REFINO Y PREPARACIÓN DEL LECHO DE ASIENTO. INCLUSO PARTE PROPORCIONAL DE ALETAS DE HORMIGÓN ARMADO PARA CONTENCIÓN DE TALUDES Y PROTECCIÓN DE ENTRADA Y SALIDA MEDIANTE RASTRILLO DE HORMIGÓN. | E108: ml | F108: 0 | G108: 71603571 | H108: 0
A109: CIV | B109: 1.9.4 | C109: 6.60. DMP OBRAS DE DRENAJE | D109: OBRA DE DRENAJE TRANSVERSAL CON BATERÍA DE 2 MARCOS RECTANGULARES (BOX CULVERT) DE HORMIGÓN ARMADO DE 4,8 M DE ANCHO Y 2,50 METROS DE ALTURA ÚTIL, INCLUIDO EXCAVACIÓN DE LA CAJA QUE REQUIERE EL MARCO, LA NIVELACIÓN, REFINO Y PREPARACIÓN DEL LECHO DE ASIENTO. INCLUSO PARTE PROPORCIONAL DE ALETAS DE HORMIGÓN ARMADO PARA CONTENCIÓN DE TALUDES Y PROTECCIÓN DE ENTRADA Y SALIDA MEDIANTE RASTRILLO DE HORMIGÓN. | E109: ml | F109: 0 | G109: 61621055 | H109: 0
A110: CIV | B110: 1.9.5 | C110: 6.60. DMP OBRAS DE DRENAJE | D110: OBRA DE DRENAJE TRANSVERSAL CON BATERÍA DE 5 MARCOS RECTANGULARES (BOX CULVERT) DE HORMIGÓN ARMADO DE 4,8 M DE ANCHO Y 2,50 METROS DE ALTURA ÚTIL, INCLUIDO EXCAVACIÓN DE LA CAJA QUE REQUIERE EL MARCO, LA NIVELACIÓN, REFINO Y PREPARACIÓN DEL LECHO DE ASIENTO. INCLUSO PARTE PROPORCIONAL DE ALETAS DE HORMIGÓN ARMADO PARA CONTENCIÓN DE TALUDES Y PROTECCIÓN DE ENTRADA Y SALIDA MEDIANTE RASTRILLO DE HORMIGÓN. | E110: ml | F110: 0 | G110: 155569103 | H110: 0
A111: CIV | B111: 1.9.6 | C111: 6.60. DMP OBRAS DE DRENAJE | D111: ODT-OBRA DE DRENAJE TRANSVERSAL CON UNA (1) TUBERÍA EN CONCRETO Ø1200 MM , INCLUIDO EXCAVACIÓN DE LA CAJA QUE REQUIERE EL MARCO, LA NIVELACIÓN, REFINO Y PREPARACIÓN DEL LECHO DE ASIENTO. INCLUSO PARTE PROPORCIONAL DE ALETAS DE HORMIGÓN ARMADO PARA CONTENCIÓN DE TALUDES Y PROTECCIÓN DE ENTRADA Y SALIDA MEDIANTE RASTRILLO DE HORMIGÓN. | E111: ml | F111: 0 | G111: 10285553 | H111: 0
A112: CIV | B112: 1.9.7 | C112: 6.60. DMP OBRAS DE DRENAJE | D112: ODT-OBRA DE DRENAJE TRANSVERSAL CON DOS (2) TUBERÍA EN CONCRETO Ø1200 MM , INCLUIDO EXCAVACIÓN DE LA CAJA QUE REQUIERE EL MARCO, LA NIVELACIÓN, REFINO Y PREPARACIÓN DEL LECHO DE ASIENTO. INCLUSO PARTE PROPORCIONAL DE ALETAS DE HORMIGÓN ARMADO PARA CONTENCIÓN DE TALUDES Y PROTECCIÓN DE ENTRADA Y SALIDA MEDIANTE RASTRILLO DE HORMIGÓN. | E112: ml | F112: 0 | G112: 19669682 | H112: 0
A113: CIV | B113: 1.9.8 | C113: 6.60. DMP OBRAS DE DRENAJE | D113: ODT-OBRA DE DRENAJE TRANSVERSAL CON UNA (1) TUBERÍA EN CONCRETO Ø 1500 MM , INCLUIDO EXCAVACIÓN DE LA CAJA QUE REQUIERE EL MARCO, LA NIVELACIÓN, REFINO Y PREPARACIÓN DEL LECHO DE ASIENTO. INCLUSO PARTE PROPORCIONAL DE ALETAS DE HORMIGÓN ARMADO PARA CONTENCIÓN DE TALUDES Y PROTECCIÓN DE ENTRADA Y SALIDA MEDIANTE RASTRILLO DE HORMIGÓN. | E113: ml | F113: 0 | G113: 11159629 | H113: 0
A114: CIV | B114: 1.9.9 | C114: 6.60. DMP OBRAS DE DRENAJE | D114: ODT-OBRA DE DRENAJE TRANSVERSAL CON UNA (1) TUBERÍA EN CONCRETO Ø 2000 MM , INCLUIDO EXCAVACIÓN DE LA CAJA QUE REQUIERE EL MARCO, LA NIVELACIÓN, REFINO Y PREPARACIÓN DEL LECHO DE ASIENTO. INCLUSO PARTE PROPORCIONAL DE ALETAS DE HORMIGÓN ARMADO PARA CONTENCIÓN DE TALUDES Y PROTECCIÓN DE ENTRADA Y SALIDA MEDIANTE RASTRILLO DE HORMIGÓN. | E114: ml | F114: 0 | G114: 19046924 | H114: 0
A115: CIV | B115: 1.9.10 | C115: 6.60. DMP OBRAS DE DRENAJE | D115: ODT-OBRA DE DRENAJE TRANSVERSAL CON DOS (2) TUBERÍA EN CONCRETO Ø 2000 MM , INCLUIDO EXCAVACIÓN DE LA CAJA QUE REQUIERE EL MARCO, LA NIVELACIÓN, REFINO Y PREPARACIÓN DEL LECHO DE ASIENTO. INCLUSO PARTE PROPORCIONAL DE ALETAS DE HORMIGÓN ARMADO PARA CONTENCIÓN DE TALUDES Y PROTECCIÓN DE ENTRADA Y SALIDA MEDIANTE RASTRILLO DE HORMIGÓN. | E115: ml | F115: 0 | G115: 22696763 | H115: 0
A116: CIV | B116: 1.9.11 | C116: 6.60. DMP OBRAS DE DRENAJE | D116: ODT-OBRA DE DRENAJE TRANSVERSAL CON TRES (3) TUBERÍA EN CONCRETO Ø 2000 MM , INCLUIDO EXCAVACIÓN DE LA CAJA QUE REQUIERE EL MARCO, LA NIVELACIÓN, REFINO Y PREPARACIÓN DEL LECHO DE ASIENTO. INCLUSO PARTE PROPORCIONAL DE ALETAS DE HORMIGÓN ARMADO PARA CONTENCIÓN DE TALUDES Y PROTECCIÓN DE ENTRADA Y SALIDA MEDIANTE RASTRILLO DE HORMIGÓN. | E116: ml | F116: 0 | G116: 32250699 | H116: 0
A117: CIV | B117: 1.10 SEÑALIZACION Y DEMARCACION VIAL
A118: CIV | B118: 1.10.1 | C118: 6.61. DMP SEÑALIZACIÓN | D118: SUMINISTRO E INSTALACION DE SEÑALIZACION Y DEMARCACION VIAL | E118: Und | F118: 0 | G118: 580462 | H118: 0
A119: CIV | B119: 1.10.1.A | C119: 6.62 DMP CERCAS DE ALAMBRE DE PÚAS | D119: CERCA DE ALAMBRE DE PÚAS 5 HILOS. (CON POSTE EN CONCRETO) | E119: m | F119: 0 | G119: 77414 | H119: 0
A120: CIV | B120: 1.10.1.B | C120: 6.62 DMP CERCAS DE ALAMBRE DE PÚAS | D120: CERCA DE ALAMBRE DE PÚAS 5 HILOS. (CON POSTE EN POLIPROPILENO) | E120: m | F120: 0 | G120: 89929 | H120: 0
A121: CIV | B121: 1.10.1.C | C121: 6.62 DMP CERCAS DE ALAMBRE DE PÚAS | D121: CERCA DE ALAMBRE DE PÚAS 5 HILOS. (CON POSTE EN POLIPROPILENO REUTILIZADO) | E121: m | F121: 0 | G121: 58514 | H121: 0
A122: CIV | B122: 1.11 EQUIPOS Y/O HERRAMIENTAS POR LLLAMADO
A123: CIV | B123: 1.11.1 | C123: 6.63. DMP SUMINISTRO EQUIPOS Y HERRAMIENTAS | D123: BULDOZER POTENCIA MINIMA 120HP | E123: Día | F123: 100 | G123: 2706667 | H123: 270666700
A124: CIV | B124: 1.11.2 | C124: 6.63. DMP SUMINISTRO EQUIPOS Y HERRAMIENTAS | D124: MOTO NIVELADORA POTENCIA MINIMA 120HP | E124: Día | F124: 100 | G124: 2786667 | H124: 278666700
A125: CIV | B125: 1.11.3 | C125: 6.63. DMP SUMINISTRO EQUIPOS Y HERRAMIENTAS | D125: RETROEXCAVADORA POTENCIA MINIMA 130HP | E125: Día | F125: 100 | G125: 2786667 | H125: 278666700
A126: CIV | B126: 1.11.4 | C126: 6.63. DMP SUMINISTRO EQUIPOS Y HERRAMIENTAS | D126: VIBROCOMPACTADOR PESO MINIMO 10Ton | E126: Día | F126: 100 | G126: 1842667 | H126: 184266700
A127: CIV | B127: 1.11.5 | C127: 6.63. DMP SUMINISTRO EQUIPOS Y HERRAMIENTAS | D127: VIBROCOMPACTADOR PATA DE CABRA | E127: Día | F127: 100 | G127: 1842667 | H127: 184266700
A128: CIV | B128: 1.11.6 | C128: 6.63. DMP SUMINISTRO EQUIPOS Y HERRAMIENTAS | D128: MONTACARGAS DIESEL O GAS CAPACIDAD MINIMA 1000 KG. ALTURA MINIMA DE ELEVACIÓN 2.5 M | E128: Día | F128: 120 | G128: 2444444 | H128: 293333280
A129: CIV | B129: 1.11.7 | C129: 6.63. DMP SUMINISTRO EQUIPOS Y HERRAMIENTAS | D129: CARROTANQUE SENCILLO IRRIGADOR DE AGUA | E129: Día | F129: 100 | G129: 1564444 | H129: 156444400
A130: CIV | B130: 1.11.8 | C130: 6.63. DMP SUMINISTRO EQUIPOS Y HERRAMIENTAS | D130: CARROTANQUE DOBLETROQUE IRRIGADOR DE AGUA | E130: Día | F130: 30 | G130: 1604444 | H130: 48133320
A131: CIV | B131: 1.11.9 | C131: 6.63. DMP SUMINISTRO EQUIPOS Y HERRAMIENTAS | D131: RETROEXCAVADORA POTENCIA MINIMA 75HP | E131: Día | F131: 100 | G131: 1826667 | H131: 182666700
A132: CIV | B132: 1.11.10 | C132: 6.63. DMP SUMINISTRO EQUIPOS Y HERRAMIENTAS | D132: VOLQUETA TIPO SENCILLA CON CAPACIDAD MÍNIMA DE 6 m3 | E132: Día | F132: 100 | G132: 1324444 | H132: 132444400
A133: CIV | B133: 1.11.11 | C133: 6.63. DMP SUMINISTRO EQUIPOS Y HERRAMIENTAS | D133: VOLQUETA TIPO DT CON CAPACIDAD MÍNIMA DE 15 m3 | E133: Día | F133: 100 | G133: 2170344 | H133: 217034400
A134: CIV | B134: 1.11.12 | C134: 6.63. DMP SUMINISTRO EQUIPOS Y HERRAMIENTAS | D134: MOTOBOMBA 4" | E134: Día | F134: 30 | G134: 363180 | H134: 10895400
... A139: CIV | B139: 1.11.17 | C139: 6.64. DMP EQUIPO PARA MANTENIMIENTO DE VIAS TIPO 1. | D139: EQUIPO PARA MANTENIMIENTO DE VIAS TIPO 1. | E139: mes | F139: 0 | G139: 284426031 | H139: 0
...

Sheet Curva "S" Avance Físico
A1: =+'PDT ODS02 EARLY'!B3 -> CW381147-ODS002: CONSTRUCCIÓN DE PLATAFORMAS Y CIMENTACIONES DE AEROGENERADORES DEL PARQUE EÓLICO WINDPESHI

Sheet PDT ODS02 EARLY
B3: CW381147-ODS002: CONSTRUCCIÓN DE PLATAFORMAS Y CIMENTACIONES DE AEROGENERADORES DEL PARQUE EÓLICO WINDPESHI | H3: SEMANAS | I3: 0 | J3: 1 | K3: 2 | L3: 3 | M3: 4 | N3: 5 | O3: 6 | P3: 7 | Q3: 8 | R3: 9 | S3: 10 | T3: 11 | U3: 12 | V3: 13 | W3: 14 | X3: 15 | Y3: 16 | Z3: 17 | AA3: 18 | AB3: 19 | AC3: 20 | AD3: 21 | AE3: 22 | AF3: 23 | AG3: 24 | AH3: 25 | AI3: 26 | AJ3: 27 | AK3: 28 | AL3: 29 | AM3: 30 | AN3: 31 | AO3: 32 | AP3: 33 | AQ3: 34 | AR3: 35 | AS3: 36 | AT3: 37 | AU3: 38 | AV3: 39 | AW3: 40 | AX3: 41 | AY3: 42 | AZ3: 43 | BA3: 44 | BB3: 45 | BC3: 46 | BD3: 47 | BE3: 48 | BF3: 49 | BG3: 50 | BH3: 51 | BI3: 52 | BJ3: 53 | BK3: 54 | BL3: 55 | BM3: 56 | BN3: 57 | BO3: 58
I4: =G8 -> 46218 | J4: =I4+2 -> 46220 | K4: =J4+7 -> 46227 | L4: =K4+7 -> 46234 | M4: =L4+7 -> 46241 | N4: =M4+7 -> 46248 | O4: =N4+7 -> 46255 | P4: =O4+7 -> 46262 | Q4: =P4+7 -> 46269 | R4: =Q4+7 -> 46276 | ... BO4: =BN4+7 -> 46619
H5: AVANCES PROGRAMADOS | I5: =I7*$E$8 -> 0 | J5: =J7*$E$8 -> 0 | K5: =K7*$E$8 -> 0 | L5: =L7*$E$8 -> 0 | M5: =M7*$E$8 -> 16654356 | N5: =N7*$E$8 -> 2.7101093e+08 | O5: =O7*$E$8 -> 8.577558e+08 | P5: =P7*$E$8 -> 1.7342925e+09 | ... BO5: =BO7*$E$8 -> 2.084461e+11
H6: FECHAS | I6: =I4 -> 46218 | J6: =J4 -> 46220 | K6: =K4 -> 46227 | L6: =L4 -> 46234 | M6: =M4 -> 46241 | N6: =N4 -> 46248 | O6: =O4 -> 46255 | P6: =P4 -> 46262 | ... BO6: =BO4 -> 46619
B7: EDT | C7: Nombre de tarea | D7: Duración | E7: Costo | F7: PESO RELATIVO AL CAPITULO (%) | G7: Comienzo | H7: Fin | I7: =$F34*I34+$F39*I39+$F44*I44+$F109*I109+$F689*I689+$F695*I695+$F699*I699 -> 0 | J7: =$F34*J34+$F39*J39+$F44*J44+$F109*J109+$F689*J689+$F695*J695+$F699*J699 -> 0 | K7: =$F34*K34+$F39*K39+$F44*K44+$F109*K109+$F689*K689+$F695*K695+$F699*K699 -> 0 | L7: =$F34*L34+$F39*L39+$F44*L44+$F109*L109+$F689*L689+$F695*L695+$F699*L699 -> 0 | M7: =$F34*M34+$F39*M39+$F44*M44+$F109*M109+$F689*M689+$F695*M695+$F699*M699 -> 7.9897664e-05 | N7: =$F34*N34+$F39*N39+$F44*N44+$F109*N109+$F689*N689+$F695*N695+$F699*N699 -> 0.0013001487 | O7: =$F34*O34+$F39*O39+$F44*O44+$F109*O109+$F689*O689+$F695*O695+$F699*O699 -> 0.0041150005 | P7: =$F34*P34+$F39*P39+$F44*P44+$F109*P109+$F689*P689+$F695*P695+$F699*P699 -> 0.0083201005 | ... BO7: =$F34*BO34+$F39*BO39+$F44*BO44+$F109*BO109+$F689*BO689+$F695*BO695+$F699*BO699 -> 1
B8: 0 | C8: ODS02_IIWAKAI | D8: 357 días | E8: =+E34+E39+E44+E109+E689+E695+E699 -> 2.084461e+11 | F8: =+F10+F14++F29+F30+F34+F39+F44+F109+F689+F695+F699 -> 1 | G8: 46218 | H8: 46617 | I8: =I7*$E$8 -> 0 | J8: =J7*$E$8 -> 0 | K8: =K7*$E$8 -> 0 | L8: =L7*$E$8 -> 0 | M8: =M7*$E$8 -> 16654356 | N8: =N7*$E$8 -> 2.7101093e+08 | O8: =O7*$E$8 -> 8.577558e+08 | P8: =P7*$E$8 -> 1.7342925e+09 | ... BO8: =BO7*$E$8 -> 2.084461e+11
B9: 1 | C9: HITO 1: ACTA DE INICIO | D9: 0 días | E9: =VLOOKUP(B9,'Cuadro Control'!C5:J1939,8,FALSE) -> 0 | F9: =IFERROR(E9/$E$8,0) -> 0 | G9: 46218 | H9: 46218 | I9: =IF($G9=0,0,IF(I$6<$G9,0,IF(I$6>$H9,1,(I$6-$G9+1)/($H9-$G9+1)))) -> 1 | J9: =IF($G9=0,0,IF(J$6<$G9,0,IF(J$6>$H9,1,(J$6-$G9+1)/($H9-$G9+1)))) -> 1 | K9: =IF($G9=0,0,IF(K$6<$G9,0,IF(K$6>$H9,1,(K$6-$G9+1)/($H9-$G9+1)))) -> 1 | L9: =IF($G9=0,0,IF(L$6<$G9,0,IF(L$6>$H9,1,(L$6-$G9+1)/($H9-$G9+1)))) -> 1 | M9: =IF($G9=0,0,IF(M$6<$G9,0,IF(M$6>$H9,1,(M$6-$G9+1)/($H9-$G9+1)))) -> 1 | N9: =IF($G9=0,0,IF(N$6<$G9,0,IF(N$6>$H9,1,(N$6-$G9+1)/($H9-$G9+1)))) -> 1 | O9: =IF($G9=0,0,IF(O$6<$G9,0,IF(O$6>$H9,1,(O$6-$G9+1)/($H9-$G9+1)))) -> 1 | P9: =IF($G9=0,0,IF(P$6<$G9,0,IF(P$6>$H9,1,(P$6-$G9+1)/($H9-$G9+1)))) -> 1 | ... BO9: =IF($G9=0,0,IF(BO$6<$G9,0,IF(BO$6>$H9,1,(BO$6-$G9+1)/($H9-$G9+1)))) -> 1
B10: 2 | C10: PRELIMINARES GENERALES | D10: 21 días | E10: =VLOOKUP(B10,'Cuadro Control'!C6:J1940,8,FALSE) -> 0 | F10: =IFERROR(E10/$E$8,0) -> 0 | G10: 46218 | H10: 46240 | I10: =IF($G10=0,0,IF(I$6<$G10,0,IF(I$6>$H10,1,(I$6-$G10+1)/($H10-$G10+1)))) -> 0.043478261 | J10: =IF($G10=0,0,IF(J$6<$G10,0,IF(J$6>$H10,1,(J$6-$G10+1)/($H10-$G10+1)))) -> 0.13043478 | K10: =IF($G10=0,0,IF(K$6<$G10,0,IF(K$6>$H10,1,(K$6-$G10+1)/($H10-$G10+1)))) -> 0.43478261 | L10: =IF($G10=0,0,IF(L$6<$G10,0,IF(L$6>$H10,1,(L$6-$G10+1)/($H10-$G10+1)))) -> 0.73913043 | M10: =IF($G10=0,0,IF(M$6<$G10,0,IF(M$6>$H10,1,(M$6-$G10+1)/($H10-$G10+1)))) -> 1 | N10: =IF($G10=0,0,IF(N$6<$G10,0,IF(N$6>$H10,1,(N$6-$G10+1)/($H10-$G10+1)))) -> 1 | O10: =IF($G10=0,0,IF(O$6<$G10,0,IF(O$6>$H10,1,(O$6-$G10+1)/($H10-$G10+1)))) -> 1 | P10: =IF($G10=0,0,IF(P$6<$G10,0,IF(P$6>$H10,1,(P$6-$G10+1)/($H10-$G10+1)))) -> 1 | ... BO10: =IF($G10=0,0,IF(BO$6<$G10,0,IF(BO$6>$H10,1,(BO$6-$G10+1)/($H10-$G10+1)))) -> 1
B11: 2.1 | C11: ENTREGA DE DOCUMENTOS HABILITADORES | D11: 0 días | E11: =VLOOKUP(B11,'Cuadro Control'!C7:J1941,8,FALSE) -> 0 | F11: =IFERROR(E11/$E$8,0) -> 0 | G11: 46218 | H11: 46218 | I11: =IF($G11=0,0,IF(I$6<$G11,0,IF(I$6>$H11,1,(I$6-$G11+1)/($H11-$G11+1)))) -> 1 | J11: =IF($G11=0,0,IF(J$6<$G11,0,IF(J$6>$H11,1,(J$6-$G11+1)/($H11-$G11+1)))) -> 1 | K11: =IF($G11=0,0,IF(K$6<$G11,0,IF(K$6>$H11,1,(K$6-$G11+1)/($H11-$G11+1)))) -> 1 | L11: =IF($G11=0,0,IF(L$6<$G11,0,IF(L$6>$H11,1,(L$6-$G11+1)/($H11-$G11+1)))) -> 1 | M11: =IF($G11=0,0,IF(M$6<$G11,0,IF(M$6>$H11,1,(M$6-$G11+1)/($H11-$G11+1)))) -> 1 | N11: =IF($G11=0,0,IF(N$6<$G11,0,IF(N$6>$H11,1,(N$6-$G11+1)/($H11-$G11+1)))) -> 1 | O11: =IF($G11=0,0,IF(O$6<$G11,0,IF(O$6>$H11,1,(O$6-$G11+1)/($H11-$G11+1)))) -> 1 | P11: =IF($G11=0,0,IF(P$6<$G11,0,IF(P$6>$H11,1,(P$6-$G11+1)/($H11-$G11+1)))) -> 1 | ... BO11: =IF($G11=0,0,IF(BO$6<$G11,0,IF(BO$6>$H11,1,(BO$6-$G11+1)/($H11-$G11+1)))) -> 1
B12: 2.2 | C12: ENTREGA DE DOCUMENTACIÓN DE EJECUCION DEL PROYECTO | D12: 0 días | E12: =VLOOKUP(B12,'Cuadro Control'!C8:J1942,8,FALSE) -> 0 | F12: =IFERROR(E12/$E$8,0) -> 0 | G12: 46218 | H12: 46218 | I12: =IF($G12=0,0,IF(I$6<$G12,0,IF(I$6>$H12,1,(I$6-$G12+1)/($H12-$G12+1)))) -> 1 | J12: =IF($G12=0,0,IF(J$6<$G12,0,IF(J$6>$H12,1,(J$6-$G12+1)/($H12-$G12+1)))) -> 1 | K12: =IF($G12=0,0,IF(K$6<$G12,0,IF(K$6>$H12,1,(K$6-$G12+1)/($H12-$G12+1)))) -> 1 | L12: =IF($G12=0,0,IF(L$6<$G12,0,IF(L$6>$H12,1,(L$6-$G12+1)/($H12-$G12+1)))) -> 1 | M12: =IF($G12=0,0,IF(M$6<$G12,0,IF(M$6>$H12,1,(M$6-$G12+1)/($H12-$G12+1)))) -> 1 | N12: =IF($G12=0,0,IF(N$6<$G12,0,IF(N$6>$H12,1,(N$6-$G12+1)/($H12-$G12+1)))) -> 1 | O12: =IF($G12=0,0,IF(O$6<$G12,0,IF(O$6>$H12,1,(O$6-$G12+1)/($H12-$G12+1)))) -> 1 | P12: =IF($G12=0,0,IF(P$6<$G12,0,IF(P$6>$H12,1,(P$6-$G12+1)/($H12-$G12+1)))) -> 1 | ... BO12: =IF($G12=0,0,IF(BO$6<$G12,0,IF(BO$6>$H12,1,(BO$6-$G12+1)/($H12-$G12+1)))) -> 1
B13: 2.3 | C13: REVISIÓN Y RECEPCIÓN DE INGENIERIA | D13: 21 días | E13: =VLOOKUP(B13,'Cuadro Control'!C9:J1943,8,FALSE) -> 0 | F13: =IFERROR(E13/$E$8,0) -> 0 | G13: 46218 | H13: 46240 | I13: =IF($G13=0,0,IF(I$6<$G13,0,IF(I$6>$H13,1,(I$6-$G13+1)/($H13-$G13+1)))) -> 0.043478261 | J13: =IF($G13=0,0,IF(J$6<$G13,0,IF(J$6>$H13,1,(J$6-$G13+1)/($H13-$G13+1)))) -> 0.13043478 | K13: =IF($G13=0,0,IF(K$6<$G13,0,IF(K$6>$H13,1,(K$6-$G13+1)/($H13-$G13+1)))) -> 0.43478261 | L13: =IF($G13=0,0,IF(L$6<$G13,0,IF(L$6>$H13,1,(L$6-$G13+1)/($H13-$G13+1)))) -> 0.73913043 | M13: =IF($G13=0,0,IF(M$6<$G13,0,IF(M$6>$H13,1,(M$6-$G13+1)/($H13-$G13+1)))) -> 1 | N13: =IF($G13=0,0,IF(N$6<$G13,0,IF(N$6>$H13,1,(N$6-$G13+1)/($H13-$G13+1)))) -> 1 | O13: =IF($G13=0,0,IF(O$6<$G13,0,IF(O$6>$H13,1,(O$6-$G13+1)/($H13-$G13+1)))) -> 1 | P13: =IF($G13=0,0,IF(P$6<$G13,0,IF(P$6>$H13,1,(P$6-$G13+1)/($H13-$G13+1)))) -> 1 | ... BO13: =IF($G13=0,0,IF(BO$6<$G13,0,IF(BO$6>$H13,1,(BO$6-$G13+1)/($H13-$G13+1)))) -> 1
B14: 3 | C14: SOCIALIZACIÓN CON COMUNIDADES | D14: 30 días | E14: =VLOOKUP(B14,'Cuadro Control'!C10:J1944,8,FALSE) -> 0 | F14: =IFERROR(E14/$E$8,0) -> 0 | G14: 46218 | H14: 46252 | I14: =IF($G14=0,0,IF(I$6<$G14,0,IF(I$6>$H14,1,(I$6-$G14+1)/($H14-$G14+1)))) -> 0.028571429 | J14: =IF($G14=0,0,IF(J$6<$G14,0,IF(J$6>$H14,1,(J$6-$G14+1)/($H14-$G14+1)))) -> 0.085714286 | K14: =IF($G14=0,0,IF(K$6<$G14,0,IF(K$6>$H14,1,(K$6-$G14+1)/($H14-$G14+1)))) -> 0.28571429 | L14: =IF($G14=0,0,IF(L$6<$G14,0,IF(L$6>$H14,1,(L$6-$G14+1)/($H14-$G14+1)))) -> 0.48571429 | M14: =IF($G14=0,0,IF(M$6<$G14,0,IF(M$6>$H14,1,(M$6-$G14+1)/($H14-$G14+1)))) -> 0.68571429 | N14: =IF($G14=0,0,IF(N$6<$G14,0,IF(N$6>$H14,1,(N$6-$G14+1)/($H14-$G14+1)))) -> 0.88571429 | O14: =IF($G14=0,0,IF(O$6<$G14,0,IF(O$6>$H14,1,(O$6-$G14+1)/($H14-$G14+1)))) -> 1 | P14: =IF($G14=0,0,IF(P$6<$G14,0,IF(P$6>$H14,1,(P$6-$G14+1)/($H14-$G14+1)))) -> 1 | ... BO14: =IF($G14=0,0,IF(BO$6<$G14,0,IF(BO$6>$H14,1,(BO$6-$G14+1)/($H14-$G14+1)))) -> 1
B15: 3.1 | C15: REUNIONES RIO PATAJATAMA | D15: 0 días | E15: =VLOOKUP(B15,'Cuadro Control'!C11:J1945,8,FALSE) -> 0 | F15: =IFERROR(E15/$E$8,0) -> 0 | G15: 46218 | H15: 46218 | I15: =IF($G15=0,0,IF(I$6<$G15,0,IF(I$6>$H15,1,(I$6-$G15+1)/($H15-$G15+1)))) -> 1 | J15: =IF($G15=0,0,IF(J$6<$G15,0,IF(J$6>$H15,1,(J$6-$G15+1)/($H15-$G15+1)))) -> 1 | K15: =IF($G15=0,0,IF(K$6<$G15,0,IF(K$6>$H15,1,(K$6-$G15+1)/($H15-$G15+1)))) -> 1 | L15: =IF($G15=0,0,IF(L$6<$G15,0,IF(L$6>$H15,1,(L$6-$G15+1)/($H15-$G15+1)))) -> 1 | M15: =IF($G15=0,0,IF(M$6<$G15,0,IF(M$6>$H15,1,(M$6-$G15+1)/($H15-$G15+1)))) -> 1 | N15: =IF($G15=0,0,IF(N$6<$G15,0,IF(N$6>$H15,1,(N$6-$G15+1)/($H15-$G15+1)))) -> 1 | O15: =IF($G15=0,0,IF(O$6<$G15,0,IF(O$6>$H15,1,(O$6-$G15+1)/($H15-$G15+1)))) -> 1 | P15: =IF($G15=0,0,IF(P$6<$G15,0,IF(P$6>$H15,1,(P$6-$G15+1)/($H15-$G15+1)))) -> 1 | ... BO15: =IF($G15=0,0,IF(BO$6<$G15,0,IF(BO$6>$H15,1,(BO$6-$G15+1)/($H15-$G15+1)))) -> 1
B16: 3.2 | C16: REUNIONES RIO ROMANA | D16: 0 días | E16: =VLOOKUP(B16,'Cuadro Control'!C12:J1946,8,FALSE) -> 0 | F16: =IFERROR(E16/$E$8,0) -> 0 | G16: 46218 | H16: 46218 | I16: =IF($G16=0,0,IF(I$6<$G16,0,IF(I$6>$H16,1,(I$6-$G16+1)/($H16-$G16+1)))) -> 1 | J16: =IF($G16=0,0,IF(J$6<$G16,0,IF(J$6>$H16,1,(J$6-$G16+1)/($H16-$G16+1)))) -> 1 | K16: =IF($G16=0,0,IF(K$6<$G16,0,IF(K$6>$H16,1,(K$6-$G16+1)/($H16-$G16+1)))) -> 1 | L16: =IF($G16=0,0,IF(L$6<$G16,0,IF(L$6>$H16,1,(L$6-$G16+1)/($H16-$G16+1)))) -> 1 | M16: =IF($G16=0,0,IF(M$6<$G16,0,IF(M$6>$H16,1,(M$6-$G16+1)/($H16-$G16+1)))) -> 1 | N16: =IF($G16=0,0,IF(N$6<$G16,0,IF(N$6>$H16,1,(N$6-$G16+1)/($H16-$G16+1)))) -> 1 | O16: =IF($G16=0,0,IF(O$6<$G16,0,IF(O$6>$H16,1,(O$6-$G16+1)/($H16-$G16+1)))) -> 1 | P16: =IF($G16=0,0,IF(P$6<$G16,0,IF(P$6>$H16,1,(P$6-$G16+1)/($H16-$G16+1)))) -> 1 | ... BO16: =IF($G16=0,0,IF(BO$6<$G16,0,IF(BO$6>$H16,1,(BO$6-$G16+1)/($H16-$G16+1)))) -> 1
B17: 3.3 | C17: REUNIONES RIO UTKAP | D17: 0 días | E17: =VLOOKUP(B17,'Cuadro Control'!C13:J1947,8,FALSE) -> 0 | F17: =IFERROR(E17/$E$8,0) -> 0 | G17: 46218 | H17: 46218 | I17: =IF($G17=0,0,IF(I$6<$G17,0,IF(I$6>$H17,1,(I$6-$G17+1)/($H17-$G17+1)))) -> 1 | J17: =IF($G17=0,0,IF(J$6<$G17,0,IF(J$6>$H17,1,(J$6-$G17+1)/($H17-$G17+1)))) -> 1 | K17: =IF($G17=0,0,IF(K$6<$G17,0,IF(K$6>$H17,1,(K$6-$G17+1)/($H17-$G17+1)))) -> 1 | L17: =IF($G17=0,0,IF(L$6<$G17,0,IF(L$6>$H17,1,(L$6-$G17+1)/($H17-$G17+1)))) -> 1 | M17: =IF($G17=0,0,IF(M$6<$G17,0,IF(M$6>$H17,1,(M$6-$G17+1)/($H17-$G17+1)))) -> 1 | N17: =IF($G17=0,0,IF(N$6<$G17,0,IF(N$6>$H17,1,(N$6-$G17+1)/($H17-$G17+1)))) -> 1 | O17: =IF($G17=0,0,IF(O$6<$G17,0,IF(O$6>$H17,1,(O$6-$G17+1)/($H17-$G17+1)))) -> 1 | P17: =IF($G17=0,0,IF(P$6<$G17,0,IF(P$6>$H17,1,(P$6-$G17+1)/($H17-$G17+1)))) -> 1 | ... BO17: =IF($G17=0,0,IF(BO$6<$G17,0,IF(BO$6>$H17,1,(BO$6-$G17+1)/($H17-$G17+1)))) -> 1
B18: 3.4 | C18: REUNIONES RIO CALINCHON | D18: 0 días | E18: =VLOOKUP(B18,'Cuadro Control'!C14:J1948,8,FALSE) -> 0 | F18: =IFERROR(E18/$E$8,0) -> 0 | G18: 46218 | H18: 46218 | I18: =IF($G18=0,0,IF(I$6<$G18,0,IF(I$6>$H18,1,(I$6-$G18+1)/($H18-$G18+1)))) -> 1 | J18: =IF($G18=0,0,IF(J$6<$G18,0,IF(J$6>$H18,1,(J$6-$G18+1)/($H18-$G18+1)))) -> 1 | K18: =IF($G18=0,0,IF(K$6<$G18,0,IF(K$6>$H18,1,(K$6-$G18+1)/($H18-$G18+1)))) -> 1 | L18: =IF($G18=0,0,IF(L$6<$G18,0,IF(L$6>$H18,1,(L$6-$G18+1)/($H18-$G18+1)))) -> 1 | M18: =IF($G18=0,0,IF(M$6<$G18,0,IF(M$6>$H18,1,(M$6-$G18+1)/($H18-$G18+1)))) -> 1 | N18: =IF($G18=0,0,IF(N$6<$G18,0,IF(N$6>$H18,1,(N$6-$G18+1)/($H18-$G18+1)))) -> 1 | O18: =IF($G18=0,0,IF(O$6<$G18,0,IF(O$6>$H18,1,(O$6-$G18+1)/($H18-$G18+1)))) -> 1 | P18: =IF($G18=0,0,IF(P$6<$G18,0,IF(P$6>$H18,1,(P$6-$G18+1)/($H18-$G18+1)))) -> 1 | ... BO18: =IF($G18=0,0,IF(BO$6<$G18,0,IF(BO$6>$H18,1,(BO$6-$G18+1)/($H18-$G18+1)))) -> 1
B19: 3.5 | C19: REUNIONES RIO CAÑAVERAL | D19: 0 días | E19: =VLOOKUP(B19,'Cuadro Control'!C15:J1949,8,FALSE) -> 0 | F19: =IFERROR(E19/$E$8,0) -> 0 | G19: 46218 | H19: 46218 | I19: =IF($G19=0,0,IF(I$6<$G19,0,IF(I$6>$H19,1,(I$6-$G19+1)/($H19-$G19+1)))) -> 1 | J19: =IF($G19=0,0,IF(J$6<$G19,0,IF(J$6>$H19,1,(J$6-$G19+1)/($H19-$G19+1)))) -> 1 | K19: =IF($G19=0,0,IF(K$6<$G19,0,IF(K$6>$H19,1,(K$6-$G19+1)/($H19-$G19+1)))) -> 1 | L19: =IF($G19=0,0,IF(L$6<$G19,0,IF(L$6>$H19,1,(L$6-$G19+1)/($H19-$G19+1)))) -> 1 | M19: =IF($G19=0,0,IF(M$6<$G19,0,IF(M$6>$H19,1,(M$6-$G19+1)/($H19-$G19+1)))) -> 1 | N19: =IF($G19=0,0,IF(N$6<$G19,0,IF(N$6>$H19,1,(N$6-$G19+1)/($H19-$G19+1)))) -> 1 | O19: =IF($G19=0,0,IF(O$6<$G19,0,IF(O$6>$H19,1,(O$6-$G19+1)/($H19-$G19+1)))) -> 1 | P19: =IF($G19=0,0,IF(P$6<$G19,0,IF(P$6>$H19,1,(P$6-$G19+1)/($H19-$G19+1)))) -> 1 | ... BO19: =IF($G19=0,0,IF(BO$6<$G19,0,IF(BO$6>$H19,1,(BO$6-$G19+1)/($H19-$G19+1)))) -> 1
B20: 3.6 | C20: REUNIONES RIO KAMUSHIPA | D20: 0 días | E20: =VLOOKUP(B20,'Cuadro Control'!C16:J1950,8,FALSE) -> 0 | F20: =IFERROR(E20/$E$8,0) -> 0 | G20: 46218 | H20: 46218 | I20: =IF($G20=0,0,IF(I$6<$G20,0,IF(I$6>$H20,1,(I$6-$G20+1)/($H20-$G20+1)))) -> 1 | J20: =IF($G20=0,0,IF(J$6<$G20,0,IF(J$6>$H20,1,(J$6-$G20+1)/($H20-$G20+1)))) -> 1 | K20: =IF($G20=0,0,IF(K$6<$G20,0,IF(K$6>$H20,1,(K$6-$G20+1)/($H20-$G20+1)))) -> 1 | L20: =IF($G20=0,0,IF(L$6<$G20,0,IF(L$6>$H20,1,(L$6-$G20+1)/($H20-$G20+1)))) -> 1 | M20: =IF($G20=0,0,IF(M$6<$G20,0,IF(M$6>$H20,1,(M$6-$G20+1)/($H20-$G20+1)))) -> 1 | N20: =IF($G20=0,0,IF(N$6<$G20,0,IF(N$6>$H20,1,(N$6-$G20+1)/($H20-$G20+1)))) -> 1 | O20: =IF($G20=0,0,IF(O$6<$G20,0,IF(O$6>$H20,1,(O$6-$G20+1)/($H20-$G20+1)))) -> 1 | P20: =IF($G20=0,0,IF(P$6<$G20,0,IF(P$6>$H20,1,(P$6-$G20+1)/($H20-$G20+1)))) -> 1 | ... BO20: =IF($G20=0,0,IF(BO$6<$G20,0,IF(BO$6>$H20,1,(BO$6-$G20+1)/($H20-$G20+1)))) -> 1
B21: 3.7 | C21: REUNIONES RIO FLOR DE LA FRONTERA | D21: 0 días | E21: =VLOOKUP(B21,'Cuadro Control'!C17:J1951,8,FALSE) -> 0 | F21: =IFERROR(E21/$E$8,0) -> 0 | G21: 46218 | H21: 46218 | I21: =IF($G21=0,0,IF(I$6<$G21,0,IF(I$6>$H21,1,(I$6-$G21+1)/($H21-$G21+1)))) -> 1 | J21: =IF($G21=0,0,IF(J$6<$G21,0,IF(J$6>$H21,1,(J$6-$G21+1)/($H21-$G21+1)))) -> 1 | K21: =IF($G21=0,0,IF(K$6<$G21,0,IF(K$6>$H21,1,(K$6-$G21+1)/($H21-$G21+1)))) -> 1 | L21: =IF($G21=0,0,IF(L$6<$G21,0,IF(L$6>$H21,1,(L$6-$G21+1)/($H21-$G21+1)))) -> 1 | M21: =IF($G21=0,0,IF(M$6<$G21,0,IF(M$6>$H21,1,(M$6-$G21+1)/($H21-$G21+1)))) -> 1 | N21: =IF($G21=0,0,IF(N$6<$G21,0,IF(N$6>$H21,1,(N$6-$G21+1)/($H21-$G21+1)))) -> 1 | O21: =IF($G21=0,0,IF(O$6<$G21,0,IF(O$6>$H21,1,(O$6-$G21+1)/($H21-$G21+1)))) -> 1 | P21: =IF($G21=0,0,IF(P$6<$G21,0,IF(P$6>$H21,1,(P$6-$G21+1)/($H21-$G21+1)))) -> 1 | ... BO21: =IF($G21=0,0,IF(BO$6<$G21,0,IF(BO$6>$H21,1,(BO$6-$G21+1)/($H21-$G21+1)))) -> 1
B22: 3.8 | C22: REUNIONES RIO JAIKA KALINCHON | D22: 0 días | E22: =VLOOKUP(B22,'Cuadro Control'!C18:J1952,8,FALSE) -> 0 | F22: =IFERROR(E22/$E$8,0) -> 0 | G22: 46218 | H22: 46218 | I22: =IF($G22=0,0,IF(I$6<$G22,0,IF(I$6>$H22,1,(I$6-$G22+1)/($H22-$G22+1)))) -> 1 | J22: =IF($G22=0,0,IF(J$6<$G22,0,IF(J$6>$H22,1,(J$6-$G22+1)/($H22-$G22+1)))) -> 1 | K22: =IF($G22=0,0,IF(K$6<$G22,0,IF(K$6>$H22,1,(K$6-$G22+1)/($H22-$G22+1)))) -> 1 | L22: =IF($G22=0,0,IF(L$6<$G22,0,IF(L$6>$H22,1,(L$6-$G22+1)/($H22-$G22+1)))) -> 1 | M22: =IF($G22=0,0,IF(M$6<$G22,0,IF(M$6>$H22,1,(M$6-$G22+1)/($H22-$G22+1)))) -> 1 | N22: =IF($G22=0,0,IF(N$6<$G22,0,IF(N$6>$H22,1,(N$6-$G22+1)/($H22-$G22+1)))) -> 1 | O22: =IF($G22=0,0,IF(O$6<$G22,0,IF(O$6>$H22,1,(O$6-$G22+1)/($H22-$G22+1)))) -> 1 | P22: =IF($G22=0,0,IF(P$6<$G22,0,IF(P$6>$H22,1,(P$6-$G22+1)/($H22-$G22+1)))) -> 1 | ... BO22: =IF($G22=0,0,IF(BO$6<$G22,0,IF(BO$6>$H22,1,(BO$6-$G22+1)/($H22-$G22+1)))) -> 1
B23: 3.9 | C23: REUNIONES RIO MASHUMANA | D23: 0 días | E23: =VLOOKUP(B23,'Cuadro Control'!C19:J1953,8,FALSE) -> 0 | F23: =IFERROR(E23/$E$8,0) -> 0 | G23: 46218 | H23: 46218 | I23: =IF($G23=0,0,IF(I$6<$G23,0,IF(I$6>$H23,1,(I$6-$G23+1)/($H23-$G23+1)))) -> 1 | J23: =IF($G23=0,0,IF(J$6<$G23,0,IF(J$6>$H23,1,(J$6-$G23+1)/($H23-$G23+1)))) -> 1 | K23: =IF($G23=0,0,IF(K$6<$G23,0,IF(K$6>$H23,1,(K$6-$G23+1)/($H23-$G23+1)))) -> 1 | L23: =IF($G23=0,0,IF(L$6<$G23,0,IF(L$6>$H23,1,(L$6-$G23+1)/($H23-$G23+1)))) -> 1 | M23: =IF($G23=0,0,IF(M$6<$G23,0,IF(M$6>$H23,1,(M$6-$G23+1)/($H23-$G23+1)))) -> 1 | N23: =IF($G23=0,0,IF(N$6<$G23,0,IF(N$6>$H23,1,(N$6-$G23+1)/($H23-$G23+1)))) -> 1 | O23: =IF($G23=0,0,IF(O$6<$G23,0,IF(O$6>$H23,1,(O$6-$G23+1)/($H23-$G23+1)))) -> 1 | P23: =IF($G23=0,0,IF(P$6<$G23,0,IF(P$6>$H23,1,(P$6-$G23+1)/($H23-$G23+1)))) -> 1 | ... BO23: =IF($G23=0,0,IF(BO$6<$G23,0,IF(BO$6>$H23,1,(BO$6-$G23+1)/($H23-$G23+1)))) -> 1
B24: 3.10 | C24: REUNIONES RIO MASHUMANA WANE | D24: 0 días | E24: =VLOOKUP(B24,'Cuadro Control'!C20:J1954,8,FALSE) -> 0 | F24: =IFERROR(E24/$E$8,0) -> 0 | G24: 46218 | H24: 46218 | I24: =IF($G24=0,0,IF(I$6<$G24,0,IF(I$6>$H24,1,(I$6-$G24+1)/($H24-$G24+1)))) -> 1 | J24: =IF($G24=0,0,IF(J$6<$G24,0,IF(J$6>$H24,1,(J$6-$G24+1)/($H24-$G24+1)))) -> 1 | K24: =IF($G24=0,0,IF(K$6<$G24,0,IF(K$6>$H24,1,(K$6-$G24+1)/($H24-$G24+1)))) -> 1 | L24: =IF($G24=0,0,IF(L$6<$G24,0,IF(L$6>$H24,1,(L$6-$G24+1)/($H24-$G24+1)))) -> 1 | M24: =IF($G24=0,0,IF(M$6<$G24,0,IF(M$6>$H24,1,(M$6-$G24+1)/($H24-$G24+1)))) -> 1 | N24: =IF($G24=0,0,IF(N$6<$G24,0,IF(N$6>$H24,1,(N$6-$G24+1)/($H24-$G24+1)))) -> 1 | O24: =IF($G24=0,0,IF(O$6<$G24,0,IF(O$6>$H24,1,(O$6-$G24+1)/($H24-$G24+1)))) -> 1 | P24: =IF($G24=0,0,IF(P$6<$G24,0,IF(P$6>$H24,1,(P$6-$G24+1)/($H24-$G24+1)))) -> 1 | ... BO24: =IF($G24=0,0,IF(BO$6<$G24,0,IF(BO$6>$H24,1,(BO$6-$G24+1)/($H24-$G24+1)))) -> 1
B25: 3.11 | C25: REUNIONES RIO MATAJUNAY | D25: 0 días | E25: =VLOOKUP(B25,'Cuadro Control'!C21:J1955,8,FALSE) -> 0 | F25: =IFERROR(E25/$E$8,0) -> 0 | G25: 46218 | H25: 46218 | I25: =IF($G25=0,0,IF(I$6<$G25,0,IF(I$6>$H25,1,(I$6-$G25+1)/($H25-$G25+1)))) -> 1 | J25: =IF($G25=0,0,IF(J$6<$G25,0,IF(J$6>$H25,1,(J$6-$G25+1)/($H25-$G25+1)))) -> 1 | K25: =IF($G25=0,0,IF(K$6<$G25,0,IF(K$6>$H25,1,(K$6-$G25+1)/($H25-$G25+1)))) -> 1 | L25: =IF($G25=0,0,IF(L$6<$G25,0,IF(L$6>$H25,1,(L$6-$G25+1)/($H25-$G25+1)))) -> 1 | M25: =IF($G25=0,0,IF(M$6<$G25,0,IF(M$6>$H25,1,(M$6-$G25+1)/($H25-$G25+1)))) -> 1 | N25: =IF($G25=0,0,IF(N$6<$G25,0,IF(N$6>$H25,1,(N$6-$G25+1)/($H25-$G25+1)))) -> 1 | O25: =IF($G25=0,0,IF(O$6<$G25,0,IF(O$6>$H25,1,(O$6-$G25+1)/($H25-$G25+1)))) -> 1 | P25: =IF($G25=0,0,IF(P$6<$G25,0,IF(P$6>$H25,1,(P$6-$G25+1)/($H25-$G25+1)))) -> 1 | ... BO25: =IF($G25=0,0,IF(BO$6<$G25,0,IF(BO$6>$H25,1,(BO$6-$G25+1)/($H25-$G25+1)))) -> 1
B26: 3.12 | C26: REUNIONES RIO MANNAJUYAY | D26: 0 días | E26: =VLOOKUP(B26,'Cuadro Control'!C22:J1956,8,FALSE) -> 0 | F26: =IFERROR(E26/$E$8,0) -> 0 | G26: 46218 | H26: 46218 | I26: =IF($G26=0,0,IF(I$6<$G26,0,IF(I$6>$H26,1,(I$6-$G26+1)/($H26-$G26+1)))) -> 1 | J26: =IF($G26=0,0,IF(J$6<$G26,0,IF(J$6>$H26,1,(J$6-$G26+1)/($H26-$G26+1)))) -> 1 | K26: =IF($G26=0,0,IF(K$6<$G26,0,IF(K$6>$H26,1,(K$6-$G26+1)/($H26-$G26+1)))) -> 1 | L26: =IF($G26=0,0,IF(L$6<$G26,0,IF(L$6>$H26,1,(L$6-$G26+1)/($H26-$G26+1)))) -> 1 | M26: =IF($G26=0,0,IF(M$6<$G26,0,IF(M$6>$H26,1,(M$6-$G26+1)/($H26-$G26+1)))) -> 1 | N26: =IF($G26=0,0,IF(N$6<$G26,0,IF(N$6>$H26,1,(N$6-$G26+1)/($H26-$G26+1)))) -> 1 | O26: =IF($G26=0,0,IF(O$6<$G26,0,IF(O$6>$H26,1,(O$6-$G26+1)/($H26-$G26+1)))) -> 1 | P26: =IF($G26=0,0,IF(P$6<$G26,0,IF(P$6>$H26,1,(P$6-$G26+1)/($H26-$G26+1)))) -> 1 | ... BO26: =IF($G26=0,0,IF(BO$6<$G26,0,IF(BO$6>$H26,1,(BO$6-$G26+1)/($H26-$G26+1)))) -> 1
... B28: 3.14 | C28: REUNIONES RIO JAMUCHERRU | D28: 0 días | E28: =VLOOKUP(B28,'Cuadro Control'!C24:J1958,8,FALSE) -> 0 | F28: =IFERROR(E28/$E$8,0) -> 0 | G28: 46252 | H28: 46252 | I28: =IF($G28=0,0,IF(I$6<$G28,0,IF(I$6>$H28,1,(I$6-$G28+1)/($H28-$G28+1)))) -> 0 | J28: =IF($G28=0,0,IF(J$6<$G28,0,IF(J$6>$H28,1,(J$6-$G28+1)/($H28-$G28+1)))) -> 0 | K28: =IF($G28=0,0,IF(K$6<$G28,0,IF(K$6>$H28,1,(K$6-$G28+1)/($H28-$G28+1)))) -> 0 | L28: =IF($G28=0,0,IF(L$6<$G28,0,IF(L$6>$H28,1,(L$6-$G28+1)/($H28-$G28+1)))) -> 0 | M28: =IF($G28=0,0,IF(M$6<$G28,0,IF(M$6>$H28,1,(M$6-$G28+1)/($H28-$G28+1)))) -> 0 | N28: =IF($G28=0,0,IF(N$6<$G28,0,IF(N$6>$H28,1,(N$6-$G28+1)/($H28-$G28+1)))) -> 0 | O28: =IF($G28=0,0,IF(O$6<$G28,0,IF(O$6>$H28,1,(O$6-$G28+1)/($H28-$G28+1)))) -> 1 | P28: =IF($G28=0,0,IF(P$6<$G28,0,IF(P$6>$H28,1,(P$6-$G28+1)/($H28-$G28+1)))) -> 1 | ... BO28: =IF($G28=0,0,IF(BO$6<$G28,0,IF(BO$6>$H28,1,(BO$6-$G28+1)/($H28-$G28+1)))) -> 1
B29: 4 | C29: PUBLICACIÓN DE VACANTES/CONTRATACIÓN DE PERSONAL | D29: 20 días | E29: =VLOOKUP(B29,'Cuadro Control'!C25:J1959,8,FALSE) -> 0 | F29: =IFERROR(E29/$E$8,0) -> 0 | G29: 46218 | H29: 46239 | I29: =IF($G29=0,0,IF(I$6<$G29,0,IF(I$6>$H29,1,(I$6-$G29+1)/($H29-$G29+1)))) -> 0.045454545 | J29: =IF($G29=0,0,IF(J$6<$G29,0,IF(J$6>$H29,1,(J$6-$G29+1)/($H29-$G29+1)))) -> 0.13636364 | K29: =IF($G29=0,0,IF(K$6<$G29,0,IF(K$6>$H29,1,(K$6-$G29+1)/($H29-$G29+1)))) -> 0.45454545 | L29: =IF($G29=0,0,IF(L$6<$G29,0,IF(L$6>$H29,1,(L$6-$G29+1)/($H29-$G29+1)))) -> 0.77272727 | M29: =IF($G29=0,0,IF(M$6<$G29,0,IF(M$6>$H29,1,(M$6-$G29+1)/($H29-$G29+1)))) -> 1 | N29: =IF($G29=0,0,IF(N$6<$G29,0,IF(N$6>$H29,1,(N$6-$G29+1)/($H29-$G29+1)))) -> 1 | O29: =IF($G29=0,0,IF(O$6<$G29,0,IF(O$6>$H29,1,(O$6-$G29+1)/($H29-$G29+1)))) -> 1 | P29: =IF($G29=0,0,IF(P$6<$G29,0,IF(P$6>$H29,1,(P$6-$G29+1)/($H29-$G29+1)))) -> 1 | ... BO29: =IF($G29=0,0,IF(BO$6<$G29,0,IF(BO$6>$H29,1,(BO$6-$G29+1)/($H29-$G29+1)))) -> 1
B30: 5 | C30: SUMINISTRO DE MATERIALES | D30: 21 días | E30: =VLOOKUP(B30,'Cuadro Control'!C26:J1960,8,FALSE) -> 0 | F30: =IFERROR(E30/$E$8,0) -> 0 | G30: 46240 | H30: 46273 | I30: =IF($G30=0,0,IF(I$6<$G30,0,IF(I$6>$H30,1,(I$6-$G30+1)/($H30-$G30+1)))) -> 0 | J30: =IF($G30=0,0,IF(J$6<$G30,0,IF(J$6>$H30,1,(J$6-$G30+1)/($H30-$G30+1)))) -> 0 | K30: =IF($G30=0,0,IF(K$6<$G30,0,IF(K$6>$H30,1,(K$6-$G30+1)/($H30-$G30+1)))) -> 0 | L30: =IF($G30=0,0,IF(L$6<$G30,0,IF(L$6>$H30,1,(L$6-$G30+1)/($H30-$G30+1)))) -> 0 | M30: =IF($G30=0,0,IF(M$6<$G30,0,IF(M$6>$H30,1,(M$6-$G30+1)/($H30-$G30+1)))) -> 0.058823529 | N30: =IF($G30=0,0,IF(N$6<$G30,0,IF(N$6>$H30,1,(N$6-$G30+1)/($H30-$G30+1)))) -> 0.26470588 | O30: =IF($G30=0,0,IF(O$6<$G30,0,IF(O$6>$H30,1,(O$6-$G30+1)/($H30-$G30+1)))) -> 0.47058824 | P30: =IF($G30=0,0,IF(P$6<$G30,0,IF(P$6>$H30,1,(P$6-$G30+1)/($H30-$G30+1)))) -> 0.67647059 | ... BO30: =IF($G30=0,0,IF(BO$6<$G30,0,IF(BO$6>$H30,1,(BO$6-$G30+1)/($H30-$G30+1)))) -> 1
B31: 5.1 | C31: SUMINISTRO DE MATERIALES CIVILES: ANCHOR CAGE (CLIENTE) | D31: 14 días | E31: =VLOOKUP(B31,'Cuadro Control'!C27:J1961,8,FALSE) -> 0 | F31: =IFERROR(E31/$E$30,0) -> 0 | G31: 46240 | H31: 46258 | I31: =IF($G31=0,0,IF(I$6<$G31,0,IF(I$6>$H31,1,(I$6-$G31+1)/($H31-$G31+1)))) -> 0 | J31: =IF($G31=0,0,IF(J$6<$G31,0,IF(J$6>$H31,1,(J$6-$G31+1)/($H31-$G31+1)))) -> 0 | K31: =IF($G31=0,0,IF(K$6<$G31,0,IF(K$6>$H31,1,(K$6-$G31+1)/($H31-$G31+1)))) -> 0 | L31: =IF($G31=0,0,IF(L$6<$G31,0,IF(L$6>$H31,1,(L$6-$G31+1)/($H31-$G31+1)))) -> 0 | M31: =IF($G31=0,0,IF(M$6<$G31,0,IF(M$6>$H31,1,(M$6-$G31+1)/($H31-$G31+1)))) -> 0.10526316 | N31: =IF($G31=0,0,IF(N$6<$G31,0,IF(N$6>$H31,1,(N$6-$G31+1)/($H31-$G31+1)))) -> 0.47368421 | O31: =IF($G31=0,0,IF(O$6<$G31,0,IF(O$6>$H31,1,(O$6-$G31+1)/($H31-$G31+1)))) -> 0.84210526 | P31: =IF($G31=0,0,IF(P$6<$G31,0,IF(P$6>$H31,1,(P$6-$G31+1)/($H31-$G31+1)))) -> 1 | ... BO31: =IF($G31=0,0,IF(BO$6<$G31,0,IF(BO$6>$H31,1,(BO$6-$G31+1)/($H31-$G31+1)))) -> 1
B32: 5.2 | C32: SUMINISTRO DE MATERIALES CIVILES: ACEROS DE REFUERSO | D32: 7 días | E32: =VLOOKUP(B32,'Cuadro Control'!C28:J1962,8,FALSE) -> 0 | F32: =IFERROR(E32/$E$30,0) -> 0 | G32: 46258 | H32: 46273 | I32: =IF($G32=0,0,IF(I$6<$G32,0,IF(I$6>$H32,1,(I$6-$G32+1)/($H32-$G32+1)))) -> 0 | J32: =IF($G32=0,0,IF(J$6<$G32,0,IF(J$6>$H32,1,(J$6-$G32+1)/($H32-$G32+1)))) -> 0 | K32: =IF($G32=0,0,IF(K$6<$G32,0,IF(K$6>$H32,1,(K$6-$G32+1)/($H32-$G32+1)))) -> 0 | L32: =IF($G32=0,0,IF(L$6<$G32,0,IF(L$6>$H32,1,(L$6-$G32+1)/($H32-$G32+1)))) -> 0 | M32: =IF($G32=0,0,IF(M$6<$G32,0,IF(M$6>$H32,1,(M$6-$G32+1)/($H32-$G32+1)))) -> 0 | N32: =IF($G32=0,0,IF(N$6<$G32,0,IF(N$6>$H32,1,(N$6-$G32+1)/($H32-$G32+1)))) -> 0 | O32: =IF($G32=0,0,IF(O$6<$G32,0,IF(O$6>$H32,1,(O$6-$G32+1)/($H32-$G32+1)))) -> 0 | P32: =IF($G32=0,0,IF(P$6<$G32,0,IF(P$6>$H32,1,(P$6-$G32+1)/($H32-$G32+1)))) -> 0.3125 | ... BO32: =IF($G32=0,0,IF(BO$6<$G32,0,IF(BO$6>$H32,1,(BO$6-$G32+1)/($H32-$G32+1)))) -> 1
B33: 6 | C33: HITO 2: INICIO DE ACTIVIDADES EN CAMPO | D33: 0 días | E33: =VLOOKUP(B33,'Cuadro Control'!C29:J1963,8,FALSE) -> 0 | F33: =IFERROR(E33/$E$8,0) -> 0 | G33: 46239 | H33: 46239 | I33: =IF($G33=0,0,IF(I$6<$G33,0,IF(I$6>$H33,1,(I$6-$G33+1)/($H33-$G33+1)))) -> 0 | J33: =IF($G33=0,0,IF(J$6<$G33,0,IF(J$6>$H33,1,(J$6-$G33+1)/($H33-$G33+1)))) -> 0 | K33: =IF($G33=0,0,IF(K$6<$G33,0,IF(K$6>$H33,1,(K$6-$G33+1)/($H33-$G33+1)))) -> 0 | L33: =IF($G33=0,0,IF(L$6<$G33,0,IF(L$6>$H33,1,(L$6-$G33+1)/($H33-$G33+1)))) -> 0 | M33: =IF($G33=0,0,IF(M$6<$G33,0,IF(M$6>$H33,1,(M$6-$G33+1)/($H33-$G33+1)))) -> 1 | N33: =IF($G33=0,0,IF(N$6<$G33,0,IF(N$6>$H33,1,(N$6-$G33+1)/($H33-$G33+1)))) -> 1 | O33: =IF($G33=0,0,IF(O$6<$G33,0,IF(O$6>$H33,1,(O$6-$G33+1)/($H33-$G33+1)))) -> 1 | P33: =IF($G33=0,0,IF(P$6<$G33,0,IF(P$6>$H33,1,(P$6-$G33+1)/($H33-$G33+1)))) -> 1 | ... BO33: =IF($G33=0,0,IF(BO$6<$G33,0,IF(BO$6>$H33,1,(BO$6-$G33+1)/($H33-$G33+1)))) -> 1
B34: 7 | C34: PISCINA INDUSTRIAL | D34: 32 días | E34: =SUM(E35:E38) -> 4.6179078e+08 | F34: =IFERROR(E34/$E$8,0) -> 0.0022153966 | G34: 46240 | H34: 46276 | I34: =SUMPRODUCT($F35:$F38,I35:I38) -> 0 | J34: =SUMPRODUCT($F35:$F38,J35:J38) -> 0 | K34: =SUMPRODUCT($F35:$F38,K35:K38) -> 0 | L34: =SUMPRODUCT($F35:$F38,L35:L38) -> 0 | M34: =SUMPRODUCT($F35:$F38,M35:M38) -> 0 | N34: =SUMPRODUCT($F35:$F38,N35:N38) -> 0 | O34: =SUMPRODUCT($F35:$F38,O35:O38) -> 0 | P34: =SUMPRODUCT($F35:$F38,P35:P38) -> 0 | ... BO34: =SUMPRODUCT($F35:$F38,BO35:BO38) -> 1
B35: 7.1 | C35: MOVIMIENTO DE TIERRAS Y RECONFORMACION PISCINA INDUSTRIAL | D35: 14 días | E35: =VLOOKUP(B35,'Cuadro Control'!C31:J1965,8,FALSE) -> 0 | F35: =IFERROR(E35/$E$34,0) -> 0 | G35: 46240 | H35: 46258 | I35: =IF($G35=0,0,IF(I$6<$G35,0,IF(I$6>$H35,1,(I$6-$G35+1)/($H35-$G35+1)))) -> 0 | J35: =IF($G35=0,0,IF(J$6<$G35,0,IF(J$6>$H35,1,(J$6-$G35+1)/($H35-$G35+1)))) -> 0 | K35: =IF($G35=0,0,IF(K$6<$G35,0,IF(K$6>$H35,1,(K$6-$G35+1)/($H35-$G35+1)))) -> 0 | L35: =IF($G35=0,0,IF(L$6<$G35,0,IF(L$6>$H35,1,(L$6-$G35+1)/($H35-$G35+1)))) -> 0 | M35: =IF($G35=0,0,IF(M$6<$G35,0,IF(M$6>$H35,1,(M$6-$G35+1)/($H35-$G35+1)))) -> 0.10526316 | N35: =IF($G35=0,0,IF(N$6<$G35,0,IF(N$6>$H35,1,(N$6-$G35+1)/($H35-$G35+1)))) -> 0.47368421 | O35: =IF($G35=0,0,IF(O$6<$G35,0,IF(O$6>$H35,1,(O$6-$G35+1)/($H35-$G35+1)))) -> 0.84210526 | P35: =IF($G35=0,0,IF(P$6<$G35,0,IF(P$6>$H35,1,(P$6-$G35+1)/($H35-$G35+1)))) -> 1 | ... BO35: =IF($G35=0,0,IF(BO$6<$G35,0,IF(BO$6>$H35,1,(BO$6-$G35+1)/($H35-$G35+1)))) -> 1
B36: 7.2 | C36: INSTALACION DE GEOMEMBRANA PISCINA INDUSTRIAL | D36: 10 días | E36: =VLOOKUP(B36,'Cuadro Control'!C32:J1966,8,FALSE) -> 0 | F36: =IFERROR(E36/$E$34,0) -> 0 | G36: 46258 | H36: 46268 | I36: =IF($G36=0,0,IF(I$6<$G36,0,IF(I$6>$H36,1,(I$6-$G36+1)/($H36-$G36+1)))) -> 0 | J36: =IF($G36=0,0,IF(J$6<$G36,0,IF(J$6>$H36,1,(J$6-$G36+1)/($H36-$G36+1)))) -> 0 | K36: =IF($G36=0,0,IF(K$6<$G36,0,IF(K$6>$H36,1,(K$6-$G36+1)/($H36-$G36+1)))) -> 0 | L36: =IF($G36=0,0,IF(L$6<$G36,0,IF(L$6>$H36,1,(L$6-$G36+1)/($H36-$G36+1)))) -> 0 | M36: =IF($G36=0,0,IF(M$6<$G36,0,IF(M$6>$H36,1,(M$6-$G36+1)/($H36-$G36+1)))) -> 0 | N36: =IF($G36=0,0,IF(N$6<$G36,0,IF(N$6>$H36,1,(N$6-$G36+1)/($H36-$G36+1)))) -> 0 | O36: =IF($G36=0,0,IF(O$6<$G36,0,IF(O$6>$H36,1,(O$6-$G36+1)/($H36-$G36+1)))) -> 0 | P36: =IF($G36=0,0,IF(P$6<$G36,0,IF(P$6>$H36,1,(P$6-$G36+1)/($H36-$G36+1)))) -> 0.45454545 | ... BO36: =IF($G36=0,0,IF(BO$6<$G36,0,IF(BO$6>$H36,1,(BO$6-$G36+1)/($H36-$G36+1)))) -> 1
B37: 7.3 | C37: CONSTRUCCION DE CERRAMIENTO EN ALAMBRE DE PUA PISCINA INDUSTRIAL | D37: 14 días | E37: =VLOOKUP(B37,'Cuadro Control'!C33:J1967,8,FALSE) -> 0 | F37: =IFERROR(E37/$E$34,0) -> 0 | G37: 46245 | H37: 46261 | I37: =IF($G37=0,0,IF(I$6<$G37,0,IF(I$6>$H37,1,(I$6-$G37+1)/($H37-$G37+1)))) -> 0 | J37: =IF($G37=0,0,IF(J$6<$G37,0,IF(J$6>$H37,1,(J$6-$G37+1)/($H37-$G37+1)))) -> 0 | K37: =IF($G37=0,0,IF(K$6<$G37,0,IF(K$6>$H37,1,(K$6-$G37+1)/($H37-$G37+1)))) -> 0 | L37: =IF($G37=0,0,IF(L$6<$G37,0,IF(L$6>$H37,1,(L$6-$G37+1)/($H37-$G37+1)))) -> 0 | M37: =IF($G37=0,0,IF(M$6<$G37,0,IF(M$6>$H37,1,(M$6-$G37+1)/($H37-$G37+1)))) -> 0 | N37: =IF($G37=0,0,IF(N$6<$G37,0,IF(N$6>$H37,1,(N$6-$G37+1)/($H37-$G37+1)))) -> 0.23529412 | O37: =IF($G37=0,0,IF(O$6<$G37,0,IF(O$6>$H37,1,(O$6-$G37+1)/($H37-$G37+1)))) -> 0.64705882 | P37: =IF($G37=0,0,IF(P$6<$G37,0,IF(P$6>$H37,1,(P$6-$G37+1)/($H37-$G37+1)))) -> 1 | ... BO37: =IF($G37=0,0,IF(BO$6<$G37,0,IF(BO$6>$H37,1,(BO$6-$G37+1)/($H37-$G37+1)))) -> 1
B38: 7.4 | C38: CONSTRUCCION CUNETA PERIMETRAL PISCINA INDUSTRIAL | D38: 8 días | E38: =VLOOKUP(B38,'Cuadro Control'!C34:J1968,8,FALSE) -> 4.6179078e+08 | F38: =IFERROR(E38/$E$34,0) -> 1 | G38: 46268 | H38: 46276 | I38: =IF($G38=0,0,IF(I$6<$G38,0,IF(I$6>$H38,1,(I$6-$G38+1)/($H38-$G38+1)))) -> 0 | J38: =IF($G38=0,0,IF(J$6<$G38,0,IF(J$6>$H38,1,(J$6-$G38+1)/($H38-$G38+1)))) -> 0 | K38: =IF($G38=0,0,IF(K$6<$G38,0,IF(K$6>$H38,1,(K$6-$G38+1)/($H38-$G38+1)))) -> 0 | L38: =IF($G38=0,0,IF(L$6<$G38,0,IF(L$6>$H38,1,(L$6-$G38+1)/($H38-$G38+1)))) -> 0 | M38: =IF($G38=0,0,IF(M$6<$G38,0,IF(M$6>$H38,1,(M$6-$G38+1)/($H38-$G38+1)))) -> 0 | N38: =IF($G38=0,0,IF(N$6<$G38,0,IF(N$6>$H38,1,(N$6-$G38+1)/($H38-$G38+1)))) -> 0 | O38: =IF($G38=0,0,IF(O$6<$G38,0,IF(O$6>$H38,1,(O$6-$G38+1)/($H38-$G38+1)))) -> 0 | P38: =IF($G38=0,0,IF(P$6<$G38,0,IF(P$6>$H38,1,(P$6-$G38+1)/($H38-$G38+1)))) -> 0 | ... BO38: =IF($G38=0,0,IF(BO$6<$G38,0,IF(BO$6>$H38,1,(BO$6-$G38+1)/($H38-$G38+1)))) -> 1
B39: 8 | C39: ZONAS DE CAMPAMENTOS - FAENAS | D39: 305 días | E39: =SUM(E40:E43) -> 8.3636378e+09 | F39: =IFERROR(E39/$E$8,0) -> 0.040123744 | G39: 46256 | H39: 46596 | I39: =SUMPRODUCT($F40:$F43,I40:I43) -> 0 | J39: =SUMPRODUCT($F40:$F43,J40:J43) -> 0 | K39: =SUMPRODUCT($F40:$F43,K40:K43) -> 0 | L39: =SUMPRODUCT($F40:$F43,L40:L43) -> 0 | M39: =SUMPRODUCT($F40:$F43,M40:M43) -> 0 | N39: =SUMPRODUCT($F40:$F43,N40:N43) -> 0 | O39: =SUMPRODUCT($F40:$F43,O40:O43) -> 0 | P39: =SUMPRODUCT($F40:$F43,P40:P43) -> 0.00042802934 | ... BO39: =SUMPRODUCT($F40:$F43,BO40:BO43) -> 1
B40: 8.1 | C40: CONFORMACIÓN DEL AREA ZONAS DE CAMPAMENTOS - FAENAS | D40: 14 días | E40: =VLOOKUP(B40,'Cuadro Control'!C36:J1970,8,FALSE) -> 8694000 | F40: =IFERROR(E40/$E$39,0) -> 0.0010394998 | G40: 46256 | H40: 46272 | I40: =IF($G40=0,0,IF(I$6<$G40,0,IF(I$6>$H40,1,(I$6-$G40+1)/($H40-$G40+1)))) -> 0 | J40: =IF($G40=0,0,IF(J$6<$G40,0,IF(J$6>$H40,1,(J$6-$G40+1)/($H40-$G40+1)))) -> 0 | K40: =IF($G40=0,0,IF(K$6<$G40,0,IF(K$6>$H40,1,(K$6-$G40+1)/($H40-$G40+1)))) -> 0 | L40: =IF($G40=0,0,IF(L$6<$G40,0,IF(L$6>$H40,1,(L$6-$G40+1)/($H40-$G40+1)))) -> 0 | M40: =IF($G40=0,0,IF(M$6<$G40,0,IF(M$6>$H40,1,(M$6-$G40+1)/($H40-$G40+1)))) -> 0 | N40: =IF($G40=0,0,IF(N$6<$G40,0,IF(N$6>$H40,1,(N$6-$G40+1)/($H40-$G40+1)))) -> 0 | O40: =IF($G40=0,0,IF(O$6<$G40,0,IF(O$6>$H40,1,(O$6-$G40+1)/($H40-$G40+1)))) -> 0 | P40: =IF($G40=0,0,IF(P$6<$G40,0,IF(P$6>$H40,1,(P$6-$G40+1)/($H40-$G40+1)))) -> 0.41176471 | ... BO40: =IF($G40=0,0,IF(BO$6<$G40,0,IF(BO$6>$H40,1,(BO$6-$G40+1)/($H40-$G40+1)))) -> 1
B41: 8.2 | C41: INSTALACIÓN DE CONTENEDORES Y EQUIPOS ZONAS DE CAMPAMENTOS - FAENAS | D41: 10 días | E41: =VLOOKUP(B41,'Cuadro Control'!C37:J1971,8,FALSE) -> 5260179.1 | F41: =IFERROR(E41/$E$39,0) -> 0.00062893435 | G41: 46272 | H41: 46282 | I41: =IF($G41=0,0,IF(I$6<$G41,0,IF(I$6>$H41,1,(I$6-$G41+1)/($H41-$G41+1)))) -> 0 | J41: =IF($G41=0,0,IF(J$6<$G41,0,IF(J$6>$H41,1,(J$6-$G41+1)/($H41-$G41+1)))) -> 0 | K41: =IF($G41=0,0,IF(K$6<$G41,0,IF(K$6>$H41,1,(K$6-$G41+1)/($H41-$G41+1)))) -> 0 | L41: =IF($G41=0,0,IF(L$6<$G41,0,IF(L$6>$H41,1,(L$6-$G41+1)/($H41-$G41+1)))) -> 0 | M41: =IF($G41=0,0,IF(M$6<$G41,0,IF(M$6>$H41,1,(M$6-$G41+1)/($H41-$G41+1)))) -> 0 | N41: =IF($G41=0,0,IF(N$6<$G41,0,IF(N$6>$H41,1,(N$6-$G41+1)/($H41-$G41+1)))) -> 0 | O41: =IF($G41=0,0,IF(O$6<$G41,0,IF(O$6>$H41,1,(O$6-$G41+1)/($H41-$G41+1)))) -> 0 | P41: =IF($G41=0,0,IF(P$6<$G41,0,IF(P$6>$H41,1,(P$6-$G41+1)/($H41-$G41+1)))) -> 0 | ... BO41: =IF($G41=0,0,IF(BO$6<$G41,0,IF(BO$6>$H41,1,(BO$6-$G41+1)/($H41-$G41+1)))) -> 1
B42: 8.3 | C42: INSTALACIÓN DE LAS FACILIDADES ELECTRICAS E HIDRÚALICAS DE LOS CONTENEDORES ZONAS DE CAMPAMENTOS - FAENAS | D42: 8 días | E42: =VLOOKUP(B42,'Cuadro Control'!C38:J1972,8,FALSE) -> 70893128 | F42: =IFERROR(E42/$E$39,0) -> 0.0084763508 | G42: 46282 | H42: 46290 | I42: =IF($G42=0,0,IF(I$6<$G42,0,IF(I$6>$H42,1,(I$6-$G42+1)/($H42-$G42+1)))) -> 0 | J42: =IF($G42=0,0,IF(J$6<$G42,0,IF(J$6>$H42,1,(J$6-$G42+1)/($H42-$G42+1)))) -> 0 | K42: =IF($G42=0,0,IF(K$6<$G42,0,IF(K$6>$H42,1,(K$6-$G42+1)/($H42-$G42+1)))) -> 0 | L42: =IF($G42=0,0,IF(L$6<$G42,0,IF(L$6>$H42,1,(L$6-$G42+1)/($H42-$G42+1)))) -> 0 | M42: =IF($G42=0,0,IF(M$6<$G42,0,IF(M$6>$H42,1,(M$6-$G42+1)/($H42-$G42+1)))) -> 0 | N42: =IF($G42=0,0,IF(N$6<$G42,0,IF(N$6>$H42,1,(N$6-$G42+1)/($H42-$G42+1)))) -> 0 | O42: =IF($G42=0,0,IF(O$6<$G42,0,IF(O$6>$H42,1,(O$6-$G42+1)/($H42-$G42+1)))) -> 0 | P42: =IF($G42=0,0,IF(P$6<$G42,0,IF(P$6>$H42,1,(P$6-$G42+1)/($H42-$G42+1)))) -> 0 | ... BO42: =IF($G42=0,0,IF(BO$6<$G42,0,IF(BO$6>$H42,1,(BO$6-$G42+1)/($H42-$G42+1)))) -> 1
B43: 8.4 | C43: ADMINISTRACIÓN Y MANTENIMIENTO DE CAMPAMENTOS | D43: 280 días | E43: =VLOOKUP(B43,'Cuadro Control'!C40:J1973,8,FALSE) -> 8.2787905e+09 | F43: =IFERROR(E43/$E$39,0) -> 0.98985521 | G43: 46283 | H43: 46596 | I43: =IF($G43=0,0,IF(I$6<$G43,0,IF(I$6>$H43,1,(I$6-$G43+1)/($H43-$G43+1)))) -> 0 | J43: =IF($G43=0,0,IF(J$6<$G43,0,IF(J$6>$H43,1,(J$6-$G43+1)/($H43-$G43+1)))) -> 0 | K43: =IF($G43=0,0,IF(K$6<$G43,0,IF(K$6>$H43,1,(K$6-$G43+1)/($H43-$G43+1)))) -> 0 | L43: =IF($G43=0,0,IF(L$6<$G43,0,IF(L$6>$H43,1,(L$6-$G43+1)/($H43-$G43+1)))) -> 0 | M43: =IF($G43=0,0,IF(M$6<$G43,0,IF(M$6>$H43,1,(M$6-$G43+1)/($H43-$G43+1)))) -> 0 | N43: =IF($G43=0,0,IF(N$6<$G43,0,IF(N$6>$H43,1,(N$6-$G43+1)/($H43-$G43+1)))) -> 0 | O43: =IF($G43=0,0,IF(O$6<$G43,0,IF(O$6>$H43,1,(O$6-$G43+1)/($H43-$G43+1)))) -> 0 | P43: =IF($G43=0,0,IF(P$6<$G43,0,IF(P$6>$H43,1,(P$6-$G43+1)/($H43-$G43+1)))) -> 0 | ... BO43: =IF($G43=0,0,IF(BO$6<$G43,0,IF(BO$6>$H43,1,(BO$6-$G43+1)/($H43-$G43+1)))) -> 1
B44: 9 | C44: EJECUCIÓN DE ACTIVIDADES DE CIMENTACIONES EXISTENTES | D44: 101 días | E44: =+E45+E54+E63+E72+E81+E90+E99 -> 6.4606628e+09 | F44: =IFERROR(E44/$E$8,0) -> 0.030994405 | G44: 46244 | H44: 46352 | I44: =$F45*I45+$F54*I54+$F63*I63+$F72*I72+$F81*I81+$F90*I90+$F99*I99 -> 0 | J44: =$F45*J45+$F54*J54+$F63*J63+$F72*J72+$F81*J81+$F90*J90+$F99*J99 -> 0 | K44: =$F45*K45+$F54*K54+$F63*K63+$F72*K72+$F81*K81+$F90*K90+$F99*K99 -> 0 | L44: =$F45*L45+$F54*L54+$F63*L63+$F72*L72+$F81*L81+$F90*L90+$F99*L99 -> 0 | M44: =$F45*M45+$F54*M54+$F63*M63+$F72*M72+$F81*M81+$F90*M90+$F99*M99 -> 0 | N44: =$F45*N45+$F54*N54+$F63*N63+$F72*N72+$F81*N81+$F90*N90+$F99*N99 -> 0.029591837 | O44: =$F45*O45+$F54*O54+$F63*O63+$F72*O72+$F81*O81+$F90*O90+$F99*O99 -> 0.074489796 | P44: =$F45*P45+$F54*P54+$F63*P63+$F72*P72+$F81*P81+$F90*P90+$F99*P99 -> 0.12988095 | ... BO44: =$F45*BO45+$F54*BO54+$F63*BO63+$F72*BO72+$F81*BO81+$F90*BO90+$F99*BO99 -> 1
B45: 9.1 | C45: RECALCE 1 WP44 | D45: 18 | E45: =SUM(E46:E53) -> 9.2295182e+08 | F45: =IFERROR(E45/$E$44,0) -> 0.14285714 | G45: 46244 | H45: 46317 | I45: =SUMPRODUCT($F46:$F53,I46:I53) -> 0 | J45: =SUMPRODUCT($F46:$F53,J46:J53) -> 0 | K45: =SUMPRODUCT($F46:$F53,K46:K53) -> 0 | L45: =SUMPRODUCT($F46:$F53,L46:L53) -> 0 | M45: =SUMPRODUCT($F46:$F53,M46:M53) -> 0 | N45: =SUMPRODUCT($F46:$F53,N46:N53) -> 0.20714286 | O45: =SUMPRODUCT($F46:$F53,O46:O53) -> 0.35 | P45: =SUMPRODUCT($F46:$F53,P46:P53) -> 0.35 | ... BO45: =SUMPRODUCT($F46:$F53,BO46:BO53) -> 1
B46: 9.1.1 | C46: LOCALIZACIÓN DEL ACERO WP44 | D46: 1 | E46: =VLOOKUP(B46,'Cuadro Control'!C46:J1976,8,FALSE) -> 90662605 | F46: 0.1 | G46: 46244 | H46: 46246 | I46: =IF($G46=0,0,IF(I$6<$G46,0,IF(I$6>$H46,1,(I$6-$G46+1)/($H46-$G46+1)))) -> 0 | J46: =IF($G46=0,0,IF(J$6<$G46,0,IF(J$6>$H46,1,(J$6-$G46+1)/($H46-$G46+1)))) -> 0 | K46: =IF($G46=0,0,IF(K$6<$G46,0,IF(K$6>$H46,1,(K$6-$G46+1)/($H46-$G46+1)))) -> 0 | L46: =IF($G46=0,0,IF(L$6<$G46,0,IF(L$6>$H46,1,(L$6-$G46+1)/($H46-$G46+1)))) -> 0 | M46: =IF($G46=0,0,IF(M$6<$G46,0,IF(M$6>$H46,1,(M$6-$G46+1)/($H46-$G46+1)))) -> 0 | N46: =IF($G46=0,0,IF(N$6<$G46,0,IF(N$6>$H46,1,(N$6-$G46+1)/($H46-$G46+1)))) -> 1 | O46: =IF($G46=0,0,IF(O$6<$G46,0,IF(O$6>$H46,1,(O$6-$G46+1)/($H46-$G46+1)))) -> 1 | P46: =IF($G46=0,0,IF(P$6<$G46,0,IF(P$6>$H46,1,(P$6-$G46+1)/($H46-$G46+1)))) -> 1 | ... BO46: =IF($G46=0,0,IF(BO$6<$G46,0,IF(BO$6>$H46,1,(BO$6-$G46+1)/($H46-$G46+1)))) -> 1
B47: 9.1.2 | C47: PERFORACION, ESCARIFICADO Y LIMPIEZA DEL RECUBRIMIENTO WP44 | D47: 4 | E47: =VLOOKUP(B47,'Cuadro Control'!C47:J1977,8,FALSE) -> 2.3077754e+08 | F47: 0.25 | G47: 46246 | H47: 46252 | I47: =IF($G47=0,0,IF(I$6<$G47,0,IF(I$6>$H47,1,(I$6-$G47+1)/($H47-$G47+1)))) -> 0 | J47: =IF($G47=0,0,IF(J$6<$G47,0,IF(J$6>$H47,1,(J$6-$G47+1)/($H47-$G47+1)))) -> 0 | K47: =IF($G47=0,0,IF(K$6<$G47,0,IF(K$6>$H47,1,(K$6-$G47+1)/($H47-$G47+1)))) -> 0 | L47: =IF($G47=0,0,IF(L$6<$G47,0,IF(L$6>$H47,1,(L$6-$G47+1)/($H47-$G47+1)))) -> 0 | M47: =IF($G47=0,0,IF(M$6<$G47,0,IF(M$6>$H47,1,(M$6-$G47+1)/($H47-$G47+1)))) -> 0 | N47: =IF($G47=0,0,IF(N$6<$G47,0,IF(N$6>$H47,1,(N$6-$G47+1)/($H47-$G47+1)))) -> 0.42857143 | O47: =IF($G47=0,0,IF(O$6<$G47,0,IF(O$6>$H47,1,(O$6-$G47+1)/($H47-$G47+1)))) -> 1 | P47: =IF($G47=0,0,IF(P$6<$G47,0,IF(P$6>$H47,1,(P$6-$G47+1)/($H47-$G47+1)))) -> 1 | ... BO47: =IF($G47=0,0,IF(BO$6<$G47,0,IF(BO$6>$H47,1,(BO$6-$G47+1)/($H47-$G47+1)))) -> 1
B48: 9.1.3 | C48: CORTE Y FIGURADO DE ACERO WP44 | D48: 2 | E48: =VLOOKUP(B48,'Cuadro Control'!C48:J1978,8,FALSE) -> 82420550 | F48: 0.09 | G48: 46273 | H48: 46276 | I48: =IF($G48=0,0,IF(I$6<$G48,0,IF(I$6>$H48,1,(I$6-$G48+1)/($H48-$G48+1)))) -> 0 | J48: =IF($G48=0,0,IF(J$6<$G48,0,IF(J$6>$H48,1,(J$6-$G48+1)/($H48-$G48+1)))) -> 0 | K48: =IF($G48=0,0,IF(K$6<$G48,0,IF(K$6>$H48,1,(K$6-$G48+1)/($H48-$G48+1)))) -> 0 | L48: =IF($G48=0,0,IF(L$6<$G48,0,IF(L$6>$H48,1,(L$6-$G48+1)/($H48-$G48+1)))) -> 0 | M48: =IF($G48=0,0,IF(M$6<$G48,0,IF(M$6>$H48,1,(M$6-$G48+1)/($H48-$G48+1)))) -> 0 | N48: =IF($G48=0,0,IF(N$6<$G48,0,IF(N$6>$H48,1,(N$6-$G48+1)/($H48-$G48+1)))) -> 0 | O48: =IF($G48=0,0,IF(O$6<$G48,0,IF(O$6>$H48,1,(O$6-$G48+1)/($H48-$G48+1)))) -> 0 | P48: =IF($G48=0,0,IF(P$6<$G48,0,IF(P$6>$H48,1,(P$6-$G48+1)/($H48-$G48+1)))) -> 0 | ... BO48: =IF($G48=0,0,IF(BO$6<$G48,0,IF(BO$6>$H48,1,(BO$6-$G48+1)/($H48-$G48+1)))) -> 1
B49: 9.1.4 | C49: APLICACIÓN DE EPOXICO Y FIJACIÓN DEL ACERO WP44 | D49: 4 | E49: =VLOOKUP(B49,'Cuadro Control'!C49:J1979,8,FALSE) -> 2.3077754e+08 | F49: 0.25 | G49: 46300 | H49: 46304 | I49: =IF($G49=0,0,IF(I$6<$G49,0,IF(I$6>$H49,1,(I$6-$G49+1)/($H49-$G49+1)))) -> 0 | J49: =IF($G49=0,0,IF(J$6<$G49,0,IF(J$6>$H49,1,(J$6-$G49+1)/($H49-$G49+1)))) -> 0 | K49: =IF($G49=0,0,IF(K$6<$G49,0,IF(K$6>$H49,1,(K$6-$G49+1)/($H49-$G49+1)))) -> 0 | L49: =IF($G49=0,0,IF(L$6<$G49,0,IF(L$6>$H49,1,(L$6-$G49+1)/($H49-$G49+1)))) -> 0 | M49: =IF($G49=0,0,IF(M$6<$G49,0,IF(M$6>$H49,1,(M$6-$G49+1)/($H49-$G49+1)))) -> 0 | N49: =IF($G49=0,0,IF(N$6<$G49,0,IF(N$6>$H49,1,(N$6-$G49+1)/($H49-$G49+1)))) -> 0 | O49: =IF($G49=0,0,IF(O$6<$G49,0,IF(O$6>$H49,1,(O$6-$G49+1)/($H49-$G49+1)))) -> 0 | P49: =IF($G49=0,0,IF(P$6<$G49,0,IF(P$6>$H49,1,(P$6-$G49+1)/($H49-$G49+1)))) -> 0 | ... BO49: =IF($G49=0,0,IF(BO$6<$G49,0,IF(BO$6>$H49,1,(BO$6-$G49+1)/($H49-$G49+1)))) -> 1
B50: 9.1.5 | C50: ENCONFRADO WP44 | D50: 1 | E50: =VLOOKUP(B50,'Cuadro Control'!C50:J1980,8,FALSE) -> 49452330 | F50: 0.05 | G50: 46304 | H50: 46305 | I50: =IF($G50=0,0,IF(I$6<$G50,0,IF(I$6>$H50,1,(I$6-$G50+1)/($H50-$G50+1)))) -> 0 | J50: =IF($G50=0,0,IF(J$6<$G50,0,IF(J$6>$H50,1,(J$6-$G50+1)/($H50-$G50+1)))) -> 0 | K50: =IF($G50=0,0,IF(K$6<$G50,0,IF(K$6>$H50,1,(K$6-$G50+1)/($H50-$G50+1)))) -> 0 | L50: =IF($G50=0,0,IF(L$6<$G50,0,IF(L$6>$H50,1,(L$6-$G50+1)/($H50-$G50+1)))) -> 0 | M50: =IF($G50=0,0,IF(M$6<$G50,0,IF(M$6>$H50,1,(M$6-$G50+1)/($H50-$G50+1)))) -> 0 | N50: =IF($G50=0,0,IF(N$6<$G50,0,IF(N$6>$H50,1,(N$6-$G50+1)/($H50-$G50+1)))) -> 0 | O50: =IF($G50=0,0,IF(O$6<$G50,0,IF(O$6>$H50,1,(O$6-$G50+1)/($H50-$G50+1)))) -> 0 | P50: =IF($G50=0,0,IF(P$6<$G50,0,IF(P$6>$H50,1,(P$6-$G50+1)/($H50-$G50+1)))) -> 0 | ... BO50: =IF($G50=0,0,IF(BO$6<$G50,0,IF(BO$6>$H50,1,(BO$6-$G50+1)/($H50-$G50+1)))) -> 1
B51: 9.1.6 | C51: VACIADO DE CONCRETO (APLICACIÓN PUENTE DE ADHERENCIA) WP44 | D51: 1 | E51: =VLOOKUP(B51,'Cuadro Control'!C51:J1981,8,FALSE) -> 1.4011493e+08 | F51: 0.15 | G51: 46305 | H51: 46308 | I51: =IF($G51=0,0,IF(I$6<$G51,0,IF(I$6>$H51,1,(I$6-$G51+1)/($H51-$G51+1)))) -> 0 | J51: =IF($G51=0,0,IF(J$6<$G51,0,IF(J$6>$H51,1,(J$6-$G51+1)/($H51-$G51+1)))) -> 0 | K51: =IF($G51=0,0,IF(K$6<$G51,0,IF(K$6>$H51,1,(K$6-$G51+1)/($H51-$G51+1)))) -> 0 | L51: =IF($G51=0,0,IF(L$6<$G51,0,IF(L$6>$H51,1,(L$6-$G51+1)/($H51-$G51+1)))) -> 0 | M51: =IF($G51=0,0,IF(M$6<$G51,0,IF(M$6>$H51,1,(M$6-$G51+1)/($H51-$G51+1)))) -> 0 | N51: =IF($G51=0,0,IF(N$6<$G51,0,IF(N$6>$H51,1,(N$6-$G51+1)/($H51-$G51+1)))) -> 0 | O51: =IF($G51=0,0,IF(O$6<$G51,0,IF(O$6>$H51,1,(O$6-$G51+1)/($H51-$G51+1)))) -> 0 | P51: =IF($G51=0,0,IF(P$6<$G51,0,IF(P$6>$H51,1,(P$6-$G51+1)/($H51-$G51+1)))) -> 0 | ... BO51: =IF($G51=0,0,IF(BO$6<$G51,0,IF(BO$6>$H51,1,(BO$6-$G51+1)/($H51-$G51+1)))) -> 1
B52: 9.1.7 | C52: ADECUACIONES E INSTALACIONES ELECTRICAS REQUERIDAS WP44 | D52: 3 | E52: =VLOOKUP(B52,'Cuadro Control'!C52:J1982,8,FALSE) -> 52335716 | F52: 0.06 | G52: 46308 | H52: 46310 | I52: =IF($G52=0,0,IF(I$6<$G52,0,IF(I$6>$H52,1,(I$6-$G52+1)/($H52-$G52+1)))) -> 0 | J52: =IF($G52=0,0,IF(J$6<$G52,0,IF(J$6>$H52,1,(J$6-$G52+1)/($H52-$G52+1)))) -> 0 | K52: =IF($G52=0,0,IF(K$6<$G52,0,IF(K$6>$H52,1,(K$6-$G52+1)/($H52-$G52+1)))) -> 0 | L52: =IF($G52=0,0,IF(L$6<$G52,0,IF(L$6>$H52,1,(L$6-$G52+1)/($H52-$G52+1)))) -> 0 | M52: =IF($G52=0,0,IF(M$6<$G52,0,IF(M$6>$H52,1,(M$6-$G52+1)/($H52-$G52+1)))) -> 0 | N52: =IF($G52=0,0,IF(N$6<$G52,0,IF(N$6>$H52,1,(N$6-$G52+1)/($H52-$G52+1)))) -> 0 | O52: =IF($G52=0,0,IF(O$6<$G52,0,IF(O$6>$H52,1,(O$6-$G52+1)/($H52-$G52+1)))) -> 0 | P52: =IF($G52=0,0,IF(P$6<$G52,0,IF(P$6>$H52,1,(P$6-$G52+1)/($H52-$G52+1)))) -> 0 | ... BO52: =IF($G52=0,0,IF(BO$6<$G52,0,IF(BO$6>$H52,1,(BO$6-$G52+1)/($H52-$G52+1)))) -> 1
B53: 9.1.8 | C53: INSTALACION DE GROUT Y MORTERO AUTOCOMPACTANTE DE ALTA RESISTENCIA WP44 | D53: 2 | E53: =VLOOKUP(B53,'Cuadro Control'!C53:J1983,8,FALSE) -> 46410609 | F53: 0.05 | G53: 46315 | H53: 46317 | I53: =IF($G53=0,0,IF(I$6<$G53,0,IF(I$6>$H53,1,(I$6-$G53+1)/($H53-$G53+1)))) -> 0 | J53: =IF($G53=0,0,IF(J$6<$G53,0,IF(J$6>$H53,1,(J$6-$G53+1)/($H53-$G53+1)))) -> 0 | K53: =IF($G53=0,0,IF(K$6<$G53,0,IF(K$6>$H53,1,(K$6-$G53+1)/($H53-$G53+1)))) -> 0 | L53: =IF($G53=0,0,IF(L$6<$G53,0,IF(L$6>$H53,1,(L$6-$G53+1)/($H53-$G53+1)))) -> 0 | M53: =IF($G53=0,0,IF(M$6<$G53,0,IF(M$6>$H53,1,(M$6-$G53+1)/($H53-$G53+1)))) -> 0 | N53: =IF($G53=0,0,IF(N$6<$G53,0,IF(N$6>$H53,1,(N$6-$G53+1)/($H53-$G53+1)))) -> 0 | O53: =IF($G53=0,0,IF(O$6<$G53,0,IF(O$6>$H53,1,(O$6-$G53+1)/($H53-$G53+1)))) -> 0 | P53: =IF($G53=0,0,IF(P$6<$G53,0,IF(P$6>$H53,1,(P$6-$G53+1)/($H53-$G53+1)))) -> 0 | ... BO53: =IF($G53=0,0,IF(BO$6<$G53,0,IF(BO$6>$H53,1,(BO$6-$G53+1)/($H53-$G53+1)))) -> 1
B54: 9.2 | C54: RECALCE 2 WP45 | D54: 53 días | E54: =SUM(E55:E62) -> 9.2295182e+08 | F54: =IFERROR(E54/$E$44,0) -> 0.14285714 | G54: 46253 | H54: 46316 | I54: =SUMPRODUCT($F55:$F62,I55:I62) -> 0 | J54: =SUMPRODUCT($F55:$F62,J55:J62) -> 0 | K54: =SUMPRODUCT($F55:$F62,K55:K62) -> 0 | L54: =SUMPRODUCT($F55:$F62,L55:L62) -> 0 | M54: =SUMPRODUCT($F55:$F62,M55:M62) -> 0 | N54: =SUMPRODUCT($F55:$F62,N55:N62) -> 0 | O54: =SUMPRODUCT($F55:$F62,O55:O62) -> 0.17142857 | P54: =SUMPRODUCT($F55:$F62,P55:P62) -> 0.4175 | ... BO54: =SUMPRODUCT($F55:$F62,BO55:BO62) -> 1
B55: 9.2.1 | C55: LOCALIZACIÓN DEL ACERO WP45 | D55: 1 día | E55: =VLOOKUP(B55,'Cuadro Control'!C55:J1985,8,FALSE) -> 90662605 | F55: 0.1 | G55: 46253 | H55: 46254 | I55: =IF($G55=0,0,IF(I$6<$G55,0,IF(I$6>$H55,1,(I$6-$G55+1)/($H55-$G55+1)))) -> 0 | J55: =IF($G55=0,0,IF(J$6<$G55,0,IF(J$6>$H55,1,(J$6-$G55+1)/($H55-$G55+1)))) -> 0 | K55: =IF($G55=0,0,IF(K$6<$G55,0,IF(K$6>$H55,1,(K$6-$G55+1)/($H55-$G55+1)))) -> 0 | L55: =IF($G55=0,0,IF(L$6<$G55,0,IF(L$6>$H55,1,(L$6-$G55+1)/($H55-$G55+1)))) -> 0 | M55: =IF($G55=0,0,IF(M$6<$G55,0,IF(M$6>$H55,1,(M$6-$G55+1)/($H55-$G55+1)))) -> 0 | N55: =IF($G55=0,0,IF(N$6<$G55,0,IF(N$6>$H55,1,(N$6-$G55+1)/($H55-$G55+1)))) -> 0 | O55: =IF($G55=0,0,IF(O$6<$G55,0,IF(O$6>$H55,1,(O$6-$G55+1)/($H55-$G55+1)))) -> 1 | P55: =IF($G55=0,0,IF(P$6<$G55,0,IF(P$6>$H55,1,(P$6-$G55+1)/($H55-$G55+1)))) -> 1 | ... BO55: =IF($G55=0,0,IF(BO$6<$G55,0,IF(BO$6>$H55,1,(BO$6-$G55+1)/($H55-$G55+1)))) -> 1
B56: 9.2.2 | C56: PERFORACION, ESCARIFICADO Y LIMPIEZA DEL RECUBRIMIENTO WP45 | D56: 4 días | E56: =VLOOKUP(B56,'Cuadro Control'!C56:J1986,8,FALSE) -> 2.3077754e+08 | F56: 0.25 | G56: 46254 | H56: 46260 | I56: =IF($G56=0,0,IF(I$6<$G56,0,IF(I$6>$H56,1,(I$6-$G56+1)/($H56-$G56+1)))) -> 0 | J56: =IF($G56=0,0,IF(J$6<$G56,0,IF(J$6>$H56,1,(J$6-$G56+1)/($H56-$G56+1)))) -> 0 | K56: =IF($G56=0,0,IF(K$6<$G56,0,IF(K$6>$H56,1,(K$6-$G56+1)/($H56-$G56+1)))) -> 0 | L56: =IF($G56=0,0,IF(L$6<$G56,0,IF(L$6>$H56,1,(L$6-$G56+1)/($H56-$G56+1)))) -> 0 | M56: =IF($G56=0,0,IF(M$6<$G56,0,IF(M$6>$H56,1,(M$6-$G56+1)/($H56-$G56+1)))) -> 0 | N56: =IF($G56=0,0,IF(N$6<$G56,0,IF(N$6>$H56,1,(N$6-$G56+1)/($H56-$G56+1)))) -> 0 | O56: =IF($G56=0,0,IF(O$6<$G56,0,IF(O$6>$H56,1,(O$6-$G56+1)/($H56-$G56+1)))) -> 0.28571429 | P56: =IF($G56=0,0,IF(P$6<$G56,0,IF(P$6>$H56,1,(P$6-$G56+1)/($H56-$G56+1)))) -> 1 | ... BO56: =IF($G56=0,0,IF(BO$6<$G56,0,IF(BO$6>$H56,1,(BO$6-$G56+1)/($H56-$G56+1)))) -> 1
B57: 9.2.3 | C57: CORTE Y FIGURADO DE ACERO WP45 | D57: 2 días | E57: =VLOOKUP(B57,'Cuadro Control'!C57:J1987,8,FALSE) -> 82420550 | F57: 0.09 | G57: 46260 | H57: 46263 | I57: =IF($G57=0,0,IF(I$6<$G57,0,IF(I$6>$H57,1,(I$6-$G57+1)/($H57-$G57+1)))) -> 0 | J57: =IF($G57=0,0,IF(J$6<$G57,0,IF(J$6>$H57,1,(J$6-$G57+1)/($H57-$G57+1)))) -> 0 | K57: =IF($G57=0,0,IF(K$6<$G57,0,IF(K$6>$H57,1,(K$6-$G57+1)/($H57-$G57+1)))) -> 0 | L57: =IF($G57=0,0,IF(L$6<$G57,0,IF(L$6>$H57,1,(L$6-$G57+1)/($H57-$G57+1)))) -> 0 | M57: =IF($G57=0,0,IF(M$6<$G57,0,IF(M$6>$H57,1,(M$6-$G57+1)/($H57-$G57+1)))) -> 0 | N57: =IF($G57=0,0,IF(N$6<$G57,0,IF(N$6>$H57,1,(N$6-$G57+1)/($H57-$G57+1)))) -> 0 | O57: =IF($G57=0,0,IF(O$6<$G57,0,IF(O$6>$H57,1,(O$6-$G57+1)/($H57-$G57+1)))) -> 0 | P57: =IF($G57=0,0,IF(P$6<$G57,0,IF(P$6>$H57,1,(P$6-$G57+1)/($H57-$G57+1)))) -> 0.75 | ... BO57: =IF($G57=0,0,IF(BO$6<$G57,0,IF(BO$6>$H57,1,(BO$6-$G57+1)/($H57-$G57+1)))) -> 1
B58: 9.2.4 | C58: APLICACIÓN DE EPOXICO Y FIJACIÓN DEL ACERO WP45 | D58: 4 días | E58: =VLOOKUP(B58,'Cuadro Control'!C58:J1988,8,FALSE) -> 2.3077754e+08 | F58: 0.25 | G58: 46296 | H58: 46300 | I58: =IF($G58=0,0,IF(I$6<$G58,0,IF(I$6>$H58,1,(I$6-$G58+1)/($H58-$G58+1)))) -> 0 | J58: =IF($G58=0,0,IF(J$6<$G58,0,IF(J$6>$H58,1,(J$6-$G58+1)/($H58-$G58+1)))) -> 0 | K58: =IF($G58=0,0,IF(K$6<$G58,0,IF(K$6>$H58,1,(K$6-$G58+1)/($H58-$G58+1)))) -> 0 | L58: =IF($G58=0,0,IF(L$6<$G58,0,IF(L$6>$H58,1,(L$6-$G58+1)/($H58-$G58+1)))) -> 0 | M58: =IF($G58=0,0,IF(M$6<$G58,0,IF(M$6>$H58,1,(M$6-$G58+1)/($H58-$G58+1)))) -> 0 | N58: =IF($G58=0,0,IF(N$6<$G58,0,IF(N$6>$H58,1,(N$6-$G58+1)/($H58-$G58+1)))) -> 0 | O58: =IF($G58=0,0,IF(O$6<$G58,0,IF(O$6>$H58,1,(O$6-$G58+1)/($H58-$G58+1)))) -> 0 | P58: =IF($G58=0,0,IF(P$6<$G58,0,IF(P$6>$H58,1,(P$6-$G58+1)/($H58-$G58+1)))) -> 0 | ... BO58: =IF($G58=0,0,IF(BO$6<$G58,0,IF(BO$6>$H58,1,(BO$6-$G58+1)/($H58-$G58+1)))) -> 1
B59: 9.2.5 | C59: ENCONFRADO WP45 | D59: 1 día | E59: =VLOOKUP(B59,'Cuadro Control'!C59:J1989,8,FALSE) -> 49452330 | F59: 0.05 | G59: 46300 | H59: 46301 | I59: =IF($G59=0,0,IF(I$6<$G59,0,IF(I$6>$H59,1,(I$6-$G59+1)/($H59-$G59+1)))) -> 0 | J59: =IF($G59=0,0,IF(J$6<$G59,0,IF(J$6>$H59,1,(J$6-$G59+1)/($H59-$G59+1)))) -> 0 | K59: =IF($G59=0,0,IF(K$6<$G59,0,IF(K$6>$H59,1,(K$6-$G59+1)/($H59-$G59+1)))) -> 0 | L59: =IF($G59=0,0,IF(L$6<$G59,0,IF(L$6>$H59,1,(L$6-$G59+1)/($H59-$G59+1)))) -> 0 | M59: =IF($G59=0,0,IF(M$6<$G59,0,IF(M$6>$H59,1,(M$6-$G59+1)/($H59-$G59+1)))) -> 0 | N59: =IF($G59=0,0,IF(N$6<$G59,0,IF(N$6>$H59,1,(N$6-$G59+1)/($H59-$G59+1)))) -> 0 | O59: =IF($G59=0,0,IF(O$6<$G59,0,IF(O$6>$H59,1,(O$6-$G59+1)/($H59-$G59+1)))) -> 0 | P59: =IF($G59=0,0,IF(P$6<$G59,0,IF(P$6>$H59,1,(P$6-$G59+1)/($H59-$G59+1)))) -> 0 | ... BO59: =IF($G59=0,0,IF(BO$6<$G59,0,IF(BO$6>$H59,1,(BO$6-$G59+1)/($H59-$G59+1)))) -> 1
B60: 9.2.6 | C60: VACIADO DE CONCRETO (APLICACIÓN PUENTE DE ADHERENCIA) WP45 | D60: 1 día | E60: =VLOOKUP(B60,'Cuadro Control'!C60:J1990,8,FALSE) -> 1.4011493e+08 | F60: 0.15 | G60: 46301 | H60: 46302 | I60: =IF($G60=0,0,IF(I$6<$G60,0,IF(I$6>$H60,1,(I$6-$G60+1)/($H60-$G60+1)))) -> 0 | J60: =IF($G60=0,0,IF(J$6<$G60,0,IF(J$6>$H60,1,(J$6-$G60+1)/($H60-$G60+1)))) -> 0 | K60: =IF($G60=0,0,IF(K$6<$G60,0,IF(K$6>$H60,1,(K$6-$G60+1)/($H60-$G60+1)))) -> 0 | L60: =IF($G60=0,0,IF(L$6<$G60,0,IF(L$6>$H60,1,(L$6-$G60+1)/($H60-$G60+1)))) -> 0 | M60: =IF($G60=0,0,IF(M$6<$G60,0,IF(M$6>$H60,1,(M$6-$G60+1)/($H60-$G60+1)))) -> 0 | N60: =IF($G60=0,0,IF(N$6<$G60,0,IF(N$6>$H60,1,(N$6-$G60+1)/($H60-$G60+1)))) -> 0 | O60: =IF($G60=0,0,IF(O$6<$G60,0,IF(O$6>$H60,1,(O$6-$G60+1)/($H60-$G60+1)))) -> 0 | P60: =IF($G60=0,0,IF(P$6<$G60,0,IF(P$6>$H60,1,(P$6-$G60+1)/($H60-$G60+1)))) -> 0 | ... BO60: =IF($G60=0,0,IF(BO$6<$G60,0,IF(BO$6>$H60,1,(BO$6-$G60+1)/($H60-$G60+1)))) -> 1
B61: 9.2.7 | C61: ADECUACIONES E INSTALACIONES ELECTRICAS REQUERIDAS WP45 | D61: 3 días | E61: =VLOOKUP(B61,'Cuadro Control'!C62:J1991,8,FALSE) -> 52335716 | F61: 0.06 | G61: 46310 | H61: 46314 | I61: =IF($G61=0,0,IF(I$6<$G61,0,IF(I$6>$H61,1,(I$6-$G61+1)/($H61-$G61+1)))) -> 0 | J61: =IF($G61=0,0,IF(J$6<$G61,0,IF(J$6>$H61,1,(J$6-$G61+1)/($H61-$G61+1)))) -> 0 | K61: =IF($G61=0,0,IF(K$6<$G61,0,IF(K$6>$H61,1,(K$6-$G61+1)/($H61-$G61+1)))) -> 0 | L61: =IF($G61=0,0,IF(L$6<$G61,0,IF(L$6>$H61,1,(L$6-$G61+1)/($H61-$G61+1)))) -> 0 | M61: =IF($G61=0,0,IF(M$6<$G61,0,IF(M$6>$H61,1,(M$6-$G61+1)/($H61-$G61+1)))) -> 0 | N61: =IF($G61=0,0,IF(N$6<$G61,0,IF(N$6>$H61,1,(N$6-$G61+1)/($H61-$G61+1)))) -> 0 | O61: =IF($G61=0,0,IF(O$6<$G61,0,IF(O$6>$H61,1,(O$6-$G61+1)/($H61-$G61+1)))) -> 0 | P61: =IF($G61=0,0,IF(P$6<$G61,0,IF(P$6>$H61,1,(P$6-$G61+1)/($H61-$G61+1)))) -> 0 | ... BO61: =IF($G61=0,0,IF(BO$6<$G61,0,IF(BO$6>$H61,1,(BO$6-$G61+1)/($H61-$G61+1)))) -> 1
B62: 9.2.8 | C62: INSTALACION DE GROUT Y MORTERO AUTOCOMPACTANTE DE ALTA RESISTENCIA WP45 | D62: 2 días | E62: =VLOOKUP(B62,'Cuadro Control'!C64:J1992,8,FALSE) -> 46410609 | F62: 0.05 | G62: 46314 | H62: 46316 | I62: =IF($G62=0,0,IF(I$6<$G62,0,IF(I$6>$H62,1,(I$6-$G62+1)/($H62-$G62+1)))) -> 0 | J62: =IF($G62=0,0,IF(J$6<$G62,0,IF(J$6>$H62,1,(J$6-$G62+1)/($H62-$G62+1)))) -> 0 | K62: =IF($G62=0,0,IF(K$6<$G62,0,IF(K$6>$H62,1,(K$6-$G62+1)/($H62-$G62+1)))) -> 0 | L62: =IF($G62=0,0,IF(L$6<$G62,0,IF(L$6>$H62,1,(L$6-$G62+1)/($H62-$G62+1)))) -> 0 | M62: =IF($G62=0,0,IF(M$6<$G62,0,IF(M$6>$H62,1,(M$6-$G62+1)/($H62-$G62+1)))) -> 0 | N62: =IF($G62=0,0,IF(N$6<$G62,0,IF(N$6>$H62,1,(N$6-$G62+1)/($H62-$G62+1)))) -> 0 | O62: =IF($G62=0,0,IF(O$6<$G62,0,IF(O$6>$H62,1,(O$6-$G62+1)/($H62-$G62+1)))) -> 0 | P62: =IF($G62=0,0,IF(P$6<$G62,0,IF(P$6>$H62,1,(P$6-$G62+1)/($H62-$G62+1)))) -> 0 | ... BO62: =IF($G62=0,0,IF(BO$6<$G62,0,IF(BO$6>$H62,1,(BO$6-$G62+1)/($H62-$G62+1)))) -> 1
B63: 9.3 | C63: RECALCE 3 WP46 | D63: 53 días | E63: =SUM(E64:E71) -> 9.2295182e+08 | F63: =IFERROR(E63/$E$44,0) -> 0.14285714 | G63: 46260 | H63: 46319 | I63: =SUMPRODUCT($F64:$F71,I64:I71) -> 0 | J63: =SUMPRODUCT($F64:$F71,J64:J71) -> 0 | K63: =SUMPRODUCT($F64:$F71,K64:K71) -> 0 | L63: =SUMPRODUCT($F64:$F71,L64:L71) -> 0 | M63: =SUMPRODUCT($F64:$F71,M64:M71) -> 0 | N63: =SUMPRODUCT($F64:$F71,N64:N71) -> 0 | O63: =SUMPRODUCT($F64:$F71,O64:O71) -> 0 | P63: =SUMPRODUCT($F64:$F71,P64:P71) -> 0.14166667 | ... BO63: =SUMPRODUCT($F64:$F71,BO64:BO71) -> 1
B64: 9.3.1 | C64: LOCALIZACIÓN DEL ACERO WP46 | D64: 1 día | E64: =VLOOKUP(B64,'Cuadro Control'!C68:J1994,8,FALSE) -> 90662605 | F64: 0.1 | G64: 46260 | H64: 46262 | I64: =IF($G64=0,0,IF(I$6<$G64,0,IF(I$6>$H64,1,(I$6-$G64+1)/($H64-$G64+1)))) -> 0 | J64: =IF($G64=0,0,IF(J$6<$G64,0,IF(J$6>$H64,1,(J$6-$G64+1)/($H64-$G64+1)))) -> 0 | K64: =IF($G64=0,0,IF(K$6<$G64,0,IF(K$6>$H64,1,(K$6-$G64+1)/($H64-$G64+1)))) -> 0 | L64: =IF($G64=0,0,IF(L$6<$G64,0,IF(L$6>$H64,1,(L$6-$G64+1)/($H64-$G64+1)))) -> 0 | M64: =IF($G64=0,0,IF(M$6<$G64,0,IF(M$6>$H64,1,(M$6-$G64+1)/($H64-$G64+1)))) -> 0 | N64: =IF($G64=0,0,IF(N$6<$G64,0,IF(N$6>$H64,1,(N$6-$G64+1)/($H64-$G64+1)))) -> 0 | O64: =IF($G64=0,0,IF(O$6<$G64,0,IF(O$6>$H64,1,(O$6-$G64+1)/($H64-$G64+1)))) -> 0 | P64: =IF($G64=0,0,IF(P$6<$G64,0,IF(P$6>$H64,1,(P$6-$G64+1)/($H64-$G64+1)))) -> 1 | ... BO64: =IF($G64=0,0,IF(BO$6<$G64,0,IF(BO$6>$H64,1,(BO$6-$G64+1)/($H64-$G64+1)))) -> 1
B65: 9.3.2 | C65: ESCARIFICADO Y LIMPIEZA DEL RECUBRIMIENTO WP46 | D65: 4 días | E65: =VLOOKUP(B65,'Cuadro Control'!C70:J1995,8,FALSE) -> 2.3077754e+08 | F65: 0.25 | G65: 46262 | H65: 46267 | I65: =IF($G65=0,0,IF(I$6<$G65,0,IF(I$6>$H65,1,(I$6-$G65+1)/($H65-$G65+1)))) -> 0 | J65: =IF($G65=0,0,IF(J$6<$G65,0,IF(J$6>$H65,1,(J$6-$G65+1)/($H65-$G65+1)))) -> 0 | K65: =IF($G65=0,0,IF(K$6<$G65,0,IF(K$6>$H65,1,(K$6-$G65+1)/($H65-$G65+1)))) -> 0 | L65: =IF($G65=0,0,IF(L$6<$G65,0,IF(L$6>$H65,1,(L$6-$G65+1)/($H65-$G65+1)))) -> 0 | M65: =IF($G65=0,0,IF(M$6<$G65,0,IF(M$6>$H65,1,(M$6-$G65+1)/($H65-$G65+1)))) -> 0 | N65: =IF($G65=0,0,IF(N$6<$G65,0,IF(N$6>$H65,1,(N$6-$G65+1)/($H65-$G65+1)))) -> 0 | O65: =IF($G65=0,0,IF(O$6<$G65,0,IF(O$6>$H65,1,(O$6-$G65+1)/($H65-$G65+1)))) -> 0 | P65: =IF($G65=0,0,IF(P$6<$G65,0,IF(P$6>$H65,1,(P$6-$G65+1)/($H65-$G65+1)))) -> 0.16666667 | ... BO65: =IF($G65=0,0,IF(BO$6<$G65,0,IF(BO$6>$H65,1,(BO$6-$G65+1)/($H65-$G65+1)))) -> 1
B66: 9.3.3 | C66: CORTE Y FIGURADO DE ACERO WP46 | D66: 4 días | E66: =VLOOKUP(B66,'Cuadro Control'!C71:J1996,8,FALSE) -> 82420550 | F66: 0.09 | G66: 46267 | H66: 46272 | I66: =IF($G66=0,0,IF(I$6<$G66,0,IF(I$6>$H66,1,(I$6-$G66+1)/($H66-$G66+1)))) -> 0 | J66: =IF($G66=0,0,IF(J$6<$G66,0,IF(J$6>$H66,1,(J$6-$G66+1)/($H66-$G66+1)))) -> 0 | K66: =IF($G66=0,0,IF(K$6<$G66,0,IF(K$6>$H66,1,(K$6-$G66+1)/($H66-$G66+1)))) -> 0 | L66: =IF($G66=0,0,IF(L$6<$G66,0,IF(L$6>$H66,1,(L$6-$G66+1)/($H66-$G66+1)))) -> 0 | M66: =IF($G66=0,0,IF(M$6<$G66,0,IF(M$6>$H66,1,(M$6-$G66+1)/($H66-$G66+1)))) -> 0 | N66: =IF($G66=0,0,IF(N$6<$G66,0,IF(N$6>$H66,1,(N$6-$G66+1)/($H66-$G66+1)))) -> 0 | O66: =IF($G66=0,0,IF(O$6<$G66,0,IF(O$6>$H66,1,(O$6-$G66+1)/($H66-$G66+1)))) -> 0 | P66: =IF($G66=0,0,IF(P$6<$G66,0,IF(P$6>$H66,1,(P$6-$G66+1)/($H66-$G66+1)))) -> 0 | ... BO66: =IF($G66=0,0,IF(BO$6<$G66,0,IF(BO$6>$H66,1,(BO$6-$G66+1)/($H66-$G66+1)))) -> 1
B67: 9.3.4 | C67: APLICACIÓN DE EPOXICO Y FIJACIÓN DEL ACERO WP46 | D67: 4 días | E67: =VLOOKUP(B67,'Cuadro Control'!C72:J1997,8,FALSE) -> 2.3077754e+08 | F67: 0.25 | G67: 46303 | H67: 46308 | I67: =IF($G67=0,0,IF(I$6<$G67,0,IF(I$6>$H67,1,(I$6-$G67+1)/($H67-$G67+1)))) -> 0 | J67: =IF($G67=0,0,IF(J$6<$G67,0,IF(J$6>$H67,1,(J$6-$G67+1)/($H67-$G67+1)))) -> 0 | K67: =IF($G67=0,0,IF(K$6<$G67,0,IF(K$6>$H67,1,(K$6-$G67+1)/($H67-$G67+1)))) -> 0 | L67: =IF($G67=0,0,IF(L$6<$G67,0,IF(L$6>$H67,1,(L$6-$G67+1)/($H67-$G67+1)))) -> 0 | M67: =IF($G67=0,0,IF(M$6<$G67,0,IF(M$6>$H67,1,(M$6-$G67+1)/($H67-$G67+1)))) -> 0 | N67: =IF($G67=0,0,IF(N$6<$G67,0,IF(N$6>$H67,1,(N$6-$G67+1)/($H67-$G67+1)))) -> 0 | O67: =IF($G67=0,0,IF(O$6<$G67,0,IF(O$6>$H67,1,(O$6-$G67+1)/($H67-$G67+1)))) -> 0 | P67: =IF($G67=0,0,IF(P$6<$G67,0,IF(P$6>$H67,1,(P$6-$G67+1)/($H67-$G67+1)))) -> 0 | ... BO67: =IF($G67=0,0,IF(BO$6<$G67,0,IF(BO$6>$H67,1,(BO$6-$G67+1)/($H67-$G67+1)))) -> 1
B68: 9.3.5 | C68: ENCONFRADO WP46 | D68: 1 día | E68: =VLOOKUP(B68,'Cuadro Control'!C73:J1998,8,FALSE) -> 49452330 | F68: 0.05 | G68: 46309 | H68: 46309 | I68: =IF($G68=0,0,IF(I$6<$G68,0,IF(I$6>$H68,1,(I$6-$G68+1)/($H68-$G68+1)))) -> 0 | J68: =IF($G68=0,0,IF(J$6<$G68,0,IF(J$6>$H68,1,(J$6-$G68+1)/($H68-$G68+1)))) -> 0 | K68: =IF($G68=0,0,IF(K$6<$G68,0,IF(K$6>$H68,1,(K$6-$G68+1)/($H68-$G68+1)))) -> 0 | L68: =IF($G68=0,0,IF(L$6<$G68,0,IF(L$6>$H68,1,(L$6-$G68+1)/($H68-$G68+1)))) -> 0 | M68: =IF($G68=0,0,IF(M$6<$G68,0,IF(M$6>$H68,1,(M$6-$G68+1)/($H68-$G68+1)))) -> 0 | N68: =IF($G68=0,0,IF(N$6<$G68,0,IF(N$6>$H68,1,(N$6-$G68+1)/($H68-$G68+1)))) -> 0 | O68: =IF($G68=0,0,IF(O$6<$G68,0,IF(O$6>$H68,1,(O$6-$G68+1)/($H68-$G68+1)))) -> 0 | P68: =IF($G68=0,0,IF(P$6<$G68,0,IF(P$6>$H68,1,(P$6-$G68+1)/($H68-$G68+1)))) -> 0 | ... BO68: =IF($G68=0,0,IF(BO$6<$G68,0,IF(BO$6>$H68,1,(BO$6-$G68+1)/($H68-$G68+1)))) -> 1
B69: 9.3.6 | C69: VACIADO DE CONCRETO (APLICACIÓN PUENTE DE ADHERENCIA) WP46 | D69: 1 día | E69: =VLOOKUP(B69,'Cuadro Control'!C74:J1999,8,FALSE) -> 1.4011493e+08 | F69: 0.15 | G69: 46309 | H69: 46310 | I69: =IF($G69=0,0,IF(I$6<$G69,0,IF(I$6>$H69,1,(I$6-$G69+1)/($H69-$G69+1)))) -> 0 | J69: =IF($G69=0,0,IF(J$6<$G69,0,IF(J$6>$H69,1,(J$6-$G69+1)/($H69-$G69+1)))) -> 0 | K69: =IF($G69=0,0,IF(K$6<$G69,0,IF(K$6>$H69,1,(K$6-$G69+1)/($H69-$G69+1)))) -> 0 | L69: =IF($G69=0,0,IF(L$6<$G69,0,IF(L$6>$H69,1,(L$6-$G69+1)/($H69-$G69+1)))) -> 0 | M69: =IF($G69=0,0,IF(M$6<$G69,0,IF(M$6>$H69,1,(M$6-$G69+1)/($H69-$G69+1)))) -> 0 | N69: =IF($G69=0,0,IF(N$6<$G69,0,IF(N$6>$H69,1,(N$6-$G69+1)/($H69-$G69+1)))) -> 0 | O69: =IF($G69=0,0,IF(O$6<$G69,0,IF(O$6>$H69,1,(O$6-$G69+1)/($H69-$G69+1)))) -> 0 | P69: =IF($G69=0,0,IF(P$6<$G69,0,IF(P$6>$H69,1,(P$6-$G69+1)/($H69-$G69+1)))) -> 0 | ... BO69: =IF($G69=0,0,IF(BO$6<$G69,0,IF(BO$6>$H69,1,(BO$6-$G69+1)/($H69-$G69+1)))) -> 1
B70: 9.3.7 | C70: ADECUACIONES E INSTALACIONES ELECTRICAS REQUERIDAS WP46 | D70: 3 días | E70: =VLOOKUP(B70,'Cuadro Control'!C75:J2000,8,FALSE) -> 52335716 | F70: 0.06 | G70: 46314 | H70: 46317 | I70: =IF($G70=0,0,IF(I$6<$G70,0,IF(I$6>$H70,1,(I$6-$G70+1)/($H70-$G70+1)))) -> 0 | J70: =IF($G70=0,0,IF(J$6<$G70,0,IF(J$6>$H70,1,(J$6-$G70+1)/($H70-$G70+1)))) -> 0 | K70: =IF($G70=0,0,IF(K$6<$G70,0,IF(K$6>$H70,1,(K$6-$G70+1)/($H70-$G70+1)))) -> 0 | L70: =IF($G70=0,0,IF(L$6<$G70,0,IF(L$6>$H70,1,(L$6-$G70+1)/($H70-$G70+1)))) -> 0 | M70: =IF($G70=0,0,IF(M$6<$G70,0,IF(M$6>$H70,1,(M$6-$G70+1)/($H70-$G70+1)))) -> 0 | N70: =IF($G70=0,0,IF(N$6<$G70,0,IF(N$6>$H70,1,(N$6-$G70+1)/($H70-$G70+1)))) -> 0 | O70: =IF($G70=0,0,IF(O$6<$G70,0,IF(O$6>$H70,1,(O$6-$G70+1)/($H70-$G70+1)))) -> 0 | P70: =IF($G70=0,0,IF(P$6<$G70,0,IF(P$6>$H70,1,(P$6-$G70+1)/($H70-$G70+1)))) -> 0 | ... BO70: =IF($G70=0,0,IF(BO$6<$G70,0,IF(BO$6>$H70,1,(BO$6-$G70+1)/($H70-$G70+1)))) -> 1
B71: 9.3.8 | C71: INSTALACION DE GROUT Y MORTERO AUTOCOMPACTANTE DE ALTA RESISTENCIA WP46 | D71: 2 días | E71: =VLOOKUP(B71,'Cuadro Control'!C76:J2001,8,FALSE) -> 46410609 | F71: 0.05 | G71: 46318 | H71: 46319 | I71: =IF($G71=0,0,IF(I$6<$G71,0,IF(I$6>$H71,1,(I$6-$G71+1)/($H71-$G71+1)))) -> 0 | J71: =IF($G71=0,0,IF(J$6<$G71,0,IF(J$6>$H71,1,(J$6-$G71+1)/($H71-$G71+1)))) -> 0 | K71: =IF($G71=0,0,IF(K$6<$G71,0,IF(K$6>$H71,1,(K$6-$G71+1)/($H71-$G71+1)))) -> 0 | L71: =IF($G71=0,0,IF(L$6<$G71,0,IF(L$6>$H71,1,(L$6-$G71+1)/($H71-$G71+1)))) -> 0 | M71: =IF($G71=0,0,IF(M$6<$G71,0,IF(M$6>$H71,1,(M$6-$G71+1)/($H71-$G71+1)))) -> 0 | N71: =IF($G71=0,0,IF(N$6<$G71,0,IF(N$6>$H71,1,(N$6-$G71+1)/($H71-$G71+1)))) -> 0 | O71: =IF($G71=0,0,IF(O$6<$G71,0,IF(O$6>$H71,1,(O$6-$G71+1)/($H71-$G71+1)))) -> 0 | P71: =IF($G71=0,0,IF(P$6<$G71,0,IF(P$6>$H71,1,(P$6-$G71+1)/($H71-$G71+1)))) -> 0 | ... BO71: =IF($G71=0,0,IF(BO$6<$G71,0,IF(BO$6>$H71,1,(BO$6-$G71+1)/($H71-$G71+1)))) -> 1
B72: 9.4 | C72: RECALCE 4 WP47 | D72: 53 días | E72: =SUM(E73:E80) -> 9.2295182e+08 | F72: =IFERROR(E72/$E$44,0) -> 0.14285714 | G72: 46267 | H72: 46329 | I72: =SUMPRODUCT($F73:$F80,I73:I80) -> 0 | J72: =SUMPRODUCT($F73:$F80,J73:J80) -> 0 | K72: =SUMPRODUCT($F73:$F80,K73:K80) -> 0 | L72: =SUMPRODUCT($F73:$F80,L73:L80) -> 0 | M72: =SUMPRODUCT($F73:$F80,M73:M80) -> 0 | N72: =SUMPRODUCT($F73:$F80,N73:N80) -> 0 | O72: =SUMPRODUCT($F73:$F80,O73:O80) -> 0 | P72: =SUMPRODUCT($F73:$F80,P73:P80) -> 0 | ... BO72: =SUMPRODUCT($F73:$F80,BO73:BO80) -> 1
B73: 9.4.1 | C73: LOCALIZACIÓN DEL ACERO WP47 | D73: 1 día | E73: =VLOOKUP(B73,'Cuadro Control'!C78:J2003,8,FALSE) -> 90662605 | F73: 0.1 | G73: 46267 | H73: 46269 | I73: =IF($G73=0,0,IF(I$6<$G73,0,IF(I$6>$H73,1,(I$6-$G73+1)/($H73-$G73+1)))) -> 0 | J73: =IF($G73=0,0,IF(J$6<$G73,0,IF(J$6>$H73,1,(J$6-$G73+1)/($H73-$G73+1)))) -> 0 | K73: =IF($G73=0,0,IF(K$6<$G73,0,IF(K$6>$H73,1,(K$6-$G73+1)/($H73-$G73+1)))) -> 0 | L73: =IF($G73=0,0,IF(L$6<$G73,0,IF(L$6>$H73,1,(L$6-$G73+1)/($H73-$G73+1)))) -> 0 | M73: =IF($G73=0,0,IF(M$6<$G73,0,IF(M$6>$H73,1,(M$6-$G73+1)/($H73-$G73+1)))) -> 0 | N73: =IF($G73=0,0,IF(N$6<$G73,0,IF(N$6>$H73,1,(N$6-$G73+1)/($H73-$G73+1)))) -> 0 | O73: =IF($G73=0,0,IF(O$6<$G73,0,IF(O$6>$H73,1,(O$6-$G73+1)/($H73-$G73+1)))) -> 0 | P73: =IF($G73=0,0,IF(P$6<$G73,0,IF(P$6>$H73,1,(P$6-$G73+1)/($H73-$G73+1)))) -> 0 | ... BO73: =IF($G73=0,0,IF(BO$6<$G73,0,IF(BO$6>$H73,1,(BO$6-$G73+1)/($H73-$G73+1)))) -> 1
B74: 9.4.2 | C74: ESCARIFICADO Y LIMPIEZA DEL RECUBRIMIENTO WP47 | D74: 4 días | E74: =VLOOKUP(B74,'Cuadro Control'!C79:J2004,8,FALSE) -> 2.3077754e+08 | F74: 0.25 | G74: 46269 | H74: 46274 | I74: =IF($G74=0,0,IF(I$6<$G74,0,IF(I$6>$H74,1,(I$6-$G74+1)/($H74-$G74+1)))) -> 0 | J74: =IF($G74=0,0,IF(J$6<$G74,0,IF(J$6>$H74,1,(J$6-$G74+1)/($H74-$G74+1)))) -> 0 | K74: =IF($G74=0,0,IF(K$6<$G74,0,IF(K$6>$H74,1,(K$6-$G74+1)/($H74-$G74+1)))) -> 0 | L74: =IF($G74=0,0,IF(L$6<$G74,0,IF(L$6>$H74,1,(L$6-$G74+1)/($H74-$G74+1)))) -> 0 | M74: =IF($G74=0,0,IF(M$6<$G74,0,IF(M$6>$H74,1,(M$6-$G74+1)/($H74-$G74+1)))) -> 0 | N74: =IF($G74=0,0,IF(N$6<$G74,0,IF(N$6>$H74,1,(N$6-$G74+1)/($H74-$G74+1)))) -> 0 | O74: =IF($G74=0,0,IF(O$6<$G74,0,IF(O$6>$H74,1,(O$6-$G74+1)/($H74-$G74+1)))) -> 0 | P74: =IF($G74=0,0,IF(P$6<$G74,0,IF(P$6>$H74,1,(P$6-$G74+1)/($H74-$G74+1)))) -> 0 | ... BO74: =IF($G74=0,0,IF(BO$6<$G74,0,IF(BO$6>$H74,1,(BO$6-$G74+1)/($H74-$G74+1)))) -> 1
B75: 9.4.3 | C75: CORTE Y FIGURADO DE ACERO WP47 | D75: 4 días | E75: =VLOOKUP(B75,'Cuadro Control'!C80:J2005,8,FALSE) -> 82420550 | F75: 0.09 | G75: 46275 | H75: 46279 | I75: =IF($G75=0,0,IF(I$6<$G75,0,IF(I$6>$H75,1,(I$6-$G75+1)/($H75-$G75+1)))) -> 0 | J75: =IF($G75=0,0,IF(J$6<$G75,0,IF(J$6>$H75,1,(J$6-$G75+1)/($H75-$G75+1)))) -> 0 | K75: =IF($G75=0,0,IF(K$6<$G75,0,IF(K$6>$H75,1,(K$6-$G75+1)/($H75-$G75+1)))) -> 0 | L75: =IF($G75=0,0,IF(L$6<$G75,0,IF(L$6>$H75,1,(L$6-$G75+1)/($H75-$G75+1)))) -> 0 | M75: =IF($G75=0,0,IF(M$6<$G75,0,IF(M$6>$H75,1,(M$6-$G75+1)/($H75-$G75+1)))) -> 0 | N75: =IF($G75=0,0,IF(N$6<$G75,0,IF(N$6>$H75,1,(N$6-$G75+1)/($H75-$G75+1)))) -> 0 | O75: =IF($G75=0,0,IF(O$6<$G75,0,IF(O$6>$H75,1,(O$6-$G75+1)/($H75-$G75+1)))) -> 0 | P75: =IF($G75=0,0,IF(P$6<$G75,0,IF(P$6>$H75,1,(P$6-$G75+1)/($H75-$G75+1)))) -> 0 | ... BO75: =IF($G75=0,0,IF(BO$6<$G75,0,IF(BO$6>$H75,1,(BO$6-$G75+1)/($H75-$G75+1)))) -> 1
B76: 9.4.4 | C76: APLICACIÓN DE EPOXICO Y FIJACIÓN DEL ACERO WP47 | D76: 4 días | E76: =VLOOKUP(B76,'Cuadro Control'!C81:J2006,8,FALSE) -> 2.3077754e+08 | F76: 0.25 | G76: 46311 | H76: 46316 | I76: =IF($G76=0,0,IF(I$6<$G76,0,IF(I$6>$H76,1,(I$6-$G76+1)/($H76-$G76+1)))) -> 0 | J76: =IF($G76=0,0,IF(J$6<$G76,0,IF(J$6>$H76,1,(J$6-$G76+1)/($H76-$G76+1)))) -> 0 | K76: =IF($G76=0,0,IF(K$6<$G76,0,IF(K$6>$H76,1,(K$6-$G76+1)/($H76-$G76+1)))) -> 0 | L76: =IF($G76=0,0,IF(L$6<$G76,0,IF(L$6>$H76,1,(L$6-$G76+1)/($H76-$G76+1)))) -> 0 | M76: =IF($G76=0,0,IF(M$6<$G76,0,IF(M$6>$H76,1,(M$6-$G76+1)/($H76-$G76+1)))) -> 0 | N76: =IF($G76=0,0,IF(N$6<$G76,0,IF(N$6>$H76,1,(N$6-$G76+1)/($H76-$G76+1)))) -> 0 | O76: =IF($G76=0,0,IF(O$6<$G76,0,IF(O$6>$H76,1,(O$6-$G76+1)/($H76-$G76+1)))) -> 0 | P76: =IF($G76=0,0,IF(P$6<$G76,0,IF(P$6>$H76,1,(P$6-$G76+1)/($H76-$G76+1)))) -> 0 | ... BO76: =IF($G76=0,0,IF(BO$6<$G76,0,IF(BO$6>$H76,1,(BO$6-$G76+1)/($H76-$G76+1)))) -> 1
B77: 9.4.5 | C77: ENCONFRADO WP47 | D77: 1 día | E77: =VLOOKUP(B77,'Cuadro Control'!C82:J2007,8,FALSE) -> 49452330 | F77: 0.05 | G77: 46316 | H77: 46317 | I77: =IF($G77=0,0,IF(I$6<$G77,0,IF(I$6>$H77,1,(I$6-$G77+1)/($H77-$G77+1)))) -> 0 | J77: =IF($G77=0,0,IF(J$6<$G77,0,IF(J$6>$H77,1,(J$6-$G77+1)/($H77-$G77+1)))) -> 0 | K77: =IF($G77=0,0,IF(K$6<$G77,0,IF(K$6>$H77,1,(K$6-$G77+1)/($H77-$G77+1)))) -> 0 | L77: =IF($G77=0,0,IF(L$6<$G77,0,IF(L$6>$H77,1,(L$6-$G77+1)/($H77-$G77+1)))) -> 0 | M77: =IF($G77=0,0,IF(M$6<$G77,0,IF(M$6>$H77,1,(M$6-$G77+1)/($H77-$G77+1)))) -> 0 | N77: =IF($G77=0,0,IF(N$6<$G77,0,IF(N$6>$H77,1,(N$6-$G77+1)/($H77-$G77+1)))) -> 0 | O77: =IF($G77=0,0,IF(O$6<$G77,0,IF(O$6>$H77,1,(O$6-$G77+1)/($H77-$G77+1)))) -> 0 | P77: =IF($G77=0,0,IF(P$6<$G77,0,IF(P$6>$H77,1,(P$6-$G77+1)/($H77-$G77+1)))) -> 0 | ... BO77: =IF($G77=0,0,IF(BO$6<$G77,0,IF(BO$6>$H77,1,(BO$6-$G77+1)/($H77-$G77+1)))) -> 1
B78: 9.4.6 | C78: VACIADO DE CONCRETO (APLICACIÓN PUENTE DE ADHERENCIA) WP47 | D78: 1 día | E78: =VLOOKUP(B78,'Cuadro Control'!C83:J2008,8,FALSE) -> 1.4011493e+08 | F78: 0.15 | G78: 46317 | H78: 46318 | I78: =IF($G78=0,0,IF(I$6<$G78,0,IF(I$6>$H78,1,(I$6-$G78+1)/($H78-$G78+1)))) -> 0 | J78: =IF($G78=0,0,IF(J$6<$G78,0,IF(J$6>$H78,1,(J$6-$G78+1)/($H78-$G78+1)))) -> 0 | K78: =IF($G78=0,0,IF(K$6<$G78,0,IF(K$6>$H78,1,(K$6-$G78+1)/($H78-$G78+1)))) -> 0 | L78: =IF($G78=0,0,IF(L$6<$G78,0,IF(L$6>$H78,1,(L$6-$G78+1)/($H78-$G78+1)))) -> 0 | M78: =IF($G78=0,0,IF(M$6<$G78,0,IF(M$6>$H78,1,(M$6-$G78+1)/($H78-$G78+1)))) -> 0 | N78: =IF($G78=0,0,IF(N$6<$G78,0,IF(N$6>$H78,1,(N$6-$G78+1)/($H78-$G78+1)))) -> 0 | O78: =IF($G78=0,0,IF(O$6<$G78,0,IF(O$6>$H78,1,(O$6-$G78+1)/($H78-$G78+1)))) -> 0 | P78: =IF($G78=0,0,IF(P$6<$G78,0,IF(P$6>$H78,1,(P$6-$G78+1)/($H78-$G78+1)))) -> 0 | ... BO78: =IF($G78=0,0,IF(BO$6<$G78,0,IF(BO$6>$H78,1,(BO$6-$G78+1)/($H78-$G78+1)))) -> 1
B79: 9.4.7 | C79: ADECUACIONES E INSTALACIONES ELECTRICAS REQUERIDAS WP47 | D79: 3 días | E79: =VLOOKUP(B79,'Cuadro Control'!C84:J2009,8,FALSE) -> 52335716 | F79: 0.06 | G79: 46318 | H79: 46321 | I79: =IF($G79=0,0,IF(I$6<$G79,0,IF(I$6>$H79,1,(I$6-$G79+1)/($H79-$G79+1)))) -> 0 | J79: =IF($G79=0,0,IF(J$6<$G79,0,IF(J$6>$H79,1,(J$6-$G79+1)/($H79-$G79+1)))) -> 0 | K79: =IF($G79=0,0,IF(K$6<$G79,0,IF(K$6>$H79,1,(K$6-$G79+1)/($H79-$G79+1)))) -> 0 | L79: =IF($G79=0,0,IF(L$6<$G79,0,IF(L$6>$H79,1,(L$6-$G79+1)/($H79-$G79+1)))) -> 0 | M79: =IF($G79=0,0,IF(M$6<$G79,0,IF(M$6>$H79,1,(M$6-$G79+1)/($H79-$G79+1)))) -> 0 | N79: =IF($G79=0,0,IF(N$6<$G79,0,IF(N$6>$H79,1,(N$6-$G79+1)/($H79-$G79+1)))) -> 0 | O79: =IF($G79=0,0,IF(O$6<$G79,0,IF(O$6>$H79,1,(O$6-$G79+1)/($H79-$G79+1)))) -> 0 | P79: =IF($G79=0,0,IF(P$6<$G79,0,IF(P$6>$H79,1,(P$6-$G79+1)/($H79-$G79+1)))) -> 0 | ... BO79: =IF($G79=0,0,IF(BO$6<$G79,0,IF(BO$6>$H79,1,(BO$6-$G79+1)/($H79-$G79+1)))) -> 1
B80: 9.4.8 | C80: INSTALACION DE GROUT Y MORTERO AUTOCOMPACTANTE DE ALTA RESISTENCIA WP47 | D80: 2 días | E80: =VLOOKUP(B80,'Cuadro Control'!C86:J2010,8,FALSE) -> 46410609 | F80: 0.05 | G80: 46325 | H80: 46329 | I80: =IF($G80=0,0,IF(I$6<$G80,0,IF(I$6>$H80,1,(I$6-$G80+1)/($H80-$G80+1)))) -> 0 | J80: =IF($G80=0,0,IF(J$6<$G80,0,IF(J$6>$H80,1,(J$6-$G80+1)/($H80-$G80+1)))) -> 0 | K80: =IF($G80=0,0,IF(K$6<$G80,0,IF(K$6>$H80,1,(K$6-$G80+1)/($H80-$G80+1)))) -> 0 | L80: =IF($G80=0,0,IF(L$6<$G80,0,IF(L$6>$H80,1,(L$6-$G80+1)/($H80-$G80+1)))) -> 0 | M80: =IF($G80=0,0,IF(M$6<$G80,0,IF(M$6>$H80,1,(M$6-$G80+1)/($H80-$G80+1)))) -> 0 | N80: =IF($G80=0,0,IF(N$6<$G80,0,IF(N$6>$H80,1,(N$6-$G80+1)/($H80-$G80+1)))) -> 0 | O80: =IF($G80=0,0,IF(O$6<$G80,0,IF(O$6>$H80,1,(O$6-$G80+1)/($H80-$G80+1)))) -> 0 | P80: =IF($G80=0,0,IF(P$6<$G80,0,IF(P$6>$H80,1,(P$6-$G80+1)/($H80-$G80+1)))) -> 0 | ... BO80: =IF($G80=0,0,IF(BO$6<$G80,0,IF(BO$6>$H80,1,(BO$6-$G80+1)/($H80-$G80+1)))) -> 1
B81: 9.5 | C81: RECALCE 5 WP48 | D81: 53 días | E81: =SUM(E82:E89) -> 9.2295182e+08 | F81: =IFERROR(E81/$E$44,0) -> 0.14285714 | G81: 46275 | H81: 46336 | I81: =SUMPRODUCT($F82:$F89,I82:I89) -> 0 | J81: =SUMPRODUCT($F82:$F89,J82:J89) -> 0 | K81: =SUMPRODUCT($F82:$F89,K82:K89) -> 0 | L81: =SUMPRODUCT($F82:$F89,L82:L89) -> 0 | M81: =SUMPRODUCT($F82:$F89,M82:M89) -> 0 | N81: =SUMPRODUCT($F82:$F89,N82:N89) -> 0 | O81: =SUMPRODUCT($F82:$F89,O82:O89) -> 0 | P81: =SUMPRODUCT($F82:$F89,P82:P89) -> 0 | ... BO81: =SUMPRODUCT($F82:$F89,BO82:BO89) -> 1
B82: 9.5.1 | C82: LOCALIZACIÓN DEL ACERO WP48 | D82: 1 día | E82: =VLOOKUP(B82,'Cuadro Control'!C90:J2012,8,FALSE) -> 90662605 | F82: 0.1 | G82: 46275 | H82: 46276 | I82: =IF($G82=0,0,IF(I$6<$G82,0,IF(I$6>$H82,1,(I$6-$G82+1)/($H82-$G82+1)))) -> 0 | J82: =IF($G82=0,0,IF(J$6<$G82,0,IF(J$6>$H82,1,(J$6-$G82+1)/($H82-$G82+1)))) -> 0 | K82: =IF($G82=0,0,IF(K$6<$G82,0,IF(K$6>$H82,1,(K$6-$G82+1)/($H82-$G82+1)))) -> 0 | L82: =IF($G82=0,0,IF(L$6<$G82,0,IF(L$6>$H82,1,(L$6-$G82+1)/($H82-$G82+1)))) -> 0 | M82: =IF($G82=0,0,IF(M$6<$G82,0,IF(M$6>$H82,1,(M$6-$G82+1)/($H82-$G82+1)))) -> 0 | N82: =IF($G82=0,0,IF(N$6<$G82,0,IF(N$6>$H82,1,(N$6-$G82+1)/($H82-$G82+1)))) -> 0 | O82: =IF($G82=0,0,IF(O$6<$G82,0,IF(O$6>$H82,1,(O$6-$G82+1)/($H82-$G82+1)))) -> 0 | P82: =IF($G82=0,0,IF(P$6<$G82,0,IF(P$6>$H82,1,(P$6-$G82+1)/($H82-$G82+1)))) -> 0 | ... BO82: =IF($G82=0,0,IF(BO$6<$G82,0,IF(BO$6>$H82,1,(BO$6-$G82+1)/($H82-$G82+1)))) -> 1
B83: 9.5.2 | C83: ESCARIFICADO Y LIMPIEZA DEL RECUBRIMIENTO WP48 | D83: 4 días | E83: =VLOOKUP(B83,'Cuadro Control'!C92:J2013,8,FALSE) -> 2.3077754e+08 | F83: 0.25 | G83: 46276 | H83: 46282 | I83: =IF($G83=0,0,IF(I$6<$G83,0,IF(I$6>$H83,1,(I$6-$G83+1)/($H83-$G83+1)))) -> 0 | J83: =IF($G83=0,0,IF(J$6<$G83,0,IF(J$6>$H83,1,(J$6-$G83+1)/($H83-$G83+1)))) -> 0 | K83: =IF($G83=0,0,IF(K$6<$G83,0,IF(K$6>$H83,1,(K$6-$G83+1)/($H83-$G83+1)))) -> 0 | L83: =IF($G83=0,0,IF(L$6<$G83,0,IF(L$6>$H83,1,(L$6-$G83+1)/($H83-$G83+1)))) -> 0 | M83: =IF($G83=0,0,IF(M$6<$G83,0,IF(M$6>$H83,1,(M$6-$G83+1)/($H83-$G83+1)))) -> 0 | N83: =IF($G83=0,0,IF(N$6<$G83,0,IF(N$6>$H83,1,(N$6-$G83+1)/($H83-$G83+1)))) -> 0 | O83: =IF($G83=0,0,IF(O$6<$G83,0,IF(O$6>$H83,1,(O$6-$G83+1)/($H83-$G83+1)))) -> 0 | P83: =IF($G83=0,0,IF(P$6<$G83,0,IF(P$6>$H83,1,(P$6-$G83+1)/($H83-$G83+1)))) -> 0 | ... BO83: =IF($G83=0,0,IF(BO$6<$G83,0,IF(BO$6>$H83,1,(BO$6-$G83+1)/($H83-$G83+1)))) -> 1
B84: 9.5.3 | C84: CORTE Y FIGURADO DE ACERO WP48 | D84: 4 días | E84: =VLOOKUP(B84,'Cuadro Control'!C94:J2014,8,FALSE) -> 82420550 | F84: 0.09 | G84: 46282 | H84: 46286 | I84: =IF($G84=0,0,IF(I$6<$G84,0,IF(I$6>$H84,1,(I$6-$G84+1)/($H84-$G84+1)))) -> 0 | J84: =IF($G84=0,0,IF(J$6<$G84,0,IF(J$6>$H84,1,(J$6-$G84+1)/($H84-$G84+1)))) -> 0 | K84: =IF($G84=0,0,IF(K$6<$G84,0,IF(K$6>$H84,1,(K$6-$G84+1)/($H84-$G84+1)))) -> 0 | L84: =IF($G84=0,0,IF(L$6<$G84,0,IF(L$6>$H84,1,(L$6-$G84+1)/($H84-$G84+1)))) -> 0 | M84: =IF($G84=0,0,IF(M$6<$G84,0,IF(M$6>$H84,1,(M$6-$G84+1)/($H84-$G84+1)))) -> 0 | N84: =IF($G84=0,0,IF(N$6<$G84,0,IF(N$6>$H84,1,(N$6-$G84+1)/($H84-$G84+1)))) -> 0 | O84: =IF($G84=0,0,IF(O$6<$G84,0,IF(O$6>$H84,1,(O$6-$G84+1)/($H84-$G84+1)))) -> 0 | P84: =IF($G84=0,0,IF(P$6<$G84,0,IF(P$6>$H84,1,(P$6-$G84+1)/($H84-$G84+1)))) -> 0 | ... BO84: =IF($G84=0,0,IF(BO$6<$G84,0,IF(BO$6>$H84,1,(BO$6-$G84+1)/($H84-$G84+1)))) -> 1
B85: 9.5.4 | C85: APLICACIÓN DE EPOXICO Y FIJACIÓN DEL ACERO WP48 | D85: 4 días | E85: =VLOOKUP(B85,'Cuadro Control'!C95:J2015,8,FALSE) -> 2.3077754e+08 | F85: 0.25 | G85: 46319 | H85: 46323 | I85: =IF($G85=0,0,IF(I$6<$G85,0,IF(I$6>$H85,1,(I$6-$G85+1)/($H85-$G85+1)))) -> 0 | J85: =IF($G85=0,0,IF(J$6<$G85,0,IF(J$6>$H85,1,(J$6-$G85+1)/($H85-$G85+1)))) -> 0 | K85: =IF($G85=0,0,IF(K$6<$G85,0,IF(K$6>$H85,1,(K$6-$G85+1)/($H85-$G85+1)))) -> 0 | L85: =IF($G85=0,0,IF(L$6<$G85,0,IF(L$6>$H85,1,(L$6-$G85+1)/($H85-$G85+1)))) -> 0 | M85: =IF($G85=0,0,IF(M$6<$G85,0,IF(M$6>$H85,1,(M$6-$G85+1)/($H85-$G85+1)))) -> 0 | N85: =IF($G85=0,0,IF(N$6<$G85,0,IF(N$6>$H85,1,(N$6-$G85+1)/($H85-$G85+1)))) -> 0 | O85: =IF($G85=0,0,IF(O$6<$G85,0,IF(O$6>$H85,1,(O$6-$G85+1)/($H85-$G85+1)))) -> 0 | P85: =IF($G85=0,0,IF(P$6<$G85,0,IF(P$6>$H85,1,(P$6-$G85+1)/($H85-$G85+1)))) -> 0 | ... BO85: =IF($G85=0,0,IF(BO$6<$G85,0,IF(BO$6>$H85,1,(BO$6-$G85+1)/($H85-$G85+1)))) -> 1
B86: 9.5.5 | C86: ENCONFRADO WP48 | D86: 1 día | E86: =VLOOKUP(B86,'Cuadro Control'!C96:J2016,8,FALSE) -> 49452330 | F86: 0.05 | G86: 46323 | H86: 46324 | I86: =IF($G86=0,0,IF(I$6<$G86,0,IF(I$6>$H86,1,(I$6-$G86+1)/($H86-$G86+1)))) -> 0 | J86: =IF($G86=0,0,IF(J$6<$G86,0,IF(J$6>$H86,1,(J$6-$G86+1)/($H86-$G86+1)))) -> 0 | K86: =IF($G86=0,0,IF(K$6<$G86,0,IF(K$6>$H86,1,(K$6-$G86+1)/($H86-$G86+1)))) -> 0 | L86: =IF($G86=0,0,IF(L$6<$G86,0,IF(L$6>$H86,1,(L$6-$G86+1)/($H86-$G86+1)))) -> 0 | M86: =IF($G86=0,0,IF(M$6<$G86,0,IF(M$6>$H86,1,(M$6-$G86+1)/($H86-$G86+1)))) -> 0 | N86: =IF($G86=0,0,IF(N$6<$G86,0,IF(N$6>$H86,1,(N$6-$G86+1)/($H86-$G86+1)))) -> 0 | O86: =IF($G86=0,0,IF(O$6<$G86,0,IF(O$6>$H86,1,(O$6-$G86+1)/($H86-$G86+1)))) -> 0 | P86: =IF($G86=0,0,IF(P$6<$G86,0,IF(P$6>$H86,1,(P$6-$G86+1)/($H86-$G86+1)))) -> 0 | ... BO86: =IF($G86=0,0,IF(BO$6<$G86,0,IF(BO$6>$H86,1,(BO$6-$G86+1)/($H86-$G86+1)))) -> 1
B87: 9.5.6 | C87: VACIADO DE CONCRETO (APLICACIÓN PUENTE DE ADHERENCIA) WP48 | D87: 1 día | E87: =VLOOKUP(B87,'Cuadro Control'!C97:J2017,8,FALSE) -> 1.4011493e+08 | F87: 0.15 | G87: 46324 | H87: 46325 | I87: =IF($G87=0,0,IF(I$6<$G87,0,IF(I$6>$H87,1,(I$6-$G87+1)/($H87-$G87+1)))) -> 0 | J87: =IF($G87=0,0,IF(J$6<$G87,0,IF(J$6>$H87,1,(J$6-$G87+1)/($H87-$G87+1)))) -> 0 | K87: =IF($G87=0,0,IF(K$6<$G87,0,IF(K$6>$H87,1,(K$6-$G87+1)/($H87-$G87+1)))) -> 0 | L87: =IF($G87=0,0,IF(L$6<$G87,0,IF(L$6>$H87,1,(L$6-$G87+1)/($H87-$G87+1)))) -> 0 | M87: =IF($G87=0,0,IF(M$6<$G87,0,IF(M$6>$H87,1,(M$6-$G87+1)/($H87-$G87+1)))) -> 0 | N87: =IF($G87=0,0,IF(N$6<$G87,0,IF(N$6>$H87,1,(N$6-$G87+1)/($H87-$G87+1)))) -> 0 | O87: =IF($G87=0,0,IF(O$6<$G87,0,IF(O$6>$H87,1,(O$6-$G87+1)/($H87-$G87+1)))) -> 0 | P87: =IF($G87=0,0,IF(P$6<$G87,0,IF(P$6>$H87,1,(P$6-$G87+1)/($H87-$G87+1)))) -> 0 | ... BO87: =IF($G87=0,0,IF(BO$6<$G87,0,IF(BO$6>$H87,1,(BO$6-$G87+1)/($H87-$G87+1)))) -> 1
B88: 9.5.7 | C88: ADECUACIONES E INSTALACIONES ELECTRICAS REQUERIDAS WP48 | D88: 3 días | E88: =VLOOKUP(B88,'Cuadro Control'!C98:J2018,8,FALSE) -> 52335716 | F88: 0.06 | G88: 46325 | H88: 46330 | I88: =IF($G88=0,0,IF(I$6<$G88,0,IF(I$6>$H88,1,(I$6-$G88+1)/($H88-$G88+1)))) -> 0 | J88: =IF($G88=0,0,IF(J$6<$G88,0,IF(J$6>$H88,1,(J$6-$G88+1)/($H88-$G88+1)))) -> 0 | K88: =IF($G88=0,0,IF(K$6<$G88,0,IF(K$6>$H88,1,(K$6-$G88+1)/($H88-$G88+1)))) -> 0 | L88: =IF($G88=0,0,IF(L$6<$G88,0,IF(L$6>$H88,1,(L$6-$G88+1)/($H88-$G88+1)))) -> 0 | M88: =IF($G88=0,0,IF(M$6<$G88,0,IF(M$6>$H88,1,(M$6-$G88+1)/($H88-$G88+1)))) -> 0 | N88: =IF($G88=0,0,IF(N$6<$G88,0,IF(N$6>$H88,1,(N$6-$G88+1)/($H88-$G88+1)))) -> 0 | O88: =IF($G88=0,0,IF(O$6<$G88,0,IF(O$6>$H88,1,(O$6-$G88+1)/($H88-$G88+1)))) -> 0 | P88: =IF($G88=0,0,IF(P$6<$G88,0,IF(P$6>$H88,1,(P$6-$G88+1)/($H88-$G88+1)))) -> 0 | ... BO88: =IF($G88=0,0,IF(BO$6<$G88,0,IF(BO$6>$H88,1,(BO$6-$G88+1)/($H88-$G88+1)))) -> 1
B89: 9.5.8 | C89: INSTALACION DE GROUT Y MORTERO AUTOCOMPACTANTE DE ALTA RESISTENCIA WP48 | D89: 2 días | E89: =VLOOKUP(B89,'Cuadro Control'!C99:J2019,8,FALSE) -> 46410609 | F89: 0.05 | G89: 46333 | H89: 46336 | I89: =IF($G89=0,0,IF(I$6<$G89,0,IF(I$6>$H89,1,(I$6-$G89+1)/($H89-$G89+1)))) -> 0 | J89: =IF($G89=0,0,IF(J$6<$G89,0,IF(J$6>$H89,1,(J$6-$G89+1)/($H89-$G89+1)))) -> 0 | K89: =IF($G89=0,0,IF(K$6<$G89,0,IF(K$6>$H89,1,(K$6-$G89+1)/($H89-$G89+1)))) -> 0 | L89: =IF($G89=0,0,IF(L$6<$G89,0,IF(L$6>$H89,1,(L$6-$G89+1)/($H89-$G89+1)))) -> 0 | M89: =IF($G89=0,0,IF(M$6<$G89,0,IF(M$6>$H89,1,(M$6-$G89+1)/($H89-$G89+1)))) -> 0 | N89: =IF($G89=0,0,IF(N$6<$G89,0,IF(N$6>$H89,1,(N$6-$G89+1)/($H89-$G89+1)))) -> 0 | O89: =IF($G89=0,0,IF(O$6<$G89,0,IF(O$6>$H89,1,(O$6-$G89+1)/($H89-$G89+1)))) -> 0 | P89: =IF($G89=0,0,IF(P$6<$G89,0,IF(P$6>$H89,1,(P$6-$G89+1)/($H89-$G89+1)))) -> 0 | ... BO89: =IF($G89=0,0,IF(BO$6<$G89,0,IF(BO$6>$H89,1,(BO$6-$G89+1)/($H89-$G89+1)))) -> 1
B90: 9.6 | C90: RECALCE 6 WP49 | D90: 53 días | E90: =SUM(E91:E98) -> 9.2295182e+08 | F90: =IFERROR(E90/$E$44,0) -> 0.14285714 | G90: 46282 | H90: 46345 | I90: =SUMPRODUCT($F91:$F98,I91:I98) -> 0 | J90: =SUMPRODUCT($F91:$F98,J91:J98) -> 0 | K90: =SUMPRODUCT($F91:$F98,K91:K98) -> 0 | L90: =SUMPRODUCT($F91:$F98,L91:L98) -> 0 | M90: =SUMPRODUCT($F91:$F98,M91:M98) -> 0 | N90: =SUMPRODUCT($F91:$F98,N91:N98) -> 0 | O90: =SUMPRODUCT($F91:$F98,O91:O98) -> 0 | P90: =SUMPRODUCT($F91:$F98,P91:P98) -> 0 | ... BO90: =SUMPRODUCT($F91:$F98,BO91:BO98) -> 1
B91: 9.6.1 | C91: LOCALIZACIÓN DEL HACERO WP49 | D91: 1 día | E91: =VLOOKUP(B91,'Cuadro Control'!C101:J2021,8,FALSE) -> 90662605 | F91: 0.1 | G91: 46282 | H91: 46284 | I91: =IF($G91=0,0,IF(I$6<$G91,0,IF(I$6>$H91,1,(I$6-$G91+1)/($H91-$G91+1)))) -> 0 | J91: =IF($G91=0,0,IF(J$6<$G91,0,IF(J$6>$H91,1,(J$6-$G91+1)/($H91-$G91+1)))) -> 0 | K91: =IF($G91=0,0,IF(K$6<$G91,0,IF(K$6>$H91,1,(K$6-$G91+1)/($H91-$G91+1)))) -> 0 | L91: =IF($G91=0,0,IF(L$6<$G91,0,IF(L$6>$H91,1,(L$6-$G91+1)/($H91-$G91+1)))) -> 0 | M91: =IF($G91=0,0,IF(M$6<$G91,0,IF(M$6>$H91,1,(M$6-$G91+1)/($H91-$G91+1)))) -> 0 | N91: =IF($G91=0,0,IF(N$6<$G91,0,IF(N$6>$H91,1,(N$6-$G91+1)/($H91-$G91+1)))) -> 0 | O91: =IF($G91=0,0,IF(O$6<$G91,0,IF(O$6>$H91,1,(O$6-$G91+1)/($H91-$G91+1)))) -> 0 | P91: =IF($G91=0,0,IF(P$6<$G91,0,IF(P$6>$H91,1,(P$6-$G91+1)/($H91-$G91+1)))) -> 0 | ... BO91: =IF($G91=0,0,IF(BO$6<$G91,0,IF(BO$6>$H91,1,(BO$6-$G91+1)/($H91-$G91+1)))) -> 1
B92: 9.6.2 | C92: ESCARIFICADO Y LIMPIEZA DEL RECUBRIMIENTO WP49 | D92: 4 días | E92: =VLOOKUP(B92,'Cuadro Control'!C102:J2022,8,FALSE) -> 2.3077754e+08 | F92: 0.25 | G92: 46284 | H92: 46289 | I92: =IF($G92=0,0,IF(I$6<$G92,0,IF(I$6>$H92,1,(I$6-$G92+1)/($H92-$G92+1)))) -> 0 | J92: =IF($G92=0,0,IF(J$6<$G92,0,IF(J$6>$H92,1,(J$6-$G92+1)/($H92-$G92+1)))) -> 0 | K92: =IF($G92=0,0,IF(K$6<$G92,0,IF(K$6>$H92,1,(K$6-$G92+1)/($H92-$G92+1)))) -> 0 | L92: =IF($G92=0,0,IF(L$6<$G92,0,IF(L$6>$H92,1,(L$6-$G92+1)/($H92-$G92+1)))) -> 0 | M92: =IF($G92=0,0,IF(M$6<$G92,0,IF(M$6>$H92,1,(M$6-$G92+1)/($H92-$G92+1)))) -> 0 | N92: =IF($G92=0,0,IF(N$6<$G92,0,IF(N$6>$H92,1,(N$6-$G92+1)/($H92-$G92+1)))) -> 0 | O92: =IF($G92=0,0,IF(O$6<$G92,0,IF(O$6>$H92,1,(O$6-$G92+1)/($H92-$G92+1)))) -> 0 | P92: =IF($G92=0,0,IF(P$6<$G92,0,IF(P$6>$H92,1,(P$6-$G92+1)/($H92-$G92+1)))) -> 0 | ... BO92: =IF($G92=0,0,IF(BO$6<$G92,0,IF(BO$6>$H92,1,(BO$6-$G92+1)/($H92-$G92+1)))) -> 1
B93: 9.6.3 | C93: CORTE Y FIGURADO DE ACERO WP49 | D93: 4 días | E93: =VLOOKUP(B93,'Cuadro Control'!C103:J2023,8,FALSE) -> 82420550 | F93: 0.09 | G93: 46289 | H93: 46294 | I93: =IF($G93=0,0,IF(I$6<$G93,0,IF(I$6>$H93,1,(I$6-$G93+1)/($H93-$G93+1)))) -> 0 | J93: =IF($G93=0,0,IF(J$6<$G93,0,IF(J$6>$H93,1,(J$6-$G93+1)/($H93-$G93+1)))) -> 0 | K93: =IF($G93=0,0,IF(K$6<$G93,0,IF(K$6>$H93,1,(K$6-$G93+1)/($H93-$G93+1)))) -> 0 | L93: =IF($G93=0,0,IF(L$6<$G93,0,IF(L$6>$H93,1,(L$6-$G93+1)/($H93-$G93+1)))) -> 0 | M93: =IF($G93=0,0,IF(M$6<$G93,0,IF(M$6>$H93,1,(M$6-$G93+1)/($H93-$G93+1)))) -> 0 | N93: =IF($G93=0,0,IF(N$6<$G93,0,IF(N$6>$H93,1,(N$6-$G93+1)/($H93-$G93+1)))) -> 0 | O93: =IF($G93=0,0,IF(O$6<$G93,0,IF(O$6>$H93,1,(O$6-$G93+1)/($H93-$G93+1)))) -> 0 | P93: =IF($G93=0,0,IF(P$6<$G93,0,IF(P$6>$H93,1,(P$6-$G93+1)/($H93-$G93+1)))) -> 0 | ... BO93: =IF($G93=0,0,IF(BO$6<$G93,0,IF(BO$6>$H93,1,(BO$6-$G93+1)/($H93-$G93+1)))) -> 1
B94: 9.6.4 | C94: APLICACIÓN DE EPOXICO Y FIJACIÓN DEL ACERO WP49 | D94: 4 días | E94: =VLOOKUP(B94,'Cuadro Control'!C104:J2024,8,FALSE) -> 2.3077754e+08 | F94: 0.25 | G94: 46329 | H94: 46332 | I94: =IF($G94=0,0,IF(I$6<$G94,0,IF(I$6>$H94,1,(I$6-$G94+1)/($H94-$G94+1)))) -> 0 | J94: =IF($G94=0,0,IF(J$6<$G94,0,IF(J$6>$H94,1,(J$6-$G94+1)/($H94-$G94+1)))) -> 0 | K94: =IF($G94=0,0,IF(K$6<$G94,0,IF(K$6>$H94,1,(K$6-$G94+1)/($H94-$G94+1)))) -> 0 | L94: =IF($G94=0,0,IF(L$6<$G94,0,IF(L$6>$H94,1,(L$6-$G94+1)/($H94-$G94+1)))) -> 0 | M94: =IF($G94=0,0,IF(M$6<$G94,0,IF(M$6>$H94,1,(M$6-$G94+1)/($H94-$G94+1)))) -> 0 | N94: =IF($G94=0,0,IF(N$6<$G94,0,IF(N$6>$H94,1,(N$6-$G94+1)/($H94-$G94+1)))) -> 0 | O94: =IF($G94=0,0,IF(O$6<$G94,0,IF(O$6>$H94,1,(O$6-$G94+1)/($H94-$G94+1)))) -> 0 | P94: =IF($G94=0,0,IF(P$6<$G94,0,IF(P$6>$H94,1,(P$6-$G94+1)/($H94-$G94+1)))) -> 0 | ... BO94: =IF($G94=0,0,IF(BO$6<$G94,0,IF(BO$6>$H94,1,(BO$6-$G94+1)/($H94-$G94+1)))) -> 1
B95: 9.6.5 | C95: ENCONFRADO WP49 | D95: 1 día | E95: =VLOOKUP(B95,'Cuadro Control'!C105:J2025,8,FALSE) -> 49452330 | F95: 0.05 | G95: 46332 | H95: 46333 | I95: =IF($G95=0,0,IF(I$6<$G95,0,IF(I$6>$H95,1,(I$6-$G95+1)/($H95-$G95+1)))) -> 0 | J95: =IF($G95=0,0,IF(J$6<$G95,0,IF(J$6>$H95,1,(J$6-$G95+1)/($H95-$G95+1)))) -> 0 | K95: =IF($G95=0,0,IF(K$6<$G95,0,IF(K$6>$H95,1,(K$6-$G95+1)/($H95-$G95+1)))) -> 0 | L95: =IF($G95=0,0,IF(L$6<$G95,0,IF(L$6>$H95,1,(L$6-$G95+1)/($H95-$G95+1)))) -> 0 | M95: =IF($G95=0,0,IF(M$6<$G95,0,IF(M$6>$H95,1,(M$6-$G95+1)/($H95-$G95+1)))) -> 0 | N95: =IF($G95=0,0,IF(N$6<$G95,0,IF(N$6>$H95,1,(N$6-$G95+1)/($H95-$G95+1)))) -> 0 | O95: =IF($G95=0,0,IF(O$6<$G95,0,IF(O$6>$H95,1,(O$6-$G95+1)/($H95-$G95+1)))) -> 0 | P95: =IF($G95=0,0,IF(P$6<$G95,0,IF(P$6>$H95,1,(P$6-$G95+1)/($H95-$G95+1)))) -> 0 | ... BO95: =IF($G95=0,0,IF(BO$6<$G95,0,IF(BO$6>$H95,1,(BO$6-$G95+1)/($H95-$G95+1)))) -> 1
B96: 9.6.6 | C96: VACIADO DE CONCRETO (APLICACIÓN PUENTE DE ADHERENCIA) WP49 | D96: 1 día | E96: =VLOOKUP(B96,'Cuadro Control'!C106:J2026,8,FALSE) -> 1.4011493e+08 | F96: 0.15 | G96: 46333 | H96: 46335 | I96: =IF($G96=0,0,IF(I$6<$G96,0,IF(I$6>$H96,1,(I$6-$G96+1)/($H96-$G96+1)))) -> 0 | J96: =IF($G96=0,0,IF(J$6<$G96,0,IF(J$6>$H96,1,(J$6-$G96+1)/($H96-$G96+1)))) -> 0 | K96: =IF($G96=0,0,IF(K$6<$G96,0,IF(K$6>$H96,1,(K$6-$G96+1)/($H96-$G96+1)))) -> 0 | L96: =IF($G96=0,0,IF(L$6<$G96,0,IF(L$6>$H96,1,(L$6-$G96+1)/($H96-$G96+1)))) -> 0 | M96: =IF($G96=0,0,IF(M$6<$G96,0,IF(M$6>$H96,1,(M$6-$G96+1)/($H96-$G96+1)))) -> 0 | N96: =IF($G96=0,0,IF(N$6<$G96,0,IF(N$6>$H96,1,(N$6-$G96+1)/($H96-$G96+1)))) -> 0 | O96: =IF($G96=0,0,IF(O$6<$G96,0,IF(O$6>$H96,1,(O$6-$G96+1)/($H96-$G96+1)))) -> 0 | P96: =IF($G96=0,0,IF(P$6<$G96,0,IF(P$6>$H96,1,(P$6-$G96+1)/($H96-$G96+1)))) -> 0 | ... BO96: =IF($G96=0,0,IF(BO$6<$G96,0,IF(BO$6>$H96,1,(BO$6-$G96+1)/($H96-$G96+1)))) -> 1
B97: 9.6.7 | C97: ADECUACIONES E INSTALACIONES ELECTRICAS REQUERIDAS WP49 | D97: 3 días | E97: =VLOOKUP(B97,'Cuadro Control'!C107:J2027,8,FALSE) -> 52335716 | F97: 0.06 | G97: 46335 | H97: 46338 | I97: =IF($G97=0,0,IF(I$6<$G97,0,IF(I$6>$H97,1,(I$6-$G97+1)/($H97-$G97+1)))) -> 0 | J97: =IF($G97=0,0,IF(J$6<$G97,0,IF(J$6>$H97,1,(J$6-$G97+1)/($H97-$G97+1)))) -> 0 | K97: =IF($G97=0,0,IF(K$6<$G97,0,IF(K$6>$H97,1,(K$6-$G97+1)/($H97-$G97+1)))) -> 0 | L97: =IF($G97=0,0,IF(L$6<$G97,0,IF(L$6>$H97,1,(L$6-$G97+1)/($H97-$G97+1)))) -> 0 | M97: =IF($G97=0,0,IF(M$6<$G97,0,IF(M$6>$H97,1,(M$6-$G97+1)/($H97-$G97+1)))) -> 0 | N97: =IF($G97=0,0,IF(N$6<$G97,0,IF(N$6>$H97,1,(N$6-$G97+1)/($H97-$G97+1)))) -> 0 | O97: =IF($G97=0,0,IF(O$6<$G97,0,IF(O$6>$H97,1,(O$6-$G97+1)/($H97-$G97+1)))) -> 0 | P97: =IF($G97=0,0,IF(P$6<$G97,0,IF(P$6>$H97,1,(P$6-$G97+1)/($H97-$G97+1)))) -> 0 | ... BO97: =IF($G97=0,0,IF(BO$6<$G97,0,IF(BO$6>$H97,1,(BO$6-$G97+1)/($H97-$G97+1)))) -> 1
B98: 9.6.8 | C98: INSTALACION DE GROUT Y MORTERO AUTOCOMPACTANTE DE ALTA RESISTENCIA WP49 | D98: 2 días | E98: =VLOOKUP(B98,'Cuadro Control'!C108:J2028,8,FALSE) -> 46410609 | F98: 0.05 | G98: 46343 | H98: 46345 | I98: =IF($G98=0,0,IF(I$6<$G98,0,IF(I$6>$H98,1,(I$6-$G98+1)/($H98-$G98+1)))) -> 0 | J98: =IF($G98=0,0,IF(J$6<$G98,0,IF(J$6>$H98,1,(J$6-$G98+1)/($H98-$G98+1)))) -> 0 | K98: =IF($G98=0,0,IF(K$6<$G98,0,IF(K$6>$H98,1,(K$6-$G98+1)/($H98-$G98+1)))) -> 0 | L98: =IF($G98=0,0,IF(L$6<$G98,0,IF(L$6>$H98,1,(L$6-$G98+1)/($H98-$G98+1)))) -> 0 | M98: =IF($G98=0,0,IF(M$6<$G98,0,IF(M$6>$H98,1,(M$6-$G98+1)/($H98-$G98+1)))) -> 0 | N98: =IF($G98=0,0,IF(N$6<$G98,0,IF(N$6>$H98,1,(N$6-$G98+1)/($H98-$G98+1)))) -> 0 | O98: =IF($G98=0,0,IF(O$6<$G98,0,IF(O$6>$H98,1,(O$6-$G98+1)/($H98-$G98+1)))) -> 0 | P98: =IF($G98=0,0,IF(P$6<$G98,0,IF(P$6>$H98,1,(P$6-$G98+1)/($H98-$G98+1)))) -> 0 | ... BO98: =IF($G98=0,0,IF(BO$6<$G98,0,IF(BO$6>$H98,1,(BO$6-$G98+1)/($H98-$G98+1)))) -> 1
B99: 9.7 | C99: RECALCE 7 WP52 | D99: 53 días | E99: =SUM(E100:E107) -> 9.2295182e+08 | F99: =IFERROR(E99/$E$44,0) -> 0.14285714 | G99: 46289 | H99: 46352 | I99: =SUMPRODUCT($F100:$F107,I100:I107) -> 0 | J99: =SUMPRODUCT($F100:$F107,J100:J107) -> 0 | K99: =SUMPRODUCT($F100:$F107,K100:K107) -> 0 | L99: =SUMPRODUCT($F100:$F107,L100:L107) -> 0 | M99: =SUMPRODUCT($F100:$F107,M100:M107) -> 0 | N99: =SUMPRODUCT($F100:$F107,N100:N107) -> 0 | O99: =SUMPRODUCT($F100:$F107,O100:O107) -> 0 | P99: =SUMPRODUCT($F100:$F107,P100:P107) -> 0 | ... BO99: =SUMPRODUCT($F100:$F107,BO100:BO107) -> 1
B100: 9.7.1 | C100: LOCALIZACIÓN DEL ACERO WP52 | D100: 1 día | E100: =VLOOKUP(B100,'Cuadro Control'!C112:J2030,8,FALSE) -> 90662605 | F100: 0.1 | G100: 46289 | H100: 46291 | I100: =IF($G100=0,0,IF(I$6<$G100,0,IF(I$6>$H100,1,(I$6-$G100+1)/($H100-$G100+1)))) -> 0 | J100: =IF($G100=0,0,IF(J$6<$G100,0,IF(J$6>$H100,1,(J$6-$G100+1)/($H100-$G100+1)))) -> 0 | K100: =IF($G100=0,0,IF(K$6<$G100,0,IF(K$6>$H100,1,(K$6-$G100+1)/($H100-$G100+1)))) -> 0 | L100: =IF($G100=0,0,IF(L$6<$G100,0,IF(L$6>$H100,1,(L$6-$G100+1)/($H100-$G100+1)))) -> 0 | M100: =IF($G100=0,0,IF(M$6<$G100,0,IF(M$6>$H100,1,(M$6-$G100+1)/($H100-$G100+1)))) -> 0 | N100: =IF($G100=0,0,IF(N$6<$G100,0,IF(N$6>$H100,1,(N$6-$G100+1)/($H100-$G100+1)))) -> 0 | O100: =IF($G100=0,0,IF(O$6<$G100,0,IF(O$6>$H100,1,(O$6-$G100+1)/($H100-$G100+1)))) -> 0 | P100: =IF($G100=0,0,IF(P$6<$G100,0,IF(P$6>$H100,1,(P$6-$G100+1)/($H100-$G100+1)))) -> 0 | ... BO100: =IF($G100=0,0,IF(BO$6<$G100,0,IF(BO$6>$H100,1,(BO$6-$G100+1)/($H100-$G100+1)))) -> 1
B101: 9.7.2 | C101: ESCARIFICADO Y LIMPIEZA DEL RECUBRIMIENTO WP52 | D101: 4 días | E101: =VLOOKUP(B101,'Cuadro Control'!C114:J2031,8,FALSE) -> 2.3077754e+08 | F101: 0.25 | G101: 46291 | H101: 46296 | I101: =IF($G101=0,0,IF(I$6<$G101,0,IF(I$6>$H101,1,(I$6-$G101+1)/($H101-$G101+1)))) -> 0 | J101: =IF($G101=0,0,IF(J$6<$G101,0,IF(J$6>$H101,1,(J$6-$G101+1)/($H101-$G101+1)))) -> 0 | K101: =IF($G101=0,0,IF(K$6<$G101,0,IF(K$6>$H101,1,(K$6-$G101+1)/($H101-$G101+1)))) -> 0 | L101: =IF($G101=0,0,IF(L$6<$G101,0,IF(L$6>$H101,1,(L$6-$G101+1)/($H101-$G101+1)))) -> 0 | M101: =IF($G101=0,0,IF(M$6<$G101,0,IF(M$6>$H101,1,(M$6-$G101+1)/($H101-$G101+1)))) -> 0 | N101: =IF($G101=0,0,IF(N$6<$G101,0,IF(N$6>$H101,1,(N$6-$G101+1)/($H101-$G101+1)))) -> 0 | O101: =IF($G101=0,0,IF(O$6<$G101,0,IF(O$6>$H101,1,(O$6-$G101+1)/($H101-$G101+1)))) -> 0 | P101: =IF($G101=0,0,IF(P$6<$G101,0,IF(P$6>$H101,1,(P$6-$G101+1)/($H101-$G101+1)))) -> 0 | ... BO101: =IF($G101=0,0,IF(BO$6<$G101,0,IF(BO$6>$H101,1,(BO$6-$G101+1)/($H101-$G101+1)))) -> 1
B102: 9.7.3 | C102: CORTE Y FIGURADO DE ACERO WP52 | D102: 2 días | E102: =VLOOKUP(B102,'Cuadro Control'!C116:J2032,8,FALSE) -> 82420550 | F102: 0.09 | G102: 46297 | H102: 46301 | I102: =IF($G102=0,0,IF(I$6<$G102,0,IF(I$6>$H102,1,(I$6-$G102+1)/($H102-$G102+1)))) -> 0 | J102: =IF($G102=0,0,IF(J$6<$G102,0,IF(J$6>$H102,1,(J$6-$G102+1)/($H102-$G102+1)))) -> 0 | K102: =IF($G102=0,0,IF(K$6<$G102,0,IF(K$6>$H102,1,(K$6-$G102+1)/($H102-$G102+1)))) -> 0 | L102: =IF($G102=0,0,IF(L$6<$G102,0,IF(L$6>$H102,1,(L$6-$G102+1)/($H102-$G102+1)))) -> 0 | M102: =IF($G102=0,0,IF(M$6<$G102,0,IF(M$6>$H102,1,(M$6-$G102+1)/($H102-$G102+1)))) -> 0 | N102: =IF($G102=0,0,IF(N$6<$G102,0,IF(N$6>$H102,1,(N$6-$G102+1)/($H102-$G102+1)))) -> 0 | O102: =IF($G102=0,0,IF(O$6<$G102,0,IF(O$6>$H102,1,(O$6-$G102+1)/($H102-$G102+1)))) -> 0 | P102: =IF($G102=0,0,IF(P$6<$G102,0,IF(P$6>$H102,1,(P$6-$G102+1)/($H102-$G102+1)))) -> 0 | ... BO102: =IF($G102=0,0,IF(BO$6<$G102,0,IF(BO$6>$H102,1,(BO$6-$G102+1)/($H102-$G102+1)))) -> 1
B103: 9.7.4 | C103: APLICACIÓN DE EPOXICO Y FIJACIÓN DEL ACERO WP52 | D103: 4 días | E103: =VLOOKUP(B103,'Cuadro Control'!C118:J2033,8,FALSE) -> 2.3077754e+08 | F103: 0.25 | G103: 46335 | H103: 46339 | I103: =IF($G103=0,0,IF(I$6<$G103,0,IF(I$6>$H103,1,(I$6-$G103+1)/($H103-$G103+1)))) -> 0 | J103: =IF($G103=0,0,IF(J$6<$G103,0,IF(J$6>$H103,1,(J$6-$G103+1)/($H103-$G103+1)))) -> 0 | K103: =IF($G103=0,0,IF(K$6<$G103,0,IF(K$6>$H103,1,(K$6-$G103+1)/($H103-$G103+1)))) -> 0 | L103: =IF($G103=0,0,IF(L$6<$G103,0,IF(L$6>$H103,1,(L$6-$G103+1)/($H103-$G103+1)))) -> 0 | M103: =IF($G103=0,0,IF(M$6<$G103,0,IF(M$6>$H103,1,(M$6-$G103+1)/($H103-$G103+1)))) -> 0 | N103: =IF($G103=0,0,IF(N$6<$G103,0,IF(N$6>$H103,1,(N$6-$G103+1)/($H103-$G103+1)))) -> 0 | O103: =IF($G103=0,0,IF(O$6<$G103,0,IF(O$6>$H103,1,(O$6-$G103+1)/($H103-$G103+1)))) -> 0 | P103: =IF($G103=0,0,IF(P$6<$G103,0,IF(P$6>$H103,1,(P$6-$G103+1)/($H103-$G103+1)))) -> 0 | ... BO103: =IF($G103=0,0,IF(BO$6<$G103,0,IF(BO$6>$H103,1,(BO$6-$G103+1)/($H103-$G103+1)))) -> 1
...

Sheet PDT ODS02 Proyectado
B3: CW381147-ODS002: CONSTRUCCIÓN DE PLATAFORMAS Y CIMENTACIONES DE AEROGENERADORES DEL PARQUE EÓLICO WINDPESHI | I3: SEMANAS | K3: 0 | L3: 1 | M3: 2 | N3: 3 | O3: 4 | P3: 5 | Q3: 6 | R3: 7 | S3: 8 | T3: 9 | U3: 10 | V3: 11 | W3: 12 | X3: 13 | Y3: 14 | Z3: 15 | AA3: 16 | AB3: 17 | AC3: 18 | AD3: 19 | AE3: 20 | AF3: 21 | AG3: 22 | AH3: 23 | AI3: 24 | AJ3: 25 | AK3: 26 | AL3: 27 | AM3: 28 | AN3: 29 | AO3: 30 | AP3: 31 | AQ3: 32 | AR3: 33 | AS3: 34 | AT3: 35 | AU3: 36 | AV3: 37 | AW3: 38 | AX3: 39 | AY3: 40 | AZ3: 41 | BA3: 42 | BB3: 43 | BC3: 44 | BD3: 45 | BE3: 46 | BF3: 47 | BG3: 48 | BH3: 49 | BI3: 50 | BJ3: 51 | BK3: 52 | BL3: 53 | BM3: 54 | BN3: 55 | BO3: 56 | BP3: 57 | BQ3: 58
K4: =G8 -> 46218 | L4: =K4+2 -> 46220 | M4: =L4+7 -> 46227 | N4: =M4+7 -> 46234 | O4: =N4+7 -> 46241 | P4: =O4+7 -> 46248 | Q4: =P4+7 -> 46255 | R4: =Q4+7 -> 46262 | S4: =R4+7 -> 46269 | T4: =S4+7 -> 46276 | ... BQ4: =BP4+7 -> 46619
I5: AVANCES PROGRAMADOS | K5: =K7*$E$8 -> 0 | L5: =L7*$E$8 -> 2871440.7 | M5: =M7*$E$8 -> 25521456 | N5: =N7*$E$8 -> 6.4757687e+08 | O5: =O7*$E$8 -> 1.320406e+09 | P5: =P7*$E$8 -> 1.5043962e+09 | Q5: =Q7*$E$8 -> 1.8283878e+09 | R5: =R7*$E$8 -> 2.2925623e+09 | ... BQ5: =BQ7*$E$8 -> 2.0706618e+11
I6: FECHAS | K6: =K4 -> 46218 | L6: =L4 -> 46220 | M6: =M4 -> 46227 | N6: =N4 -> 46234 | O6: =O4 -> 46241 | P6: =P4 -> 46248 | Q6: =Q4 -> 46255 | R6: =R4 -> 46262 | ... BR6: =BR4 -> 0
B7: EDT | C7: Nombre de tarea | D7: Duración | E7: Costo | F7: PESO RELATIVO AL CAPITULO (%) | G7: Comienzo | I7: Fin | K7: =$F34*K34+$F39*K39+$F44*K44+$F109*K109+$F689*K689+$F695*K695+$F699*K699 -> 0 | L7: =$F34*L34+$F39*L39+$F44*L44+$F109*L109+$F689*L689+$F695*L695+$F699*L699 -> 1.3775459e-05 | M7: =$F34*M34+$F39*M39+$F44*M44+$F109*M109+$F689*M689+$F695*M695+$F699*M699 -> 0.00012243672 | N7: =$F34*N34+$F39*N39+$F44*N44+$F109*N109+$F689*N689+$F695*N695+$F699*N699 -> 0.0031066874 | O7: =$F34*O34+$F39*O39+$F44*O44+$F109*O109+$F689*O689+$F695*O695+$F699*O699 -> 0.0063345203 | P7: =$F34*P34+$F39*P39+$F44*P44+$F109*P109+$F689*P689+$F695*P695+$F699*P699 -> 0.0072171954 | Q7: =$F34*Q34+$F39*Q39+$F44*Q44+$F109*Q109+$F689*Q689+$F695*Q695+$F699*Q699 -> 0.0087715138 | R7: =$F34*R34+$F39*R39+$F44*R44+$F109*R109+$F689*R689+$F695*R695+$F699*R699 -> 0.010998346 | ... BQ7: =$F34*BQ34+$F39*BQ39+$F44*BQ44+$F109*BQ109+$F689*BQ689+$F695*BQ695+$F699*BQ699 -> 0.99337996
B8: 0 | C8: ODS02_IIWAKAI | D8: 357 días | E8: =+E34+E39+E44+E109+E689+E695+E699 -> 2.084461e+11 | F8: =+F10+F14++F29+F30+F34+F39+F44+F109+F689+F695+F699 -> 1 | G8: 46218 | I8: 46637 | K8: =K7*$E$8 -> 0 | L8: =L7*$E$8 -> 2871440.7 | M8: =M7*$E$8 -> 25521456 | N8: =N7*$E$8 -> 6.4757687e+08 | O8: =O7*$E$8 -> 1.320406e+09 | P8: =P7*$E$8 -> 1.5043962e+09 | Q8: =Q7*$E$8 -> 1.8283878e+09 | R8: =R7*$E$8 -> 2.2925623e+09 | ... BQ8: =BQ7*$E$8 -> 2.0706618e+11
B9: 1 | C9: HITO 1: ACTA DE INICIO | D9: 0 días | E9: =VLOOKUP(B9,'Cuadro Control'!C5:J1939,8,FALSE) -> 0 | F9: =IFERROR(E9/$E$8,0) -> 0 | G9: 46218 | I9: 46218 | J9: =+INDEX($K9:$BQ9,1,MATCH(I9,$K$6:$BQ$6,1)) -> 1 | K9: =IF($G9=0,0,IF(K$6<$G9,0,IF(K$6>$I9,1,(K$6-$G9+1)/($I9-$G9+1)))) -> 1 | L9: =IF($G9=0,0,IF(L$6<$G9,0,IF(L$6>$I9,1,(L$6-$G9+1)/($I9-$G9+1)))) -> 1 | M9: =IF($G9=0,0,IF(M$6<$G9,0,IF(M$6>$I9,1,(M$6-$G9+1)/($I9-$G9+1)))) -> 1 | N9: =IF($G9=0,0,IF(N$6<$G9,0,IF(N$6>$I9,1,(N$6-$G9+1)/($I9-$G9+1)))) -> 1 | O9: =IF($G9=0,0,IF(O$6<$G9,0,IF(O$6>$I9,1,(O$6-$G9+1)/($I9-$G9+1)))) -> 1 | P9: =IF($G9=0,0,IF(P$6<$G9,0,IF(P$6>$I9,1,(P$6-$G9+1)/($I9-$G9+1)))) -> 1 | Q9: =IF($G9=0,0,IF(Q$6<$G9,0,IF(Q$6>$I9,1,(Q$6-$G9+1)/($I9-$G9+1)))) -> 1 | R9: =IF($G9=0,0,IF(R$6<$G9,0,IF(R$6>$I9,1,(R$6-$G9+1)/($I9-$G9+1)))) -> 1 | ... BQ9: =IF($G9=0,0,IF(BQ$6<$G9,0,IF(BQ$6>$I9,1,(BQ$6-$G9+1)/($I9-$G9+1)))) -> 1 | BR9: =+AVERAGE(K9:BQ9) -> 1
B10: 2 | C10: PRELIMINARES GENERALES | D10: 21 días | E10: =VLOOKUP(B10,'Cuadro Control'!C6:J1940,8,FALSE) -> 0 | F10: =IFERROR(E10/$E$8,0) -> 0 | G10: 46218 | I10: 46268 | J10: =+INDEX($K10:$BQ10,1,MATCH(I10,$K$6:$BQ$6,1)) -> 0.88235294 | K10: =IF($G10=0,0,IF(K$6<$G10,0,IF(K$6>$I10,1,(K$6-$G10+1)/($I10-$G10+1)))) -> 0.019607843 | L10: =IF($G10=0,0,IF(L$6<$G10,0,IF(L$6>$I10,1,(L$6-$G10+1)/($I10-$G10+1)))) -> 0.058823529 | M10: =IF($G10=0,0,IF(M$6<$G10,0,IF(M$6>$I10,1,(M$6-$G10+1)/($I10-$G10+1)))) -> 0.19607843 | N10: =IF($G10=0,0,IF(N$6<$G10,0,IF(N$6>$I10,1,(N$6-$G10+1)/($I10-$G10+1)))) -> 0.33333333 | O10: =IF($G10=0,0,IF(O$6<$G10,0,IF(O$6>$I10,1,(O$6-$G10+1)/($I10-$G10+1)))) -> 0.47058824 | P10: =IF($G10=0,0,IF(P$6<$G10,0,IF(P$6>$I10,1,(P$6-$G10+1)/($I10-$G10+1)))) -> 0.60784314 | Q10: =IF($G10=0,0,IF(Q$6<$G10,0,IF(Q$6>$I10,1,(Q$6-$G10+1)/($I10-$G10+1)))) -> 0.74509804 | R10: =IF($G10=0,0,IF(R$6<$G10,0,IF(R$6>$I10,1,(R$6-$G10+1)/($I10-$G10+1)))) -> 0.88235294 | ... BQ10: =IF($G10=0,0,IF(BQ$6<$G10,0,IF(BQ$6>$I10,1,(BQ$6-$G10+1)/($I10-$G10+1)))) -> 1 | BR10: =+AVERAGE(K10:BQ10) -> 0.92057162
B11: 2.1 | C11: ENTREGA DE DOCUMENTOS HABILITADORES | D11: 0 días | E11: =VLOOKUP(B11,'Cuadro Control'!C7:J1941,8,FALSE) -> 0 | F11: =IFERROR(E11/$E$8,0) -> 0 | G11: 46218 | I11: 46218 | J11: =+INDEX($K11:$BQ11,1,MATCH(I11,$K$6:$BQ$6,1)) -> 1 | K11: =IF($G11=0,0,IF(K$6<$G11,0,IF(K$6>$I11,1,(K$6-$G11+1)/($I11-$G11+1)))) -> 1 | L11: =IF($G11=0,0,IF(L$6<$G11,0,IF(L$6>$I11,1,(L$6-$G11+1)/($I11-$G11+1)))) -> 1 | M11: =IF($G11=0,0,IF(M$6<$G11,0,IF(M$6>$I11,1,(M$6-$G11+1)/($I11-$G11+1)))) -> 1 | N11: =IF($G11=0,0,IF(N$6<$G11,0,IF(N$6>$I11,1,(N$6-$G11+1)/($I11-$G11+1)))) -> 1 | O11: =IF($G11=0,0,IF(O$6<$G11,0,IF(O$6>$I11,1,(O$6-$G11+1)/($I11-$G11+1)))) -> 1 | P11: =IF($G11=0,0,IF(P$6<$G11,0,IF(P$6>$I11,1,(P$6-$G11+1)/($I11-$G11+1)))) -> 1 | Q11: =IF($G11=0,0,IF(Q$6<$G11,0,IF(Q$6>$I11,1,(Q$6-$G11+1)/($I11-$G11+1)))) -> 1 | R11: =IF($G11=0,0,IF(R$6<$G11,0,IF(R$6>$I11,1,(R$6-$G11+1)/($I11-$G11+1)))) -> 1 | ... BQ11: =IF($G11=0,0,IF(BQ$6<$G11,0,IF(BQ$6>$I11,1,(BQ$6-$G11+1)/($I11-$G11+1)))) -> 1 | BR11: =+AVERAGE(K11:BQ11) -> 1
B12: 2.2 | C12: ENTREGA DE DOCUMENTACIÓN DE EJECUCION DEL PROYECTO | D12: 0 días | E12: =VLOOKUP(B12,'Cuadro Control'!C8:J1942,8,FALSE) -> 0 | F12: =IFERROR(E12/$E$8,0) -> 0 | G12: 46218 | I12: 46218 | J12: =+INDEX($K12:$BQ12,1,MATCH(I12,$K$6:$BQ$6,1)) -> 1 | K12: =IF($G12=0,0,IF(K$6<$G12,0,IF(K$6>$I12,1,(K$6-$G12+1)/($I12-$G12+1)))) -> 1 | L12: =IF($G12=0,0,IF(L$6<$G12,0,IF(L$6>$I12,1,(L$6-$G12+1)/($I12-$G12+1)))) -> 1 | M12: =IF($G12=0,0,IF(M$6<$G12,0,IF(M$6>$I12,1,(M$6-$G12+1)/($I12-$G12+1)))) -> 1 | N12: =IF($G12=0,0,IF(N$6<$G12,0,IF(N$6>$I12,1,(N$6-$G12+1)/($I12-$G12+1)))) -> 1 | O12: =IF($G12=0,0,IF(O$6<$G12,0,IF(O$6>$I12,1,(O$6-$G12+1)/($I12-$G12+1)))) -> 1 | P12: =IF($G12=0,0,IF(P$6<$G12,0,IF(P$6>$I12,1,(P$6-$G12+1)/($I12-$G12+1)))) -> 1 | Q12: =IF($G12=0,0,IF(Q$6<$G12,0,IF(Q$6>$I12,1,(Q$6-$G12+1)/($I12-$G12+1)))) -> 1 | R12: =IF($G12=0,0,IF(R$6<$G12,0,IF(R$6>$I12,1,(R$6-$G12+1)/($I12-$G12+1)))) -> 1 | ... BQ12: =IF($G12=0,0,IF(BQ$6<$G12,0,IF(BQ$6>$I12,1,(BQ$6-$G12+1)/($I12-$G12+1)))) -> 1 | BR12: =+AVERAGE(K12:BQ12) -> 1
B13: 2.3 | C13: REVISIÓN Y RECEPCIÓN DE INGENIERIA | D13: 21 días | E13: =VLOOKUP(B13,'Cuadro Control'!C9:J1943,8,FALSE) -> 0 | F13: =IFERROR(E13/$E$8,0) -> 0 | G13: 46218 | I13: 46268 | J13: =+INDEX($K13:$BQ13,1,MATCH(I13,$K$6:$BQ$6,1)) -> 0.88235294 | K13: =IF($G13=0,0,IF(K$6<$G13,0,IF(K$6>$I13,1,(K$6-$G13+1)/($I13-$G13+1)))) -> 0.019607843 | L13: =IF($G13=0,0,IF(L$6<$G13,0,IF(L$6>$I13,1,(L$6-$G13+1)/($I13-$G13+1)))) -> 0.058823529 | M13: =IF($G13=0,0,IF(M$6<$G13,0,IF(M$6>$I13,1,(M$6-$G13+1)/($I13-$G13+1)))) -> 0.19607843 | N13: =IF($G13=0,0,IF(N$6<$G13,0,IF(N$6>$I13,1,(N$6-$G13+1)/($I13-$G13+1)))) -> 0.33333333 | O13: =IF($G13=0,0,IF(O$6<$G13,0,IF(O$6>$I13,1,(O$6-$G13+1)/($I13-$G13+1)))) -> 0.47058824 | P13: =IF($G13=0,0,IF(P$6<$G13,0,IF(P$6>$I13,1,(P$6-$G13+1)/($I13-$G13+1)))) -> 0.60784314 | Q13: =IF($G13=0,0,IF(Q$6<$G13,0,IF(Q$6>$I13,1,(Q$6-$G13+1)/($I13-$G13+1)))) -> 0.74509804 | R13: =IF($G13=0,0,IF(R$6<$G13,0,IF(R$6>$I13,1,(R$6-$G13+1)/($I13-$G13+1)))) -> 0.88235294 | ... BQ13: =IF($G13=0,0,IF(BQ$6<$G13,0,IF(BQ$6>$I13,1,(BQ$6-$G13+1)/($I13-$G13+1)))) -> 1 | BR13: =+AVERAGE(K13:BQ13) -> 0.92057162
B14: 3 | C14: SOCIALIZACIÓN CON COMUNIDADES | D14: 30 días | E14: =VLOOKUP(B14,'Cuadro Control'!C10:J1944,8,FALSE) -> 0 | F14: =IFERROR(E14/$E$8,0) -> 0 | G14: 46218 | I14: 46255 | J14: =+INDEX($K14:$BQ14,1,MATCH(I14,$K$6:$BQ$6,1)) -> 1 | K14: =IF($G14=0,0,IF(K$6<$G14,0,IF(K$6>$I14,1,(K$6-$G14+1)/($I14-$G14+1)))) -> 0.026315789 | L14: =IF($G14=0,0,IF(L$6<$G14,0,IF(L$6>$I14,1,(L$6-$G14+1)/($I14-$G14+1)))) -> 0.078947368 | M14: =IF($G14=0,0,IF(M$6<$G14,0,IF(M$6>$I14,1,(M$6-$G14+1)/($I14-$G14+1)))) -> 0.26315789 | N14: =IF($G14=0,0,IF(N$6<$G14,0,IF(N$6>$I14,1,(N$6-$G14+1)/($I14-$G14+1)))) -> 0.44736842 | O14: =IF($G14=0,0,IF(O$6<$G14,0,IF(O$6>$I14,1,(O$6-$G14+1)/($I14-$G14+1)))) -> 0.63157895 | P14: =IF($G14=0,0,IF(P$6<$G14,0,IF(P$6>$I14,1,(P$6-$G14+1)/($I14-$G14+1)))) -> 0.81578947 | Q14: =IF($G14=0,0,IF(Q$6<$G14,0,IF(Q$6>$I14,1,(Q$6-$G14+1)/($I14-$G14+1)))) -> 1 | R14: =IF($G14=0,0,IF(R$6<$G14,0,IF(R$6>$I14,1,(R$6-$G14+1)/($I14-$G14+1)))) -> 1 | ... BQ14: =IF($G14=0,0,IF(BQ$6<$G14,0,IF(BQ$6>$I14,1,(BQ$6-$G14+1)/($I14-$G14+1)))) -> 1 | BR14: =+AVERAGE(K14:BQ14) -> 0.93666369
B15: 3.1 | C15: REUNIONES RIO PATAJATAMA | D15: 0 días | E15: =VLOOKUP(B15,'Cuadro Control'!C11:J1945,8,FALSE) -> 0 | F15: =IFERROR(E15/$E$8,0) -> 0 | G15: 46218 | I15: 46218 | J15: =+INDEX($K15:$BQ15,1,MATCH(I15,$K$6:$BQ$6,1)) -> 1 | K15: =IF($G15=0,0,IF(K$6<$G15,0,IF(K$6>$I15,1,(K$6-$G15+1)/($I15-$G15+1)))) -> 1 | L15: =IF($G15=0,0,IF(L$6<$G15,0,IF(L$6>$I15,1,(L$6-$G15+1)/($I15-$G15+1)))) -> 1 | M15: =IF($G15=0,0,IF(M$6<$G15,0,IF(M$6>$I15,1,(M$6-$G15+1)/($I15-$G15+1)))) -> 1 | N15: =IF($G15=0,0,IF(N$6<$G15,0,IF(N$6>$I15,1,(N$6-$G15+1)/($I15-$G15+1)))) -> 1 | O15: =IF($G15=0,0,IF(O$6<$G15,0,IF(O$6>$I15,1,(O$6-$G15+1)/($I15-$G15+1)))) -> 1 | P15: =IF($G15=0,0,IF(P$6<$G15,0,IF(P$6>$I15,1,(P$6-$G15+1)/($I15-$G15+1)))) -> 1 | Q15: =IF($G15=0,0,IF(Q$6<$G15,0,IF(Q$6>$I15,1,(Q$6-$G15+1)/($I15-$G15+1)))) -> 1 | R15: =IF($G15=0,0,IF(R$6<$G15,0,IF(R$6>$I15,1,(R$6-$G15+1)/($I15-$G15+1)))) -> 1 | ... BQ15: =IF($G15=0,0,IF(BQ$6<$G15,0,IF(BQ$6>$I15,1,(BQ$6-$G15+1)/($I15-$G15+1)))) -> 1 | BR15: =+AVERAGE(K15:BQ15) -> 1
B16: 3.2 | C16: REUNIONES RIO ROMANA | D16: 0 días | E16: =VLOOKUP(B16,'Cuadro Control'!C12:J1946,8,FALSE) -> 0 | F16: =IFERROR(E16/$E$8,0) -> 0 | G16: 46218 | I16: 46218 | J16: =+INDEX($K16:$BQ16,1,MATCH(I16,$K$6:$BQ$6,1)) -> 1 | K16: =IF($G16=0,0,IF(K$6<$G16,0,IF(K$6>$I16,1,(K$6-$G16+1)/($I16-$G16+1)))) -> 1 | L16: =IF($G16=0,0,IF(L$6<$G16,0,IF(L$6>$I16,1,(L$6-$G16+1)/($I16-$G16+1)))) -> 1 | M16: =IF($G16=0,0,IF(M$6<$G16,0,IF(M$6>$I16,1,(M$6-$G16+1)/($I16-$G16+1)))) -> 1 | N16: =IF($G16=0,0,IF(N$6<$G16,0,IF(N$6>$I16,1,(N$6-$G16+1)/($I16-$G16+1)))) -> 1 | O16: =IF($G16=0,0,IF(O$6<$G16,0,IF(O$6>$I16,1,(O$6-$G16+1)/($I16-$G16+1)))) -> 1 | P16: =IF($G16=0,0,IF(P$6<$G16,0,IF(P$6>$I16,1,(P$6-$G16+1)/($I16-$G16+1)))) -> 1 | Q16: =IF($G16=0,0,IF(Q$6<$G16,0,IF(Q$6>$I16,1,(Q$6-$G16+1)/($I16-$G16+1)))) -> 1 | R16: =IF($G16=0,0,IF(R$6<$G16,0,IF(R$6>$I16,1,(R$6-$G16+1)/($I16-$G16+1)))) -> 1 | ... BQ16: =IF($G16=0,0,IF(BQ$6<$G16,0,IF(BQ$6>$I16,1,(BQ$6-$G16+1)/($I16-$G16+1)))) -> 1 | BR16: =+AVERAGE(K16:BQ16) -> 1
B17: 3.3 | C17: REUNIONES RIO UTKAP | D17: 0 días | E17: =VLOOKUP(B17,'Cuadro Control'!C13:J1947,8,FALSE) -> 0 | F17: =IFERROR(E17/$E$8,0) -> 0 | G17: 46218 | I17: 46218 | J17: =+INDEX($K17:$BQ17,1,MATCH(I17,$K$6:$BQ$6,1)) -> 1 | K17: =IF($G17=0,0,IF(K$6<$G17,0,IF(K$6>$I17,1,(K$6-$G17+1)/($I17-$G17+1)))) -> 1 | L17: =IF($G17=0,0,IF(L$6<$G17,0,IF(L$6>$I17,1,(L$6-$G17+1)/($I17-$G17+1)))) -> 1 | M17: =IF($G17=0,0,IF(M$6<$G17,0,IF(M$6>$I17,1,(M$6-$G17+1)/($I17-$G17+1)))) -> 1 | N17: =IF($G17=0,0,IF(N$6<$G17,0,IF(N$6>$I17,1,(N$6-$G17+1)/($I17-$G17+1)))) -> 1 | O17: =IF($G17=0,0,IF(O$6<$G17,0,IF(O$6>$I17,1,(O$6-$G17+1)/($I17-$G17+1)))) -> 1 | P17: =IF($G17=0,0,IF(P$6<$G17,0,IF(P$6>$I17,1,(P$6-$G17+1)/($I17-$G17+1)))) -> 1 | Q17: =IF($G17=0,0,IF(Q$6<$G17,0,IF(Q$6>$I17,1,(Q$6-$G17+1)/($I17-$G17+1)))) -> 1 | R17: =IF($G17=0,0,IF(R$6<$G17,0,IF(R$6>$I17,1,(R$6-$G17+1)/($I17-$G17+1)))) -> 1 | ... BQ17: =IF($G17=0,0,IF(BQ$6<$G17,0,IF(BQ$6>$I17,1,(BQ$6-$G17+1)/($I17-$G17+1)))) -> 1 | BR17: =+AVERAGE(K17:BQ17) -> 1
B18: 3.4 | C18: REUNIONES RIO CALINCHON | D18: 0 días | E18: =VLOOKUP(B18,'Cuadro Control'!C14:J1948,8,FALSE) -> 0 | F18: =IFERROR(E18/$E$8,0) -> 0 | G18: 46218 | I18: 46218 | J18: =+INDEX($K18:$BQ18,1,MATCH(I18,$K$6:$BQ$6,1)) -> 1 | K18: =IF($G18=0,0,IF(K$6<$G18,0,IF(K$6>$I18,1,(K$6-$G18+1)/($I18-$G18+1)))) -> 1 | L18: =IF($G18=0,0,IF(L$6<$G18,0,IF(L$6>$I18,1,(L$6-$G18+1)/($I18-$G18+1)))) -> 1 | M18: =IF($G18=0,0,IF(M$6<$G18,0,IF(M$6>$I18,1,(M$6-$G18+1)/($I18-$G18+1)))) -> 1 | N18: =IF($G18=0,0,IF(N$6<$G18,0,IF(N$6>$I18,1,(N$6-$G18+1)/($I18-$G18+1)))) -> 1 | O18: =IF($G18=0,0,IF(O$6<$G18,0,IF(O$6>$I18,1,(O$6-$G18+1)/($I18-$G18+1)))) -> 1 | P18: =IF($G18=0,0,IF(P$6<$G18,0,IF(P$6>$I18,1,(P$6-$G18+1)/($I18-$G18+1)))) -> 1 | Q18: =IF($G18=0,0,IF(Q$6<$G18,0,IF(Q$6>$I18,1,(Q$6-$G18+1)/($I18-$G18+1)))) -> 1 | R18: =IF($G18=0,0,IF(R$6<$G18,0,IF(R$6>$I18,1,(R$6-$G18+1)/($I18-$G18+1)))) -> 1 | ... BQ18: =IF($G18=0,0,IF(BQ$6<$G18,0,IF(BQ$6>$I18,1,(BQ$6-$G18+1)/($I18-$G18+1)))) -> 1 | BR18: =+AVERAGE(K18:BQ18) -> 1
B19: 3.5 | C19: REUNIONES RIO CAÑAVERAL | D19: 0 días | E19: =VLOOKUP(B19,'Cuadro Control'!C15:J1949,8,FALSE) -> 0 | F19: =IFERROR(E19/$E$8,0) -> 0 | G19: 46218 | I19: 46218 | J19: =+INDEX($K19:$BQ19,1,MATCH(I19,$K$6:$BQ$6,1)) -> 1 | K19: =IF($G19=0,0,IF(K$6<$G19,0,IF(K$6>$I19,1,(K$6-$G19+1)/($I19-$G19+1)))) -> 1 | L19: =IF($G19=0,0,IF(L$6<$G19,0,IF(L$6>$I19,1,(L$6-$G19+1)/($I19-$G19+1)))) -> 1 | M19: =IF($G19=0,0,IF(M$6<$G19,0,IF(M$6>$I19,1,(M$6-$G19+1)/($I19-$G19+1)))) -> 1 | N19: =IF($G19=0,0,IF(N$6<$G19,0,IF(N$6>$I19,1,(N$6-$G19+1)/($I19-$G19+1)))) -> 1 | O19: =IF($G19=0,0,IF(O$6<$G19,0,IF(O$6>$I19,1,(O$6-$G19+1)/($I19-$G19+1)))) -> 1 | P19: =IF($G19=0,0,IF(P$6<$G19,0,IF(P$6>$I19,1,(P$6-$G19+1)/($I19-$G19+1)))) -> 1 | Q19: =IF($G19=0,0,IF(Q$6<$G19,0,IF(Q$6>$I19,1,(Q$6-$G19+1)/($I19-$G19+1)))) -> 1 | R19: =IF($G19=0,0,IF(R$6<$G19,0,IF(R$6>$I19,1,(R$6-$G19+1)/($I19-$G19+1)))) -> 1 | ... BQ19: =IF($G19=0,0,IF(BQ$6<$G19,0,IF(BQ$6>$I19,1,(BQ$6-$G19+1)/($I19-$G19+1)))) -> 1 | BR19: =+AVERAGE(K19:BQ19) -> 1
B20: 3.6 | C20: REUNIONES RIO KAMUSHIPA | D20: 0 días | E20: =VLOOKUP(B20,'Cuadro Control'!C16:J1950,8,FALSE) -> 0 | F20: =IFERROR(E20/$E$8,0) -> 0 | G20: 46218 | I20: 46218 | J20: =+INDEX($K20:$BQ20,1,MATCH(I20,$K$6:$BQ$6,1)) -> 1 | K20: =IF($G20=0,0,IF(K$6<$G20,0,IF(K$6>$I20,1,(K$6-$G20+1)/($I20-$G20+1)))) -> 1 | L20: =IF($G20=0,0,IF(L$6<$G20,0,IF(L$6>$I20,1,(L$6-$G20+1)/($I20-$G20+1)))) -> 1 | M20: =IF($G20=0,0,IF(M$6<$G20,0,IF(M$6>$I20,1,(M$6-$G20+1)/($I20-$G20+1)))) -> 1 | N20: =IF($G20=0,0,IF(N$6<$G20,0,IF(N$6>$I20,1,(N$6-$G20+1)/($I20-$G20+1)))) -> 1 | O20: =IF($G20=0,0,IF(O$6<$G20,0,IF(O$6>$I20,1,(O$6-$G20+1)/($I20-$G20+1)))) -> 1 | P20: =IF($G20=0,0,IF(P$6<$G20,0,IF(P$6>$I20,1,(P$6-$G20+1)/($I20-$G20+1)))) -> 1 | Q20: =IF($G20=0,0,IF(Q$6<$G20,0,IF(Q$6>$I20,1,(Q$6-$G20+1)/($I20-$G20+1)))) -> 1 | R20: =IF($G20=0,0,IF(R$6<$G20,0,IF(R$6>$I20,1,(R$6-$G20+1)/($I20-$G20+1)))) -> 1 | ... BQ20: =IF($G20=0,0,IF(BQ$6<$G20,0,IF(BQ$6>$I20,1,(BQ$6-$G20+1)/($I20-$G20+1)))) -> 1 | BR20: =+AVERAGE(K20:BQ20) -> 1
B21: 3.7 | C21: REUNIONES RIO FLOR DE LA FRONTERA | D21: 0 días | E21: =VLOOKUP(B21,'Cuadro Control'!C17:J1951,8,FALSE) -> 0 | F21: =IFERROR(E21/$E$8,0) -> 0 | G21: 46218 | I21: 46218 | J21: =+INDEX($K21:$BQ21,1,MATCH(I21,$K$6:$BQ$6,1)) -> 1 | K21: =IF($G21=0,0,IF(K$6<$G21,0,IF(K$6>$I21,1,(K$6-$G21+1)/($I21-$G21+1)))) -> 1 | L21: =IF($G21=0,0,IF(L$6<$G21,0,IF(L$6>$I21,1,(L$6-$G21+1)/($I21-$G21+1)))) -> 1 | M21: =IF($G21=0,0,IF(M$6<$G21,0,IF(M$6>$I21,1,(M$6-$G21+1)/($I21-$G21+1)))) -> 1 | N21: =IF($G21=0,0,IF(N$6<$G21,0,IF(N$6>$I21,1,(N$6-$G21+1)/($I21-$G21+1)))) -> 1 | O21: =IF($G21=0,0,IF(O$6<$G21,0,IF(O$6>$I21,1,(O$6-$G21+1)/($I21-$G21+1)))) -> 1 | P21: =IF($G21=0,0,IF(P$6<$G21,0,IF(P$6>$I21,1,(P$6-$G21+1)/($I21-$G21+1)))) -> 1 | Q21: =IF($G21=0,0,IF(Q$6<$G21,0,IF(Q$6>$I21,1,(Q$6-$G21+1)/($I21-$G21+1)))) -> 1 | R21: =IF($G21=0,0,IF(R$6<$G21,0,IF(R$6>$I21,1,(R$6-$G21+1)/($I21-$G21+1)))) -> 1 | ... BQ21: =IF($G21=0,0,IF(BQ$6<$G21,0,IF(BQ$6>$I21,1,(BQ$6-$G21+1)/($I21-$G21+1)))) -> 1 | BR21: =+AVERAGE(K21:BQ21) -> 1
B22: 3.8 | C22: REUNIONES RIO JAIKA KALINCHON | D22: 0 días | E22: =VLOOKUP(B22,'Cuadro Control'!C18:J1952,8,FALSE) -> 0 | F22: =IFERROR(E22/$E$8,0) -> 0 | G22: 46218 | I22: 46218 | J22: =+INDEX($K22:$BQ22,1,MATCH(I22,$K$6:$BQ$6,1)) -> 1 | K22: =IF($G22=0,0,IF(K$6<$G22,0,IF(K$6>$I22,1,(K$6-$G22+1)/($I22-$G22+1)))) -> 1 | L22: =IF($G22=0,0,IF(L$6<$G22,0,IF(L$6>$I22,1,(L$6-$G22+1)/($I22-$G22+1)))) -> 1 | M22: =IF($G22=0,0,IF(M$6<$G22,0,IF(M$6>$I22,1,(M$6-$G22+1)/($I22-$G22+1)))) -> 1 | N22: =IF($G22=0,0,IF(N$6<$G22,0,IF(N$6>$I22,1,(N$6-$G22+1)/($I22-$G22+1)))) -> 1 | O22: =IF($G22=0,0,IF(O$6<$G22,0,IF(O$6>$I22,1,(O$6-$G22+1)/($I22-$G22+1)))) -> 1 | P22: =IF($G22=0,0,IF(P$6<$G22,0,IF(P$6>$I22,1,(P$6-$G22+1)/($I22-$G22+1)))) -> 1 | Q22: =IF($G22=0,0,IF(Q$6<$G22,0,IF(Q$6>$I22,1,(Q$6-$G22+1)/($I22-$G22+1)))) -> 1 | R22: =IF($G22=0,0,IF(R$6<$G22,0,IF(R$6>$I22,1,(R$6-$G22+1)/($I22-$G22+1)))) -> 1 | ... BQ22: =IF($G22=0,0,IF(BQ$6<$G22,0,IF(BQ$6>$I22,1,(BQ$6-$G22+1)/($I22-$G22+1)))) -> 1 | BR22: =+AVERAGE(K22:BQ22) -> 1
B23: 3.9 | C23: REUNIONES RIO MASHUMANA | D23: 0 días | E23: =VLOOKUP(B23,'Cuadro Control'!C19:J1953,8,FALSE) -> 0 | F23: =IFERROR(E23/$E$8,0) -> 0 | G23: 46218 | I23: 46218 | J23: =+INDEX($K23:$BQ23,1,MATCH(I23,$K$6:$BQ$6,1)) -> 1 | K23: =IF($G23=0,0,IF(K$6<$G23,0,IF(K$6>$I23,1,(K$6-$G23+1)/($I23-$G23+1)))) -> 1 | L23: =IF($G23=0,0,IF(L$6<$G23,0,IF(L$6>$I23,1,(L$6-$G23+1)/($I23-$G23+1)))) -> 1 | M23: =IF($G23=0,0,IF(M$6<$G23,0,IF(M$6>$I23,1,(M$6-$G23+1)/($I23-$G23+1)))) -> 1 | N23: =IF($G23=0,0,IF(N$6<$G23,0,IF(N$6>$I23,1,(N$6-$G23+1)/($I23-$G23+1)))) -> 1 | O23: =IF($G23=0,0,IF(O$6<$G23,0,IF(O$6>$I23,1,(O$6-$G23+1)/($I23-$G23+1)))) -> 1 | P23: =IF($G23=0,0,IF(P$6<$G23,0,IF(P$6>$I23,1,(P$6-$G23+1)/($I23-$G23+1)))) -> 1 | Q23: =IF($G23=0,0,IF(Q$6<$G23,0,IF(Q$6>$I23,1,(Q$6-$G23+1)/($I23-$G23+1)))) -> 1 | R23: =IF($G23=0,0,IF(R$6<$G23,0,IF(R$6>$I23,1,(R$6-$G23+1)/($I23-$G23+1)))) -> 1 | ... BQ23: =IF($G23=0,0,IF(BQ$6<$G23,0,IF(BQ$6>$I23,1,(BQ$6-$G23+1)/($I23-$G23+1)))) -> 1 | BR23: =+AVERAGE(K23:BQ23) -> 1
B24: 3.10 | C24: REUNIONES RIO MASHUMANA WANE | D24: 0 días | E24: =VLOOKUP(B24,'Cuadro Control'!C20:J1954,8,FALSE) -> 0 | F24: =IFERROR(E24/$E$8,0) -> 0 | G24: 46218 | I24: 46218 | J24: =+INDEX($K24:$BQ24,1,MATCH(I24,$K$6:$BQ$6,1)) -> 1 | K24: =IF($G24=0,0,IF(K$6<$G24,0,IF(K$6>$I24,1,(K$6-$G24+1)/($I24-$G24+1)))) -> 1 | L24: =IF($G24=0,0,IF(L$6<$G24,0,IF(L$6>$I24,1,(L$6-$G24+1)/($I24-$G24+1)))) -> 1 | M24: =IF($G24=0,0,IF(M$6<$G24,0,IF(M$6>$I24,1,(M$6-$G24+1)/($I24-$G24+1)))) -> 1 | N24: =IF($G24=0,0,IF(N$6<$G24,0,IF(N$6>$I24,1,(N$6-$G24+1)/($I24-$G24+1)))) -> 1 | O24: =IF($G24=0,0,IF(O$6<$G24,0,IF(O$6>$I24,1,(O$6-$G24+1)/($I24-$G24+1)))) -> 1 | P24: =IF($G24=0,0,IF(P$6<$G24,0,IF(P$6>$I24,1,(P$6-$G24+1)/($I24-$G24+1)))) -> 1 | Q24: =IF($G24=0,0,IF(Q$6<$G24,0,IF(Q$6>$I24,1,(Q$6-$G24+1)/($I24-$G24+1)))) -> 1 | R24: =IF($G24=0,0,IF(R$6<$G24,0,IF(R$6>$I24,1,(R$6-$G24+1)/($I24-$G24+1)))) -> 1 | ... BQ24: =IF($G24=0,0,IF(BQ$6<$G24,0,IF(BQ$6>$I24,1,(BQ$6-$G24+1)/($I24-$G24+1)))) -> 1 | BR24: =+AVERAGE(K24:BQ24) -> 1
B25: 3.11 | C25: REUNIONES RIO MATAJUNAY | D25: 0 días | E25: =VLOOKUP(B25,'Cuadro Control'!C21:J1955,8,FALSE) -> 0 | F25: =IFERROR(E25/$E$8,0) -> 0 | G25: 46218 | I25: 46218 | J25: =+INDEX($K25:$BQ25,1,MATCH(I25,$K$6:$BQ$6,1)) -> 1 | K25: =IF($G25=0,0,IF(K$6<$G25,0,IF(K$6>$I25,1,(K$6-$G25+1)/($I25-$G25+1)))) -> 1 | L25: =IF($G25=0,0,IF(L$6<$G25,0,IF(L$6>$I25,1,(L$6-$G25+1)/($I25-$G25+1)))) -> 1 | M25: =IF($G25=0,0,IF(M$6<$G25,0,IF(M$6>$I25,1,(M$6-$G25+1)/($I25-$G25+1)))) -> 1 | N25: =IF($G25=0,0,IF(N$6<$G25,0,IF(N$6>$I25,1,(N$6-$G25+1)/($I25-$G25+1)))) -> 1 | O25: =IF($G25=0,0,IF(O$6<$G25,0,IF(O$6>$I25,1,(O$6-$G25+1)/($I25-$G25+1)))) -> 1 | P25: =IF($G25=0,0,IF(P$6<$G25,0,IF(P$6>$I25,1,(P$6-$G25+1)/($I25-$G25+1)))) -> 1 | Q25: =IF($G25=0,0,IF(Q$6<$G25,0,IF(Q$6>$I25,1,(Q$6-$G25+1)/($I25-$G25+1)))) -> 1 | R25: =IF($G25=0,0,IF(R$6<$G25,0,IF(R$6>$I25,1,(R$6-$G25+1)/($I25-$G25+1)))) -> 1 | ... BQ25: =IF($G25=0,0,IF(BQ$6<$G25,0,IF(BQ$6>$I25,1,(BQ$6-$G25+1)/($I25-$G25+1)))) -> 1 | BR25: =+AVERAGE(K25:BQ25) -> 1
B26: 3.12 | C26: REUNIONES RIO MANNAJUYAY | D26: 0 días | E26: =VLOOKUP(B26,'Cuadro Control'!C22:J1956,8,FALSE) -> 0 | F26: =IFERROR(E26/$E$8,0) -> 0 | G26: 46218 | I26: 46218 | J26: =+INDEX($K26:$BQ26,1,MATCH(I26,$K$6:$BQ$6,1)) -> 1 | K26: =IF($G26=0,0,IF(K$6<$G26,0,IF(K$6>$I26,1,(K$6-$G26+1)/($I26-$G26+1)))) -> 1 | L26: =IF($G26=0,0,IF(L$6<$G26,0,IF(L$6>$I26,1,(L$6-$G26+1)/($I26-$G26+1)))) -> 1 | M26: =IF($G26=0,0,IF(M$6<$G26,0,IF(M$6>$I26,1,(M$6-$G26+1)/($I26-$G26+1)))) -> 1 | N26: =IF($G26=0,0,IF(N$6<$G26,0,IF(N$6>$I26,1,(N$6-$G26+1)/($I26-$G26+1)))) -> 1 | O26: =IF($G26=0,0,IF(O$6<$G26,0,IF(O$6>$I26,1,(O$6-$G26+1)/($I26-$G26+1)))) -> 1 | P26: =IF($G26=0,0,IF(P$6<$G26,0,IF(P$6>$I26,1,(P$6-$G26+1)/($I26-$G26+1)))) -> 1 | Q26: =IF($G26=0,0,IF(Q$6<$G26,0,IF(Q$6>$I26,1,(Q$6-$G26+1)/($I26-$G26+1)))) -> 1 | R26: =IF($G26=0,0,IF(R$6<$G26,0,IF(R$6>$I26,1,(R$6-$G26+1)/($I26-$G26+1)))) -> 1 | ... BQ26: =IF($G26=0,0,IF(BQ$6<$G26,0,IF(BQ$6>$I26,1,(BQ$6-$G26+1)/($I26-$G26+1)))) -> 1 | BR26: =+AVERAGE(K26:BQ26) -> 1
... B28: 3.14 | C28: REUNIONES RIO JAMUCHERRU | D28: 0 días | E28: =VLOOKUP(B28,'Cuadro Control'!C24:J1958,8,FALSE) -> 0 | F28: =IFERROR(E28/$E$8,0) -> 0 | G28: 46252 | I28: 46252 | J28: =+INDEX($K28:$BQ28,1,MATCH(I28,$K$6:$BQ$6,1)) -> 0 | K28: =IF($G28=0,0,IF(K$6<$G28,0,IF(K$6>$I28,1,(K$6-$G28+1)/($I28-$G28+1)))) -> 0 | L28: =IF($G28=0,0,IF(L$6<$G28,0,IF(L$6>$I28,1,(L$6-$G28+1)/($I28-$G28+1)))) -> 0 | M28: =IF($G28=0,0,IF(M$6<$G28,0,IF(M$6>$I28,1,(M$6-$G28+1)/($I28-$G28+1)))) -> 0 | N28: =IF($G28=0,0,IF(N$6<$G28,0,IF(N$6>$I28,1,(N$6-$G28+1)/($I28-$G28+1)))) -> 0 | O28: =IF($G28=0,0,IF(O$6<$G28,0,IF(O$6>$I28,1,(O$6-$G28+1)/($I28-$G28+1)))) -> 0 | P28: =IF($G28=0,0,IF(P$6<$G28,0,IF(P$6>$I28,1,(P$6-$G28+1)/($I28-$G28+1)))) -> 0 | Q28: =IF($G28=0,0,IF(Q$6<$G28,0,IF(Q$6>$I28,1,(Q$6-$G28+1)/($I28-$G28+1)))) -> 1 | R28: =IF($G28=0,0,IF(R$6<$G28,0,IF(R$6>$I28,1,(R$6-$G28+1)/($I28-$G28+1)))) -> 1 | ... BQ28: =IF($G28=0,0,IF(BQ$6<$G28,0,IF(BQ$6>$I28,1,(BQ$6-$G28+1)/($I28-$G28+1)))) -> 1 | BR28: =+AVERAGE(K28:BQ28) -> 0.89830508
B29: 4 | C29: PUBLICACIÓN DE VACANTES/CONTRATACIÓN DE PERSONAL | D29: 20 días | E29: =VLOOKUP(B29,'Cuadro Control'!C25:J1959,8,FALSE) -> 0 | F29: =IFERROR(E29/$E$8,0) -> 0 | G29: 46218 | I29: 46239 | J29: =+INDEX($K29:$BQ29,1,MATCH(I29,$K$6:$BQ$6,1)) -> 0.77272727 | K29: =IF($G29=0,0,IF(K$6<$G29,0,IF(K$6>$I29,1,(K$6-$G29+1)/($I29-$G29+1)))) -> 0.045454545 | L29: =IF($G29=0,0,IF(L$6<$G29,0,IF(L$6>$I29,1,(L$6-$G29+1)/($I29-$G29+1)))) -> 0.13636364 | M29: =IF($G29=0,0,IF(M$6<$G29,0,IF(M$6>$I29,1,(M$6-$G29+1)/($I29-$G29+1)))) -> 0.45454545 | N29: =IF($G29=0,0,IF(N$6<$G29,0,IF(N$6>$I29,1,(N$6-$G29+1)/($I29-$G29+1)))) -> 0.77272727 | O29: =IF($G29=0,0,IF(O$6<$G29,0,IF(O$6>$I29,1,(O$6-$G29+1)/($I29-$G29+1)))) -> 1 | P29: =IF($G29=0,0,IF(P$6<$G29,0,IF(P$6>$I29,1,(P$6-$G29+1)/($I29-$G29+1)))) -> 1 | Q29: =IF($G29=0,0,IF(Q$6<$G29,0,IF(Q$6>$I29,1,(Q$6-$G29+1)/($I29-$G29+1)))) -> 1 | R29: =IF($G29=0,0,IF(R$6<$G29,0,IF(R$6>$I29,1,(R$6-$G29+1)/($I29-$G29+1)))) -> 1 | ... BQ29: =IF($G29=0,0,IF(BQ$6<$G29,0,IF(BQ$6>$I29,1,(BQ$6-$G29+1)/($I29-$G29+1)))) -> 1 | BR29: =+AVERAGE(K29:BQ29) -> 0.95608629
B30: 5 | C30: SUMINISTRO DE MATERIALES | D30: 21 días | E30: =VLOOKUP(B30,'Cuadro Control'!C26:J1960,8,FALSE) -> 0 | F30: =IFERROR(E30/$E$8,0) -> 0 | G30: 46268 | I30: 46283 | J30: =+INDEX($K30:$BQ30,1,MATCH(I30,$K$6:$BQ$6,1)) -> 1 | K30: =IF($G30=0,0,IF(K$6<$G30,0,IF(K$6>$I30,1,(K$6-$G30+1)/($I30-$G30+1)))) -> 0 | L30: =IF($G30=0,0,IF(L$6<$G30,0,IF(L$6>$I30,1,(L$6-$G30+1)/($I30-$G30+1)))) -> 0 | M30: =IF($G30=0,0,IF(M$6<$G30,0,IF(M$6>$I30,1,(M$6-$G30+1)/($I30-$G30+1)))) -> 0 | N30: =IF($G30=0,0,IF(N$6<$G30,0,IF(N$6>$I30,1,(N$6-$G30+1)/($I30-$G30+1)))) -> 0 | O30: =IF($G30=0,0,IF(O$6<$G30,0,IF(O$6>$I30,1,(O$6-$G30+1)/($I30-$G30+1)))) -> 0 | P30: =IF($G30=0,0,IF(P$6<$G30,0,IF(P$6>$I30,1,(P$6-$G30+1)/($I30-$G30+1)))) -> 0 | Q30: =IF($G30=0,0,IF(Q$6<$G30,0,IF(Q$6>$I30,1,(Q$6-$G30+1)/($I30-$G30+1)))) -> 0 | R30: =IF($G30=0,0,IF(R$6<$G30,0,IF(R$6>$I30,1,(R$6-$G30+1)/($I30-$G30+1)))) -> 0 | ... BQ30: =IF($G30=0,0,IF(BQ$6<$G30,0,IF(BQ$6>$I30,1,(BQ$6-$G30+1)/($I30-$G30+1)))) -> 1 | BR30: =+AVERAGE(K30:BQ30) -> 0.84216102
B31: 5.1 | C31: SUMINISTRO DE MATERIALES CIVILES: ANCHOR CAGE (CLIENTE) | D31: 14 días | E31: =VLOOKUP(B31,'Cuadro Control'!C27:J1961,8,FALSE) -> 0 | F31: =IFERROR(E31/$E$30,0) -> 0 | G31: 46268 | I31: 46283 | J31: =+INDEX($K31:$BQ31,1,MATCH(I31,$K$6:$BQ$6,1)) -> 1 | K31: =IF($G31=0,0,IF(K$6<$G31,0,IF(K$6>$I31,1,(K$6-$G31+1)/($I31-$G31+1)))) -> 0 | L31: =IF($G31=0,0,IF(L$6<$G31,0,IF(L$6>$I31,1,(L$6-$G31+1)/($I31-$G31+1)))) -> 0 | M31: =IF($G31=0,0,IF(M$6<$G31,0,IF(M$6>$I31,1,(M$6-$G31+1)/($I31-$G31+1)))) -> 0 | N31: =IF($G31=0,0,IF(N$6<$G31,0,IF(N$6>$I31,1,(N$6-$G31+1)/($I31-$G31+1)))) -> 0 | O31: =IF($G31=0,0,IF(O$6<$G31,0,IF(O$6>$I31,1,(O$6-$G31+1)/($I31-$G31+1)))) -> 0 | P31: =IF($G31=0,0,IF(P$6<$G31,0,IF(P$6>$I31,1,(P$6-$G31+1)/($I31-$G31+1)))) -> 0 | Q31: =IF($G31=0,0,IF(Q$6<$G31,0,IF(Q$6>$I31,1,(Q$6-$G31+1)/($I31-$G31+1)))) -> 0 | R31: =IF($G31=0,0,IF(R$6<$G31,0,IF(R$6>$I31,1,(R$6-$G31+1)/($I31-$G31+1)))) -> 0 | ... BQ31: =IF($G31=0,0,IF(BQ$6<$G31,0,IF(BQ$6>$I31,1,(BQ$6-$G31+1)/($I31-$G31+1)))) -> 1 | BR31: =+AVERAGE(K31:BQ31) -> 0.84216102
B32: 5.2 | C32: SUMINISTRO DE MATERIALES CIVILES: ACEROS DE REFUERSO | D32: 7 días | E32: =VLOOKUP(B32,'Cuadro Control'!C28:J1962,8,FALSE) -> 0 | F32: =IFERROR(E32/$E$30,0) -> 0 | G32: 46268 | I32: 46283 | J32: =+INDEX($K32:$BQ32,1,MATCH(I32,$K$6:$BQ$6,1)) -> 1 | K32: =IF($G32=0,0,IF(K$6<$G32,0,IF(K$6>$I32,1,(K$6-$G32+1)/($I32-$G32+1)))) -> 0 | L32: =IF($G32=0,0,IF(L$6<$G32,0,IF(L$6>$I32,1,(L$6-$G32+1)/($I32-$G32+1)))) -> 0 | M32: =IF($G32=0,0,IF(M$6<$G32,0,IF(M$6>$I32,1,(M$6-$G32+1)/($I32-$G32+1)))) -> 0 | N32: =IF($G32=0,0,IF(N$6<$G32,0,IF(N$6>$I32,1,(N$6-$G32+1)/($I32-$G32+1)))) -> 0 | O32: =IF($G32=0,0,IF(O$6<$G32,0,IF(O$6>$I32,1,(O$6-$G32+1)/($I32-$G32+1)))) -> 0 | P32: =IF($G32=0,0,IF(P$6<$G32,0,IF(P$6>$I32,1,(P$6-$G32+1)/($I32-$G32+1)))) -> 0 | Q32: =IF($G32=0,0,IF(Q$6<$G32,0,IF(Q$6>$I32,1,(Q$6-$G32+1)/($I32-$G32+1)))) -> 0 | R32: =IF($G32=0,0,IF(R$6<$G32,0,IF(R$6>$I32,1,(R$6-$G32+1)/($I32-$G32+1)))) -> 0 | ... BQ32: =IF($G32=0,0,IF(BQ$6<$G32,0,IF(BQ$6>$I32,1,(BQ$6-$G32+1)/($I32-$G32+1)))) -> 1 | BR32: =+AVERAGE(K32:BQ32) -> 0.84216102
B33: 6 | C33: HITO 2: INICIO DE ACTIVIDADES EN CAMPO | D33: 0 días | E33: =VLOOKUP(B33,'Cuadro Control'!C29:J1963,8,FALSE) -> 0 | F33: =IFERROR(E33/$E$8,0) -> 0 | G33: 46239 | I33: 46239 | J33: =+INDEX($K33:$BQ33,1,MATCH(I33,$K$6:$BQ$6,1)) -> 0 | K33: =IF($G33=0,0,IF(K$6<$G33,0,IF(K$6>$I33,1,(K$6-$G33+1)/($I33-$G33+1)))) -> 0 | L33: =IF($G33=0,0,IF(L$6<$G33,0,IF(L$6>$I33,1,(L$6-$G33+1)/($I33-$G33+1)))) -> 0 | M33: =IF($G33=0,0,IF(M$6<$G33,0,IF(M$6>$I33,1,(M$6-$G33+1)/($I33-$G33+1)))) -> 0 | N33: =IF($G33=0,0,IF(N$6<$G33,0,IF(N$6>$I33,1,(N$6-$G33+1)/($I33-$G33+1)))) -> 0 | O33: =IF($G33=0,0,IF(O$6<$G33,0,IF(O$6>$I33,1,(O$6-$G33+1)/($I33-$G33+1)))) -> 1 | P33: =IF($G33=0,0,IF(P$6<$G33,0,IF(P$6>$I33,1,(P$6-$G33+1)/($I33-$G33+1)))) -> 1 | Q33: =IF($G33=0,0,IF(Q$6<$G33,0,IF(Q$6>$I33,1,(Q$6-$G33+1)/($I33-$G33+1)))) -> 1 | R33: =IF($G33=0,0,IF(R$6<$G33,0,IF(R$6>$I33,1,(R$6-$G33+1)/($I33-$G33+1)))) -> 1 | ... BQ33: =IF($G33=0,0,IF(BQ$6<$G33,0,IF(BQ$6>$I33,1,(BQ$6-$G33+1)/($I33-$G33+1)))) -> 1 | BR33: =+AVERAGE(K33:BQ33) -> 0.93220339
B34: 7 | C34: PISCINA INDUSTRIAL | D34: 32 días | E34: =SUM(E35:E38) -> 4.6179078e+08 | F34: =IFERROR(E34/$E$8,0) -> 0.0022153966 | G34: 46268 | I34: 46302 | J34: =+INDEX($K34:$BQ34,1,MATCH(I34,$K$6:$BQ$6,1)) -> 0.44444444 | K34: =SUMPRODUCT($F35:$F38,K35:K38) -> 0 | L34: =SUMPRODUCT($F35:$F38,L35:L38) -> 0 | M34: =SUMPRODUCT($F35:$F38,M35:M38) -> 0 | N34: =SUMPRODUCT($F35:$F38,N35:N38) -> 0 | O34: =SUMPRODUCT($F35:$F38,O35:O38) -> 0 | P34: =SUMPRODUCT($F35:$F38,P35:P38) -> 0 | Q34: =SUMPRODUCT($F35:$F38,Q35:Q38) -> 0 | R34: =SUMPRODUCT($F35:$F38,R35:R38) -> 0 | ... BQ34: =SUMPRODUCT($F35:$F38,BQ35:BQ38) -> 1 | BR34: =+AVERAGE(K34:BQ34) -> 0.78719397
B35: 7.1 | C35: MOVIMIENTO DE TIERRAS Y RECONFORMACION PISCINA INDUSTRIAL | D35: 14 días | E35: =VLOOKUP(B35,'Cuadro Control'!C31:J1965,8,FALSE) -> 0 | F35: =IFERROR(E35/$E$34,0) -> 0 | G35: 46268 | I35: 46283 | J35: =+INDEX($K35:$BQ35,1,MATCH(I35,$K$6:$BQ$6,1)) -> 1 | K35: =IF($G35=0,0,IF(K$6<$G35,0,IF(K$6>$I35,1,(K$6-$G35+1)/($I35-$G35+1)))) -> 0 | L35: =IF($G35=0,0,IF(L$6<$G35,0,IF(L$6>$I35,1,(L$6-$G35+1)/($I35-$G35+1)))) -> 0 | M35: =IF($G35=0,0,IF(M$6<$G35,0,IF(M$6>$I35,1,(M$6-$G35+1)/($I35-$G35+1)))) -> 0 | N35: =IF($G35=0,0,IF(N$6<$G35,0,IF(N$6>$I35,1,(N$6-$G35+1)/($I35-$G35+1)))) -> 0 | O35: =IF($G35=0,0,IF(O$6<$G35,0,IF(O$6>$I35,1,(O$6-$G35+1)/($I35-$G35+1)))) -> 0 | P35: =IF($G35=0,0,IF(P$6<$G35,0,IF(P$6>$I35,1,(P$6-$G35+1)/($I35-$G35+1)))) -> 0 | Q35: =IF($G35=0,0,IF(Q$6<$G35,0,IF(Q$6>$I35,1,(Q$6-$G35+1)/($I35-$G35+1)))) -> 0 | R35: =IF($G35=0,0,IF(R$6<$G35,0,IF(R$6>$I35,1,(R$6-$G35+1)/($I35-$G35+1)))) -> 0 | ... BQ35: =IF($G35=0,0,IF(BQ$6<$G35,0,IF(BQ$6>$I35,1,(BQ$6-$G35+1)/($I35-$G35+1)))) -> 1 | BR35: =+AVERAGE(K35:BQ35) -> 0.84216102
B36: 7.2 | C36: INSTALACION DE GEOMEMBRANA PISCINA INDUSTRIAL | D36: 10 días | E36: =VLOOKUP(B36,'Cuadro Control'!C32:J1966,8,FALSE) -> 0 | F36: =IFERROR(E36/$E$34,0) -> 0 | G36: 46283 | I36: 46294 | J36: =+INDEX($K36:$BQ36,1,MATCH(I36,$K$6:$BQ$6,1)) -> 0.66666667 | K36: =IF($G36=0,0,IF(K$6<$G36,0,IF(K$6>$I36,1,(K$6-$G36+1)/($I36-$G36+1)))) -> 0 | L36: =IF($G36=0,0,IF(L$6<$G36,0,IF(L$6>$I36,1,(L$6-$G36+1)/($I36-$G36+1)))) -> 0 | M36: =IF($G36=0,0,IF(M$6<$G36,0,IF(M$6>$I36,1,(M$6-$G36+1)/($I36-$G36+1)))) -> 0 | N36: =IF($G36=0,0,IF(N$6<$G36,0,IF(N$6>$I36,1,(N$6-$G36+1)/($I36-$G36+1)))) -> 0 | O36: =IF($G36=0,0,IF(O$6<$G36,0,IF(O$6>$I36,1,(O$6-$G36+1)/($I36-$G36+1)))) -> 0 | P36: =IF($G36=0,0,IF(P$6<$G36,0,IF(P$6>$I36,1,(P$6-$G36+1)/($I36-$G36+1)))) -> 0 | Q36: =IF($G36=0,0,IF(Q$6<$G36,0,IF(Q$6>$I36,1,(Q$6-$G36+1)/($I36-$G36+1)))) -> 0 | R36: =IF($G36=0,0,IF(R$6<$G36,0,IF(R$6>$I36,1,(R$6-$G36+1)/($I36-$G36+1)))) -> 0 | ... BQ36: =IF($G36=0,0,IF(BQ$6<$G36,0,IF(BQ$6>$I36,1,(BQ$6-$G36+1)/($I36-$G36+1)))) -> 1 | BR36: =+AVERAGE(K36:BQ36) -> 0.80932203
B37: 7.3 | C37: CONSTRUCCION DE CERRAMIENTO EN ALAMBRE DE PUA PISCINA INDUSTRIAL | D37: 14 días | E37: =VLOOKUP(B37,'Cuadro Control'!C33:J1967,8,FALSE) -> 0 | F37: =IFERROR(E37/$E$34,0) -> 0 | G37: 46272 | I37: 46286 | J37: =+INDEX($K37:$BQ37,1,MATCH(I37,$K$6:$BQ$6,1)) -> 0.8 | K37: =IF($G37=0,0,IF(K$6<$G37,0,IF(K$6>$I37,1,(K$6-$G37+1)/($I37-$G37+1)))) -> 0 | L37: =IF($G37=0,0,IF(L$6<$G37,0,IF(L$6>$I37,1,(L$6-$G37+1)/($I37-$G37+1)))) -> 0 | M37: =IF($G37=0,0,IF(M$6<$G37,0,IF(M$6>$I37,1,(M$6-$G37+1)/($I37-$G37+1)))) -> 0 | N37: =IF($G37=0,0,IF(N$6<$G37,0,IF(N$6>$I37,1,(N$6-$G37+1)/($I37-$G37+1)))) -> 0 | O37: =IF($G37=0,0,IF(O$6<$G37,0,IF(O$6>$I37,1,(O$6-$G37+1)/($I37-$G37+1)))) -> 0 | P37: =IF($G37=0,0,IF(P$6<$G37,0,IF(P$6>$I37,1,(P$6-$G37+1)/($I37-$G37+1)))) -> 0 | Q37: =IF($G37=0,0,IF(Q$6<$G37,0,IF(Q$6>$I37,1,(Q$6-$G37+1)/($I37-$G37+1)))) -> 0 | R37: =IF($G37=0,0,IF(R$6<$G37,0,IF(R$6>$I37,1,(R$6-$G37+1)/($I37-$G37+1)))) -> 0 | ... BQ37: =IF($G37=0,0,IF(BQ$6<$G37,0,IF(BQ$6>$I37,1,(BQ$6-$G37+1)/($I37-$G37+1)))) -> 1 | BR37: =+AVERAGE(K37:BQ37) -> 0.83276836
B38: 7.4 | C38: CONSTRUCCION CUNETA PERIMETRAL PISCINA INDUSTRIAL | D38: 8 días | E38: =VLOOKUP(B38,'Cuadro Control'!C34:J1968,8,FALSE) -> 4.6179078e+08 | F38: =IFERROR(E38/$E$34,0) -> 1 | G38: 46294 | I38: 46302 | J38: =+INDEX($K38:$BQ38,1,MATCH(I38,$K$6:$BQ$6,1)) -> 0.44444444 | K38: =IF($G38=0,0,IF(K$6<$G38,0,IF(K$6>$I38,1,(K$6-$G38+1)/($I38-$G38+1)))) -> 0 | L38: =IF($G38=0,0,IF(L$6<$G38,0,IF(L$6>$I38,1,(L$6-$G38+1)/($I38-$G38+1)))) -> 0 | M38: =IF($G38=0,0,IF(M$6<$G38,0,IF(M$6>$I38,1,(M$6-$G38+1)/($I38-$G38+1)))) -> 0 | N38: =IF($G38=0,0,IF(N$6<$G38,0,IF(N$6>$I38,1,(N$6-$G38+1)/($I38-$G38+1)))) -> 0 | O38: =IF($G38=0,0,IF(O$6<$G38,0,IF(O$6>$I38,1,(O$6-$G38+1)/($I38-$G38+1)))) -> 0 | P38: =IF($G38=0,0,IF(P$6<$G38,0,IF(P$6>$I38,1,(P$6-$G38+1)/($I38-$G38+1)))) -> 0 | Q38: =IF($G38=0,0,IF(Q$6<$G38,0,IF(Q$6>$I38,1,(Q$6-$G38+1)/($I38-$G38+1)))) -> 0 | R38: =IF($G38=0,0,IF(R$6<$G38,0,IF(R$6>$I38,1,(R$6-$G38+1)/($I38-$G38+1)))) -> 0 | ... BQ38: =IF($G38=0,0,IF(BQ$6<$G38,0,IF(BQ$6>$I38,1,(BQ$6-$G38+1)/($I38-$G38+1)))) -> 1 | BR38: =+AVERAGE(K38:BQ38) -> 0.78719397
B39: 8 | C39: ZONAS DE CAMPAMENTOS - FAENAS | D39: 305 días | E39: =SUM(E40:E43) -> 8.3636378e+09 | F39: =IFERROR(E39/$E$8,0) -> 0.040123744 | G39: 46249 | I39: 46585 | J39: =+INDEX($K39:$BQ39,1,MATCH(I39,$K$6:$BQ$6,1)) -> 0.99682739 | K39: =SUMPRODUCT($F40:$F43,K40:K43) -> 0 | L39: =SUMPRODUCT($F40:$F43,L40:L43) -> 0 | M39: =SUMPRODUCT($F40:$F43,M40:M43) -> 0 | N39: =SUMPRODUCT($F40:$F43,N40:N43) -> 0 | O39: =SUMPRODUCT($F40:$F43,O40:O43) -> 0 | P39: =SUMPRODUCT($F40:$F43,P40:P43) -> 0 | Q39: =SUMPRODUCT($F40:$F43,Q40:Q43) -> 0.00025091375 | R39: =SUMPRODUCT($F40:$F43,R40:R43) -> 0.00069836949 | ... BQ39: =SUMPRODUCT($F40:$F43,BQ40:BQ43) -> 1 | BR39: =+AVERAGE(K39:BQ39) -> 0.47234668
B40: 8.1 | C40: CONFORMACIÓN DEL AREA ZONAS DE CAMPAMENTOS - FAENAS | D40: 14 días | E40: =VLOOKUP(B40,'Cuadro Control'!C36:J1970,8,FALSE) -> 8694000 | F40: =IFERROR(E40/$E$39,0) -> 0.0010394998 | G40: 46249 | I40: 46277 | J40: =+INDEX($K40:$BQ40,1,MATCH(I40,$K$6:$BQ$6,1)) -> 0.96551724 | K40: =IF($G40=0,0,IF(K$6<$G40,0,IF(K$6>$I40,1,(K$6-$G40+1)/($I40-$G40+1)))) -> 0 | L40: =IF($G40=0,0,IF(L$6<$G40,0,IF(L$6>$I40,1,(L$6-$G40+1)/($I40-$G40+1)))) -> 0 | M40: =IF($G40=0,0,IF(M$6<$G40,0,IF(M$6>$I40,1,(M$6-$G40+1)/($I40-$G40+1)))) -> 0 | N40: =IF($G40=0,0,IF(N$6<$G40,0,IF(N$6>$I40,1,(N$6-$G40+1)/($I40-$G40+1)))) -> 0 | O40: =IF($G40=0,0,IF(O$6<$G40,0,IF(O$6>$I40,1,(O$6-$G40+1)/($I40-$G40+1)))) -> 0 | P40: =IF($G40=0,0,IF(P$6<$G40,0,IF(P$6>$I40,1,(P$6-$G40+1)/($I40-$G40+1)))) -> 0 | Q40: =IF($G40=0,0,IF(Q$6<$G40,0,IF(Q$6>$I40,1,(Q$6-$G40+1)/($I40-$G40+1)))) -> 0.24137931 | R40: =IF($G40=0,0,IF(R$6<$G40,0,IF(R$6>$I40,1,(R$6-$G40+1)/($I40-$G40+1)))) -> 0.48275862 | ... BQ40: =IF($G40=0,0,IF(BQ$6<$G40,0,IF(BQ$6>$I40,1,(BQ$6-$G40+1)/($I40-$G40+1)))) -> 1 | BR40: =+AVERAGE(K40:BQ40) -> 0.87142022
B41: 8.2 | C41: INSTALACIÓN DE CONTENEDORES Y EQUIPOS ZONAS DE CAMPAMENTOS - FAENAS | D41: 10 días | E41: =VLOOKUP(B41,'Cuadro Control'!C37:J1971,8,FALSE) -> 5260179.1 | F41: =IFERROR(E41/$E$39,0) -> 0.00062893435 | G41: 46258 | I41: 46273 | J41: =+INDEX($K41:$BQ41,1,MATCH(I41,$K$6:$BQ$6,1)) -> 0.75 | K41: =IF($G41=0,0,IF(K$6<$G41,0,IF(K$6>$I41,1,(K$6-$G41+1)/($I41-$G41+1)))) -> 0 | L41: =IF($G41=0,0,IF(L$6<$G41,0,IF(L$6>$I41,1,(L$6-$G41+1)/($I41-$G41+1)))) -> 0 | M41: =IF($G41=0,0,IF(M$6<$G41,0,IF(M$6>$I41,1,(M$6-$G41+1)/($I41-$G41+1)))) -> 0 | N41: =IF($G41=0,0,IF(N$6<$G41,0,IF(N$6>$I41,1,(N$6-$G41+1)/($I41-$G41+1)))) -> 0 | O41: =IF($G41=0,0,IF(O$6<$G41,0,IF(O$6>$I41,1,(O$6-$G41+1)/($I41-$G41+1)))) -> 0 | P41: =IF($G41=0,0,IF(P$6<$G41,0,IF(P$6>$I41,1,(P$6-$G41+1)/($I41-$G41+1)))) -> 0 | Q41: =IF($G41=0,0,IF(Q$6<$G41,0,IF(Q$6>$I41,1,(Q$6-$G41+1)/($I41-$G41+1)))) -> 0 | R41: =IF($G41=0,0,IF(R$6<$G41,0,IF(R$6>$I41,1,(R$6-$G41+1)/($I41-$G41+1)))) -> 0.3125 | ... BQ41: =IF($G41=0,0,IF(BQ$6<$G41,0,IF(BQ$6>$I41,1,(BQ$6-$G41+1)/($I41-$G41+1)))) -> 1 | BR41: =+AVERAGE(K41:BQ41) -> 0.8654661
B42: 8.3 | C42: INSTALACIÓN DE LAS FACILIDADES ELECTRICAS E HIDRÚALICAS DE LOS CONTENEDORES ZONAS DE CAMPAMENTOS - FAENAS | D42: 8 días | E42: =VLOOKUP(B42,'Cuadro Control'!C38:J1972,8,FALSE) -> 70893128 | F42: =IFERROR(E42/$E$39,0) -> 0.0084763508 | G42: 46273 | I42: 46281 | J42: =+INDEX($K42:$BQ42,1,MATCH(I42,$K$6:$BQ$6,1)) -> 0.44444444 | K42: =IF($G42=0,0,IF(K$6<$G42,0,IF(K$6>$I42,1,(K$6-$G42+1)/($I42-$G42+1)))) -> 0 | L42: =IF($G42=0,0,IF(L$6<$G42,0,IF(L$6>$I42,1,(L$6-$G42+1)/($I42-$G42+1)))) -> 0 | M42: =IF($G42=0,0,IF(M$6<$G42,0,IF(M$6>$I42,1,(M$6-$G42+1)/($I42-$G42+1)))) -> 0 | N42: =IF($G42=0,0,IF(N$6<$G42,0,IF(N$6>$I42,1,(N$6-$G42+1)/($I42-$G42+1)))) -> 0 | O42: =IF($G42=0,0,IF(O$6<$G42,0,IF(O$6>$I42,1,(O$6-$G42+1)/($I42-$G42+1)))) -> 0 | P42: =IF($G42=0,0,IF(P$6<$G42,0,IF(P$6>$I42,1,(P$6-$G42+1)/($I42-$G42+1)))) -> 0 | Q42: =IF($G42=0,0,IF(Q$6<$G42,0,IF(Q$6>$I42,1,(Q$6-$G42+1)/($I42-$G42+1)))) -> 0 | R42: =IF($G42=0,0,IF(R$6<$G42,0,IF(R$6>$I42,1,(R$6-$G42+1)/($I42-$G42+1)))) -> 0 | ... BQ42: =IF($G42=0,0,IF(BQ$6<$G42,0,IF(BQ$6>$I42,1,(BQ$6-$G42+1)/($I42-$G42+1)))) -> 1 | BR42: =+AVERAGE(K42:BQ42) -> 0.83804143
B43: 8.4 | C43: ADMINISTRACIÓN Y MANTENIMIENTO DE CAMPAMENTOS | D43: 280 días | E43: =VLOOKUP(B43,'Cuadro Control'!C40:J1973,8,FALSE) -> 8.2787905e+09 | F43: =IFERROR(E43/$E$39,0) -> 0.98985521 | G43: 46274 | I43: 46585 | J43: =+INDEX($K43:$BQ43,1,MATCH(I43,$K$6:$BQ$6,1)) -> 0.99679487 | K43: =IF($G43=0,0,IF(K$6<$G43,0,IF(K$6>$I43,1,(K$6-$G43+1)/($I43-$G43+1)))) -> 0 | L43: =IF($G43=0,0,IF(L$6<$G43,0,IF(L$6>$I43,1,(L$6-$G43+1)/($I43-$G43+1)))) -> 0 | M43: =IF($G43=0,0,IF(M$6<$G43,0,IF(M$6>$I43,1,(M$6-$G43+1)/($I43-$G43+1)))) -> 0 | N43: =IF($G43=0,0,IF(N$6<$G43,0,IF(N$6>$I43,1,(N$6-$G43+1)/($I43-$G43+1)))) -> 0 | O43: =IF($G43=0,0,IF(O$6<$G43,0,IF(O$6>$I43,1,(O$6-$G43+1)/($I43-$G43+1)))) -> 0 | P43: =IF($G43=0,0,IF(P$6<$G43,0,IF(P$6>$I43,1,(P$6-$G43+1)/($I43-$G43+1)))) -> 0 | Q43: =IF($G43=0,0,IF(Q$6<$G43,0,IF(Q$6>$I43,1,(Q$6-$G43+1)/($I43-$G43+1)))) -> 0 | R43: =IF($G43=0,0,IF(R$6<$G43,0,IF(R$6>$I43,1,(R$6-$G43+1)/($I43-$G43+1)))) -> 0 | ... BQ43: =IF($G43=0,0,IF(BQ$6<$G43,0,IF(BQ$6>$I43,1,(BQ$6-$G43+1)/($I43-$G43+1)))) -> 1 | BR43: =+AVERAGE(K43:BQ43) -> 0.46854628
B44: 9 | C44: EJECUCIÓN DE ACTIVIDADES DE CIMENTACIONES EXISTENTES | D44: 101 días | E44: =+E45+E54+E63+E72+E81+E90+E99 -> 6.4606628e+09 | F44: =IFERROR(E44/$E$8,0) -> 0.030994405 | G44: 46228 | I44: 46360 | J44: =+INDEX($K44:$BQ44,1,MATCH(I44,$K$6:$BQ$6,1)) -> 1 | K44: =$F45*K45+$F54*K54+$F63*K63+$F72*K72+$F81*K81+$F90*K90+$F99*K99 -> 0 | L44: =$F45*L45+$F54*L54+$F63*L63+$F72*L72+$F81*L81+$F90*L90+$F99*L99 -> 0 | M44: =$F45*M45+$F54*M54+$F63*M63+$F72*M72+$F81*M81+$F90*M90+$F99*M99 -> 0 | N44: =$F45*N45+$F54*N54+$F63*N63+$F72*N72+$F81*N81+$F90*N90+$F99*N99 -> 0.08877551 | O44: =$F45*O45+$F54*O54+$F63*O63+$F72*O72+$F81*O81+$F90*O90+$F99*O99 -> 0.18 | P44: =$F45*P45+$F54*P54+$F63*P63+$F72*P72+$F81*P81+$F90*P90+$F99*P99 -> 0.18857143 | Q44: =$F45*Q45+$F54*Q54+$F63*Q63+$F72*Q72+$F81*Q81+$F90*Q90+$F99*Q99 -> 0.18857143 | R44: =$F45*R45+$F54*R54+$F63*R63+$F72*R72+$F81*R81+$F90*R90+$F99*R99 -> 0.20880952 | ... BQ44: =$F45*BQ45+$F54*BQ54+$F63*BQ63+$F72*BQ72+$F81*BQ81+$F90*BQ90+$F99*BQ99 -> 1 | BR44: =+AVERAGE(K44:BQ44) -> 0.79156797
B45: 9.1 | C45: RECALCE 1 WP44 | D45: 18 | E45: =SUM(E46:E53) -> 9.2295182e+08 | F45: =IFERROR(E45/$E$44,0) -> 0.14285714 | G45: 46268 | I45: 46329 | J45: =+INDEX($K45:$BQ45,1,MATCH(I45,$K$6:$BQ$6,1)) -> 0.96 | K45: =SUMPRODUCT($F46:$F53,K46:K53) -> 0 | L45: =SUMPRODUCT($F46:$F53,L46:L53) -> 0 | M45: =SUMPRODUCT($F46:$F53,M46:M53) -> 0 | N45: =SUMPRODUCT($F46:$F53,N46:N53) -> 0 | O45: =SUMPRODUCT($F46:$F53,O46:O53) -> 0 | P45: =SUMPRODUCT($F46:$F53,P46:P53) -> 0 | Q45: =SUMPRODUCT($F46:$F53,Q46:Q53) -> 0 | R45: =SUMPRODUCT($F46:$F53,R46:R53) -> 0 | ... BQ45: =SUMPRODUCT($F46:$F53,BQ46:BQ53) -> 1 | BR45: =+AVERAGE(K45:BQ45) -> 0.78731073
A46: REPLANTEO | B46: 9.1.1 | C46: LOCALIZACIÓN DEL ACERO WP44 | D46: 1 | E46: =VLOOKUP(B46,'Cuadro Control'!C46:J1976,8,FALSE) -> 90662605 | F46: 0.1 | G46: 46268 | I46: 46270 | J46: =+INDEX($K46:$BQ46,1,MATCH(I46,$K$6:$BQ$6,1)) -> 0.66666667 | K46: =IF($G46=0,0,IF(K$6<$G46,0,IF(K$6>$I46,1,(K$6-$G46+1)/($I46-$G46+1)))) -> 0 | L46: =IF($G46=0,0,IF(L$6<$G46,0,IF(L$6>$I46,1,(L$6-$G46+1)/($I46-$G46+1)))) -> 0 | M46: =IF($G46=0,0,IF(M$6<$G46,0,IF(M$6>$I46,1,(M$6-$G46+1)/($I46-$G46+1)))) -> 0 | N46: =IF($G46=0,0,IF(N$6<$G46,0,IF(N$6>$I46,1,(N$6-$G46+1)/($I46-$G46+1)))) -> 0 | O46: =IF($G46=0,0,IF(O$6<$G46,0,IF(O$6>$I46,1,(O$6-$G46+1)/($I46-$G46+1)))) -> 0 | P46: =IF($G46=0,0,IF(P$6<$G46,0,IF(P$6>$I46,1,(P$6-$G46+1)/($I46-$G46+1)))) -> 0 | Q46: =IF($G46=0,0,IF(Q$6<$G46,0,IF(Q$6>$I46,1,(Q$6-$G46+1)/($I46-$G46+1)))) -> 0 | R46: =IF($G46=0,0,IF(R$6<$G46,0,IF(R$6>$I46,1,(R$6-$G46+1)/($I46-$G46+1)))) -> 0 | ... BQ46: =IF($G46=0,0,IF(BQ$6<$G46,0,IF(BQ$6>$I46,1,(BQ$6-$G46+1)/($I46-$G46+1)))) -> 1 | BR46: =+AVERAGE(K46:BQ46) -> 0.85875706
A47: EXCAVACION | B47: 9.1.2 | C47: PERFORACION, ESCARIFICADO Y LIMPIEZA DEL RECUBRIMIENTO WP44 | D47: 4 | E47: =VLOOKUP(B47,'Cuadro Control'!C47:J1977,8,FALSE) -> 2.3077754e+08 | F47: 0.25 | G47: 46270 | I47: 46275 | J47: =+INDEX($K47:$BQ47,1,MATCH(I47,$K$6:$BQ$6,1)) -> 0 | K47: =IF($G47=0,0,IF(K$6<$G47,0,IF(K$6>$I47,1,(K$6-$G47+1)/($I47-$G47+1)))) -> 0 | L47: =IF($G47=0,0,IF(L$6<$G47,0,IF(L$6>$I47,1,(L$6-$G47+1)/($I47-$G47+1)))) -> 0 | M47: =IF($G47=0,0,IF(M$6<$G47,0,IF(M$6>$I47,1,(M$6-$G47+1)/($I47-$G47+1)))) -> 0 | N47: =IF($G47=0,0,IF(N$6<$G47,0,IF(N$6>$I47,1,(N$6-$G47+1)/($I47-$G47+1)))) -> 0 | O47: =IF($G47=0,0,IF(O$6<$G47,0,IF(O$6>$I47,1,(O$6-$G47+1)/($I47-$G47+1)))) -> 0 | P47: =IF($G47=0,0,IF(P$6<$G47,0,IF(P$6>$I47,1,(P$6-$G47+1)/($I47-$G47+1)))) -> 0 | Q47: =IF($G47=0,0,IF(Q$6<$G47,0,IF(Q$6>$I47,1,(Q$6-$G47+1)/($I47-$G47+1)))) -> 0 | R47: =IF($G47=0,0,IF(R$6<$G47,0,IF(R$6>$I47,1,(R$6-$G47+1)/($I47-$G47+1)))) -> 0 | ... BQ47: =IF($G47=0,0,IF(BQ$6<$G47,0,IF(BQ$6>$I47,1,(BQ$6-$G47+1)/($I47-$G47+1)))) -> 1 | BR47: =+AVERAGE(K47:BQ47) -> 0.84745763
B48: 9.1.3 | C48: CORTE Y FIGURADO DE ACERO WP44 | D48: 2 | E48: =VLOOKUP(B48,'Cuadro Control'!C48:J1978,8,FALSE) -> 82420550 | F48: 0.09 | G48: 46283 | H48: 46283 | I48: 46287 | J48: =+INDEX($K48:$BQ48,1,MATCH(I48,$K$6:$BQ$6,1)) -> 0.2 | K48: =IF($G48=0,0,IF(K$6<$G48,0,IF(K$6>$I48,1,(K$6-$G48+1)/($I48-$G48+1)))) -> 0 | L48: =IF($G48=0,0,IF(L$6<$G48,0,IF(L$6>$I48,1,(L$6-$G48+1)/($I48-$G48+1)))) -> 0 | M48: =IF($G48=0,0,IF(M$6<$G48,0,IF(M$6>$I48,1,(M$6-$G48+1)/($I48-$G48+1)))) -> 0 | N48: =IF($G48=0,0,IF(N$6<$G48,0,IF(N$6>$I48,1,(N$6-$G48+1)/($I48-$G48+1)))) -> 0 | O48: =IF($G48=0,0,IF(O$6<$G48,0,IF(O$6>$I48,1,(O$6-$G48+1)/($I48-$G48+1)))) -> 0 | P48: =IF($G48=0,0,IF(P$6<$G48,0,IF(P$6>$I48,1,(P$6-$G48+1)/($I48-$G48+1)))) -> 0 | Q48: =IF($G48=0,0,IF(Q$6<$G48,0,IF(Q$6>$I48,1,(Q$6-$G48+1)/($I48-$G48+1)))) -> 0 | R48: =IF($G48=0,0,IF(R$6<$G48,0,IF(R$6>$I48,1,(R$6-$G48+1)/($I48-$G48+1)))) -> 0 | ... BQ48: =IF($G48=0,0,IF(BQ$6<$G48,0,IF(BQ$6>$I48,1,(BQ$6-$G48+1)/($I48-$G48+1)))) -> 1 | BR48: =+AVERAGE(K48:BQ48) -> 0.81694915
A49: ACERO | B49: 9.1.4 | C49: APLICACIÓN DE EPOXICO Y FIJACIÓN DEL ACERO WP44 | D49: 4 | E49: =VLOOKUP(B49,'Cuadro Control'!C49:J1979,8,FALSE) -> 2.3077754e+08 | F49: 0.25 | G49: 46311 | I49: 46316 | J49: =+INDEX($K49:$BQ49,1,MATCH(I49,$K$6:$BQ$6,1)) -> 0.16666667 | K49: =IF($G49=0,0,IF(K$6<$G49,0,IF(K$6>$I49,1,(K$6-$G49+1)/($I49-$G49+1)))) -> 0 | L49: =IF($G49=0,0,IF(L$6<$G49,0,IF(L$6>$I49,1,(L$6-$G49+1)/($I49-$G49+1)))) -> 0 | M49: =IF($G49=0,0,IF(M$6<$G49,0,IF(M$6>$I49,1,(M$6-$G49+1)/($I49-$G49+1)))) -> 0 | N49: =IF($G49=0,0,IF(N$6<$G49,0,IF(N$6>$I49,1,(N$6-$G49+1)/($I49-$G49+1)))) -> 0 | O49: =IF($G49=0,0,IF(O$6<$G49,0,IF(O$6>$I49,1,(O$6-$G49+1)/($I49-$G49+1)))) -> 0 | P49: =IF($G49=0,0,IF(P$6<$G49,0,IF(P$6>$I49,1,(P$6-$G49+1)/($I49-$G49+1)))) -> 0 | Q49: =IF($G49=0,0,IF(Q$6<$G49,0,IF(Q$6>$I49,1,(Q$6-$G49+1)/($I49-$G49+1)))) -> 0 | R49: =IF($G49=0,0,IF(R$6<$G49,0,IF(R$6>$I49,1,(R$6-$G49+1)/($I49-$G49+1)))) -> 0 | ... BQ49: =IF($G49=0,0,IF(BQ$6<$G49,0,IF(BQ$6>$I49,1,(BQ$6-$G49+1)/($I49-$G49+1)))) -> 1 | BR49: =+AVERAGE(K49:BQ49) -> 0.74858757
B50: 9.1.5 | C50: ENCONFRADO WP44 | D50: 1 | E50: =VLOOKUP(B50,'Cuadro Control'!C50:J1980,8,FALSE) -> 49452330 | F50: 0.05 | G50: 46316 | I50: 46317 | J50: =+INDEX($K50:$BQ50,1,MATCH(I50,$K$6:$BQ$6,1)) -> 0 | K50: =IF($G50=0,0,IF(K$6<$G50,0,IF(K$6>$I50,1,(K$6-$G50+1)/($I50-$G50+1)))) -> 0 | L50: =IF($G50=0,0,IF(L$6<$G50,0,IF(L$6>$I50,1,(L$6-$G50+1)/($I50-$G50+1)))) -> 0 | M50: =IF($G50=0,0,IF(M$6<$G50,0,IF(M$6>$I50,1,(M$6-$G50+1)/($I50-$G50+1)))) -> 0 | N50: =IF($G50=0,0,IF(N$6<$G50,0,IF(N$6>$I50,1,(N$6-$G50+1)/($I50-$G50+1)))) -> 0 | O50: =IF($G50=0,0,IF(O$6<$G50,0,IF(O$6>$I50,1,(O$6-$G50+1)/($I50-$G50+1)))) -> 0 | P50: =IF($G50=0,0,IF(P$6<$G50,0,IF(P$6>$I50,1,(P$6-$G50+1)/($I50-$G50+1)))) -> 0 | Q50: =IF($G50=0,0,IF(Q$6<$G50,0,IF(Q$6>$I50,1,(Q$6-$G50+1)/($I50-$G50+1)))) -> 0 | R50: =IF($G50=0,0,IF(R$6<$G50,0,IF(R$6>$I50,1,(R$6-$G50+1)/($I50-$G50+1)))) -> 0 | ... BQ50: =IF($G50=0,0,IF(BQ$6<$G50,0,IF(BQ$6>$I50,1,(BQ$6-$G50+1)/($I50-$G50+1)))) -> 1 | BR50: =+AVERAGE(K50:BQ50) -> 0.74576271
A51: CONCRETO | B51: 9.1.6 | C51: VACIADO DE CONCRETO (APLICACIÓN PUENTE DE ADHERENCIA) WP44 | D51: 1 | E51: =VLOOKUP(B51,'Cuadro Control'!C51:J1981,8,FALSE) -> 1.4011493e+08 | F51: 0.15 | G51: 46317 | I51: 46318 | J51: =+INDEX($K51:$BQ51,1,MATCH(I51,$K$6:$BQ$6,1)) -> 1 | K51: =IF($G51=0,0,IF(K$6<$G51,0,IF(K$6>$I51,1,(K$6-$G51+1)/($I51-$G51+1)))) -> 0 | L51: =IF($G51=0,0,IF(L$6<$G51,0,IF(L$6>$I51,1,(L$6-$G51+1)/($I51-$G51+1)))) -> 0 | M51: =IF($G51=0,0,IF(M$6<$G51,0,IF(M$6>$I51,1,(M$6-$G51+1)/($I51-$G51+1)))) -> 0 | N51: =IF($G51=0,0,IF(N$6<$G51,0,IF(N$6>$I51,1,(N$6-$G51+1)/($I51-$G51+1)))) -> 0 | O51: =IF($G51=0,0,IF(O$6<$G51,0,IF(O$6>$I51,1,(O$6-$G51+1)/($I51-$G51+1)))) -> 0 | P51: =IF($G51=0,0,IF(P$6<$G51,0,IF(P$6>$I51,1,(P$6-$G51+1)/($I51-$G51+1)))) -> 0 | Q51: =IF($G51=0,0,IF(Q$6<$G51,0,IF(Q$6>$I51,1,(Q$6-$G51+1)/($I51-$G51+1)))) -> 0 | R51: =IF($G51=0,0,IF(R$6<$G51,0,IF(R$6>$I51,1,(R$6-$G51+1)/($I51-$G51+1)))) -> 0 | ... BQ51: =IF($G51=0,0,IF(BQ$6<$G51,0,IF(BQ$6>$I51,1,(BQ$6-$G51+1)/($I51-$G51+1)))) -> 1 | BR51: =+AVERAGE(K51:BQ51) -> 0.74576271
B52: 9.1.7 | C52: ADECUACIONES E INSTALACIONES ELECTRICAS REQUERIDAS WP44 | D52: 3 | E52: =VLOOKUP(B52,'Cuadro Control'!C52:J1982,8,FALSE) -> 52335716 | F52: 0.06 | G52: 46318 | I52: 46321 | J52: =+INDEX($K52:$BQ52,1,MATCH(I52,$K$6:$BQ$6,1)) -> 0.25 | K52: =IF($G52=0,0,IF(K$6<$G52,0,IF(K$6>$I52,1,(K$6-$G52+1)/($I52-$G52+1)))) -> 0 | L52: =IF($G52=0,0,IF(L$6<$G52,0,IF(L$6>$I52,1,(L$6-$G52+1)/($I52-$G52+1)))) -> 0 | M52: =IF($G52=0,0,IF(M$6<$G52,0,IF(M$6>$I52,1,(M$6-$G52+1)/($I52-$G52+1)))) -> 0 | N52: =IF($G52=0,0,IF(N$6<$G52,0,IF(N$6>$I52,1,(N$6-$G52+1)/($I52-$G52+1)))) -> 0 | O52: =IF($G52=0,0,IF(O$6<$G52,0,IF(O$6>$I52,1,(O$6-$G52+1)/($I52-$G52+1)))) -> 0 | P52: =IF($G52=0,0,IF(P$6<$G52,0,IF(P$6>$I52,1,(P$6-$G52+1)/($I52-$G52+1)))) -> 0 | Q52: =IF($G52=0,0,IF(Q$6<$G52,0,IF(Q$6>$I52,1,(Q$6-$G52+1)/($I52-$G52+1)))) -> 0 | R52: =IF($G52=0,0,IF(R$6<$G52,0,IF(R$6>$I52,1,(R$6-$G52+1)/($I52-$G52+1)))) -> 0 | ... BQ52: =IF($G52=0,0,IF(BQ$6<$G52,0,IF(BQ$6>$I52,1,(BQ$6-$G52+1)/($I52-$G52+1)))) -> 1 | BR52: =+AVERAGE(K52:BQ52) -> 0.73305085
B53: 9.1.8 | C53: INSTALACION DE GROUT Y MORTERO AUTOCOMPACTANTE DE ALTA RESISTENCIA WP44 | D53: 2 | E53: =VLOOKUP(B53,'Cuadro Control'!C53:J1983,8,FALSE) -> 46410609 | F53: 0.05 | G53: 46325 | I53: 46329 | J53: =+INDEX($K53:$BQ53,1,MATCH(I53,$K$6:$BQ$6,1)) -> 0.2 | K53: =IF($G53=0,0,IF(K$6<$G53,0,IF(K$6>$I53,1,(K$6-$G53+1)/($I53-$G53+1)))) -> 0 | L53: =IF($G53=0,0,IF(L$6<$G53,0,IF(L$6>$I53,1,(L$6-$G53+1)/($I53-$G53+1)))) -> 0 | M53: =IF($G53=0,0,IF(M$6<$G53,0,IF(M$6>$I53,1,(M$6-$G53+1)/($I53-$G53+1)))) -> 0 | N53: =IF($G53=0,0,IF(N$6<$G53,0,IF(N$6>$I53,1,(N$6-$G53+1)/($I53-$G53+1)))) -> 0 | O53: =IF($G53=0,0,IF(O$6<$G53,0,IF(O$6>$I53,1,(O$6-$G53+1)/($I53-$G53+1)))) -> 0 | P53: =IF($G53=0,0,IF(P$6<$G53,0,IF(P$6>$I53,1,(P$6-$G53+1)/($I53-$G53+1)))) -> 0 | Q53: =IF($G53=0,0,IF(Q$6<$G53,0,IF(Q$6>$I53,1,(Q$6-$G53+1)/($I53-$G53+1)))) -> 0 | R53: =IF($G53=0,0,IF(R$6<$G53,0,IF(R$6>$I53,1,(R$6-$G53+1)/($I53-$G53+1)))) -> 0 | ... BQ53: =IF($G53=0,0,IF(BQ$6<$G53,0,IF(BQ$6>$I53,1,(BQ$6-$G53+1)/($I53-$G53+1)))) -> 1 | BR53: =+AVERAGE(K53:BQ53) -> 0.71525424
B54: 9.2 | C54: RECALCE 2 WP45 | D54: 53 días | E54: =SUM(E55:E62) -> 9.2295182e+08 | F54: =IFERROR(E54/$E$44,0) -> 0.14285714 | G54: 46260 | I54: 46326 | J54: =+INDEX($K54:$BQ54,1,MATCH(I54,$K$6:$BQ$6,1)) -> 0.98333333 | K54: =SUMPRODUCT($F55:$F62,K55:K62) -> 0 | L54: =SUMPRODUCT($F55:$F62,L55:L62) -> 0 | M54: =SUMPRODUCT($F55:$F62,M55:M62) -> 0 | N54: =SUMPRODUCT($F55:$F62,N55:N62) -> 0 | O54: =SUMPRODUCT($F55:$F62,O55:O62) -> 0 | P54: =SUMPRODUCT($F55:$F62,P55:P62) -> 0 | Q54: =SUMPRODUCT($F55:$F62,Q55:Q62) -> 0 | R54: =SUMPRODUCT($F55:$F62,R55:R62) -> 0.14166667 | ... BQ54: =SUMPRODUCT($F55:$F62,BQ55:BQ62) -> 1 | BR54: =+AVERAGE(K54:BQ54) -> 0.8062954
B55: 9.2.1 | C55: LOCALIZACIÓN DEL ACERO WP45 | D55: 1 día | E55: =VLOOKUP(B55,'Cuadro Control'!C55:J1985,8,FALSE) -> 90662605 | F55: 0.1 | G55: 46260 | I55: 46262 | J55: =+INDEX($K55:$BQ55,1,MATCH(I55,$K$6:$BQ$6,1)) -> 1 | K55: =IF($G55=0,0,IF(K$6<$G55,0,IF(K$6>$I55,1,(K$6-$G55+1)/($I55-$G55+1)))) -> 0 | L55: =IF($G55=0,0,IF(L$6<$G55,0,IF(L$6>$I55,1,(L$6-$G55+1)/($I55-$G55+1)))) -> 0 | M55: =IF($G55=0,0,IF(M$6<$G55,0,IF(M$6>$I55,1,(M$6-$G55+1)/($I55-$G55+1)))) -> 0 | N55: =IF($G55=0,0,IF(N$6<$G55,0,IF(N$6>$I55,1,(N$6-$G55+1)/($I55-$G55+1)))) -> 0 | O55: =IF($G55=0,0,IF(O$6<$G55,0,IF(O$6>$I55,1,(O$6-$G55+1)/($I55-$G55+1)))) -> 0 | P55: =IF($G55=0,0,IF(P$6<$G55,0,IF(P$6>$I55,1,(P$6-$G55+1)/($I55-$G55+1)))) -> 0 | Q55: =IF($G55=0,0,IF(Q$6<$G55,0,IF(Q$6>$I55,1,(Q$6-$G55+1)/($I55-$G55+1)))) -> 0 | R55: =IF($G55=0,0,IF(R$6<$G55,0,IF(R$6>$I55,1,(R$6-$G55+1)/($I55-$G55+1)))) -> 1 | ... BQ55: =IF($G55=0,0,IF(BQ$6<$G55,0,IF(BQ$6>$I55,1,(BQ$6-$G55+1)/($I55-$G55+1)))) -> 1 | BR55: =+AVERAGE(K55:BQ55) -> 0.88135593
B56: 9.2.2 | C56: PERFORACION, ESCARIFICADO Y LIMPIEZA DEL RECUBRIMIENTO WP45 | D56: 4 días | E56: =VLOOKUP(B56,'Cuadro Control'!C56:J1986,8,FALSE) -> 2.3077754e+08 | F56: 0.25 | G56: 46262 | I56: 46267 | J56: =+INDEX($K56:$BQ56,1,MATCH(I56,$K$6:$BQ$6,1)) -> 0.16666667 | K56: =IF($G56=0,0,IF(K$6<$G56,0,IF(K$6>$I56,1,(K$6-$G56+1)/($I56-$G56+1)))) -> 0 | L56: =IF($G56=0,0,IF(L$6<$G56,0,IF(L$6>$I56,1,(L$6-$G56+1)/($I56-$G56+1)))) -> 0 | M56: =IF($G56=0,0,IF(M$6<$G56,0,IF(M$6>$I56,1,(M$6-$G56+1)/($I56-$G56+1)))) -> 0 | N56: =IF($G56=0,0,IF(N$6<$G56,0,IF(N$6>$I56,1,(N$6-$G56+1)/($I56-$G56+1)))) -> 0 | O56: =IF($G56=0,0,IF(O$6<$G56,0,IF(O$6>$I56,1,(O$6-$G56+1)/($I56-$G56+1)))) -> 0 | P56: =IF($G56=0,0,IF(P$6<$G56,0,IF(P$6>$I56,1,(P$6-$G56+1)/($I56-$G56+1)))) -> 0 | Q56: =IF($G56=0,0,IF(Q$6<$G56,0,IF(Q$6>$I56,1,(Q$6-$G56+1)/($I56-$G56+1)))) -> 0 | R56: =IF($G56=0,0,IF(R$6<$G56,0,IF(R$6>$I56,1,(R$6-$G56+1)/($I56-$G56+1)))) -> 0.16666667 | ... BQ56: =IF($G56=0,0,IF(BQ$6<$G56,0,IF(BQ$6>$I56,1,(BQ$6-$G56+1)/($I56-$G56+1)))) -> 1 | BR56: =+AVERAGE(K56:BQ56) -> 0.86723164
B57: 9.2.3 | C57: CORTE Y FIGURADO DE ACERO WP45 | D57: 2 días | E57: =VLOOKUP(B57,'Cuadro Control'!C57:J1987,8,FALSE) -> 82420550 | F57: 0.09 | G57: 46267 | I57: 46272 | J57: =+INDEX($K57:$BQ57,1,MATCH(I57,$K$6:$BQ$6,1)) -> 0.5 | K57: =IF($G57=0,0,IF(K$6<$G57,0,IF(K$6>$I57,1,(K$6-$G57+1)/($I57-$G57+1)))) -> 0 | L57: =IF($G57=0,0,IF(L$6<$G57,0,IF(L$6>$I57,1,(L$6-$G57+1)/($I57-$G57+1)))) -> 0 | M57: =IF($G57=0,0,IF(M$6<$G57,0,IF(M$6>$I57,1,(M$6-$G57+1)/($I57-$G57+1)))) -> 0 | N57: =IF($G57=0,0,IF(N$6<$G57,0,IF(N$6>$I57,1,(N$6-$G57+1)/($I57-$G57+1)))) -> 0 | O57: =IF($G57=0,0,IF(O$6<$G57,0,IF(O$6>$I57,1,(O$6-$G57+1)/($I57-$G57+1)))) -> 0 | P57: =IF($G57=0,0,IF(P$6<$G57,0,IF(P$6>$I57,1,(P$6-$G57+1)/($I57-$G57+1)))) -> 0 | Q57: =IF($G57=0,0,IF(Q$6<$G57,0,IF(Q$6>$I57,1,(Q$6-$G57+1)/($I57-$G57+1)))) -> 0 | R57: =IF($G57=0,0,IF(R$6<$G57,0,IF(R$6>$I57,1,(R$6-$G57+1)/($I57-$G57+1)))) -> 0 | ... BQ57: =IF($G57=0,0,IF(BQ$6<$G57,0,IF(BQ$6>$I57,1,(BQ$6-$G57+1)/($I57-$G57+1)))) -> 1 | BR57: =+AVERAGE(K57:BQ57) -> 0.8559322
B58: 9.2.4 | C58: APLICACIÓN DE EPOXICO Y FIJACIÓN DEL ACERO WP45 | D58: 4 días | E58: =VLOOKUP(B58,'Cuadro Control'!C58:J1988,8,FALSE) -> 2.3077754e+08 | F58: 0.25 | G58: 46303 | I58: 46309 | J58: =+INDEX($K58:$BQ58,1,MATCH(I58,$K$6:$BQ$6,1)) -> 0.28571429 | K58: =IF($G58=0,0,IF(K$6<$G58,0,IF(K$6>$I58,1,(K$6-$G58+1)/($I58-$G58+1)))) -> 0 | L58: =IF($G58=0,0,IF(L$6<$G58,0,IF(L$6>$I58,1,(L$6-$G58+1)/($I58-$G58+1)))) -> 0 | M58: =IF($G58=0,0,IF(M$6<$G58,0,IF(M$6>$I58,1,(M$6-$G58+1)/($I58-$G58+1)))) -> 0 | N58: =IF($G58=0,0,IF(N$6<$G58,0,IF(N$6>$I58,1,(N$6-$G58+1)/($I58-$G58+1)))) -> 0 | O58: =IF($G58=0,0,IF(O$6<$G58,0,IF(O$6>$I58,1,(O$6-$G58+1)/($I58-$G58+1)))) -> 0 | P58: =IF($G58=0,0,IF(P$6<$G58,0,IF(P$6>$I58,1,(P$6-$G58+1)/($I58-$G58+1)))) -> 0 | Q58: =IF($G58=0,0,IF(Q$6<$G58,0,IF(Q$6>$I58,1,(Q$6-$G58+1)/($I58-$G58+1)))) -> 0 | R58: =IF($G58=0,0,IF(R$6<$G58,0,IF(R$6>$I58,1,(R$6-$G58+1)/($I58-$G58+1)))) -> 0 | ... BQ58: =IF($G58=0,0,IF(BQ$6<$G58,0,IF(BQ$6>$I58,1,(BQ$6-$G58+1)/($I58-$G58+1)))) -> 1 | BR58: =+AVERAGE(K58:BQ58) -> 0.76755448
B59: 9.2.5 | C59: ENCONFRADO WP45 | D59: 1 día | E59: =VLOOKUP(B59,'Cuadro Control'!C59:J1989,8,FALSE) -> 49452330 | F59: 0.05 | G59: 46309 | I59: 46310 | J59: =+INDEX($K59:$BQ59,1,MATCH(I59,$K$6:$BQ$6,1)) -> 0 | K59: =IF($G59=0,0,IF(K$6<$G59,0,IF(K$6>$I59,1,(K$6-$G59+1)/($I59-$G59+1)))) -> 0 | L59: =IF($G59=0,0,IF(L$6<$G59,0,IF(L$6>$I59,1,(L$6-$G59+1)/($I59-$G59+1)))) -> 0 | M59: =IF($G59=0,0,IF(M$6<$G59,0,IF(M$6>$I59,1,(M$6-$G59+1)/($I59-$G59+1)))) -> 0 | N59: =IF($G59=0,0,IF(N$6<$G59,0,IF(N$6>$I59,1,(N$6-$G59+1)/($I59-$G59+1)))) -> 0 | O59: =IF($G59=0,0,IF(O$6<$G59,0,IF(O$6>$I59,1,(O$6-$G59+1)/($I59-$G59+1)))) -> 0 | P59: =IF($G59=0,0,IF(P$6<$G59,0,IF(P$6>$I59,1,(P$6-$G59+1)/($I59-$G59+1)))) -> 0 | Q59: =IF($G59=0,0,IF(Q$6<$G59,0,IF(Q$6>$I59,1,(Q$6-$G59+1)/($I59-$G59+1)))) -> 0 | R59: =IF($G59=0,0,IF(R$6<$G59,0,IF(R$6>$I59,1,(R$6-$G59+1)/($I59-$G59+1)))) -> 0 | ... BQ59: =IF($G59=0,0,IF(BQ$6<$G59,0,IF(BQ$6>$I59,1,(BQ$6-$G59+1)/($I59-$G59+1)))) -> 1 | BR59: =+AVERAGE(K59:BQ59) -> 0.76271186
B60: 9.2.6 | C60: VACIADO DE CONCRETO (APLICACIÓN PUENTE DE ADHERENCIA) WP45 | D60: 1 día | E60: =VLOOKUP(B60,'Cuadro Control'!C60:J1990,8,FALSE) -> 1.4011493e+08 | F60: 0.15 | G60: 46310 | I60: 46310 | J60: =+INDEX($K60:$BQ60,1,MATCH(I60,$K$6:$BQ$6,1)) -> 0 | K60: =IF($G60=0,0,IF(K$6<$G60,0,IF(K$6>$I60,1,(K$6-$G60+1)/($I60-$G60+1)))) -> 0 | L60: =IF($G60=0,0,IF(L$6<$G60,0,IF(L$6>$I60,1,(L$6-$G60+1)/($I60-$G60+1)))) -> 0 | M60: =IF($G60=0,0,IF(M$6<$G60,0,IF(M$6>$I60,1,(M$6-$G60+1)/($I60-$G60+1)))) -> 0 | N60: =IF($G60=0,0,IF(N$6<$G60,0,IF(N$6>$I60,1,(N$6-$G60+1)/($I60-$G60+1)))) -> 0 | O60: =IF($G60=0,0,IF(O$6<$G60,0,IF(O$6>$I60,1,(O$6-$G60+1)/($I60-$G60+1)))) -> 0 | P60: =IF($G60=0,0,IF(P$6<$G60,0,IF(P$6>$I60,1,(P$6-$G60+1)/($I60-$G60+1)))) -> 0 | Q60: =IF($G60=0,0,IF(Q$6<$G60,0,IF(Q$6>$I60,1,(Q$6-$G60+1)/($I60-$G60+1)))) -> 0 | R60: =IF($G60=0,0,IF(R$6<$G60,0,IF(R$6>$I60,1,(R$6-$G60+1)/($I60-$G60+1)))) -> 0 | ... BQ60: =IF($G60=0,0,IF(BQ$6<$G60,0,IF(BQ$6>$I60,1,(BQ$6-$G60+1)/($I60-$G60+1)))) -> 1 | BR60: =+AVERAGE(K60:BQ60) -> 0.76271186
B61: 9.2.7 | C61: ADECUACIONES E INSTALACIONES ELECTRICAS REQUERIDAS WP45 | D61: 3 días | E61: =VLOOKUP(B61,'Cuadro Control'!C62:J1991,8,FALSE) -> 52335716 | F61: 0.06 | G61: 46321 | I61: 46324 | J61: =+INDEX($K61:$BQ61,1,MATCH(I61,$K$6:$BQ$6,1)) -> 0 | K61: =IF($G61=0,0,IF(K$6<$G61,0,IF(K$6>$I61,1,(K$6-$G61+1)/($I61-$G61+1)))) -> 0 | L61: =IF($G61=0,0,IF(L$6<$G61,0,IF(L$6>$I61,1,(L$6-$G61+1)/($I61-$G61+1)))) -> 0 | M61: =IF($G61=0,0,IF(M$6<$G61,0,IF(M$6>$I61,1,(M$6-$G61+1)/($I61-$G61+1)))) -> 0 | N61: =IF($G61=0,0,IF(N$6<$G61,0,IF(N$6>$I61,1,(N$6-$G61+1)/($I61-$G61+1)))) -> 0 | O61: =IF($G61=0,0,IF(O$6<$G61,0,IF(O$6>$I61,1,(O$6-$G61+1)/($I61-$G61+1)))) -> 0 | P61: =IF($G61=0,0,IF(P$6<$G61,0,IF(P$6>$I61,1,(P$6-$G61+1)/($I61-$G61+1)))) -> 0 | Q61: =IF($G61=0,0,IF(Q$6<$G61,0,IF(Q$6>$I61,1,(Q$6-$G61+1)/($I61-$G61+1)))) -> 0 | R61: =IF($G61=0,0,IF(R$6<$G61,0,IF(R$6>$I61,1,(R$6-$G61+1)/($I61-$G61+1)))) -> 0 | ... BQ61: =IF($G61=0,0,IF(BQ$6<$G61,0,IF(BQ$6>$I61,1,(BQ$6-$G61+1)/($I61-$G61+1)))) -> 1 | BR61: =+AVERAGE(K61:BQ61) -> 0.72881356
B62: 9.2.8 | C62: INSTALACION DE GROUT Y MORTERO AUTOCOMPACTANTE DE ALTA RESISTENCIA WP45 | D62: 2 días | E62: =VLOOKUP(B62,'Cuadro Control'!C64:J1992,8,FALSE) -> 46410609 | F62: 0.05 | G62: 46324 | I62: 46326 | J62: =+INDEX($K62:$BQ62,1,MATCH(I62,$K$6:$BQ$6,1)) -> 0.66666667 | K62: =IF($G62=0,0,IF(K$6<$G62,0,IF(K$6>$I62,1,(K$6-$G62+1)/($I62-$G62+1)))) -> 0 | L62: =IF($G62=0,0,IF(L$6<$G62,0,IF(L$6>$I62,1,(L$6-$G62+1)/($I62-$G62+1)))) -> 0 | M62: =IF($G62=0,0,IF(M$6<$G62,0,IF(M$6>$I62,1,(M$6-$G62+1)/($I62-$G62+1)))) -> 0 | N62: =IF($G62=0,0,IF(N$6<$G62,0,IF(N$6>$I62,1,(N$6-$G62+1)/($I62-$G62+1)))) -> 0 | O62: =IF($G62=0,0,IF(O$6<$G62,0,IF(O$6>$I62,1,(O$6-$G62+1)/($I62-$G62+1)))) -> 0 | P62: =IF($G62=0,0,IF(P$6<$G62,0,IF(P$6>$I62,1,(P$6-$G62+1)/($I62-$G62+1)))) -> 0 | Q62: =IF($G62=0,0,IF(Q$6<$G62,0,IF(Q$6>$I62,1,(Q$6-$G62+1)/($I62-$G62+1)))) -> 0 | R62: =IF($G62=0,0,IF(R$6<$G62,0,IF(R$6>$I62,1,(R$6-$G62+1)/($I62-$G62+1)))) -> 0 | ... BQ62: =IF($G62=0,0,IF(BQ$6<$G62,0,IF(BQ$6>$I62,1,(BQ$6-$G62+1)/($I62-$G62+1)))) -> 1 | BR62: =+AVERAGE(K62:BQ62) -> 0.72316384
B63: 9.3 | C63: RECALCE 3 WP46 | D63: 53 días | E63: =SUM(E64:E71) -> 9.2295182e+08 | F63: =IFERROR(E63/$E$44,0) -> 0.14285714 | G63: 46267 | I63: 46330 | J63: =+INDEX($K63:$BQ63,1,MATCH(I63,$K$6:$BQ$6,1)) -> 0.91 | K63: =SUMPRODUCT($F64:$F71,K64:K71) -> 0 | L63: =SUMPRODUCT($F64:$F71,L64:L71) -> 0 | M63: =SUMPRODUCT($F64:$F71,M64:M71) -> 0 | N63: =SUMPRODUCT($F64:$F71,N64:N71) -> 0 | O63: =SUMPRODUCT($F64:$F71,O64:O71) -> 0 | P63: =SUMPRODUCT($F64:$F71,P64:P71) -> 0 | Q63: =SUMPRODUCT($F64:$F71,Q64:Q71) -> 0 | R63: =SUMPRODUCT($F64:$F71,R64:R71) -> 0 | ... BQ63: =SUMPRODUCT($F64:$F71,BQ64:BQ71) -> 1 | BR63: =+AVERAGE(K63:BQ63) -> 0.78920985
B64: 9.3.1 | C64: LOCALIZACIÓN DEL ACERO WP46 | D64: 1 día | E64: =VLOOKUP(B64,'Cuadro Control'!C68:J1994,8,FALSE) -> 90662605 | F64: 0.1 | G64: 46267 | I64: 46269 | J64: =+INDEX($K64:$BQ64,1,MATCH(I64,$K$6:$BQ$6,1)) -> 1 | K64: =IF($G64=0,0,IF(K$6<$G64,0,IF(K$6>$I64,1,(K$6-$G64+1)/($I64-$G64+1)))) -> 0 | L64: =IF($G64=0,0,IF(L$6<$G64,0,IF(L$6>$I64,1,(L$6-$G64+1)/($I64-$G64+1)))) -> 0 | M64: =IF($G64=0,0,IF(M$6<$G64,0,IF(M$6>$I64,1,(M$6-$G64+1)/($I64-$G64+1)))) -> 0 | N64: =IF($G64=0,0,IF(N$6<$G64,0,IF(N$6>$I64,1,(N$6-$G64+1)/($I64-$G64+1)))) -> 0 | O64: =IF($G64=0,0,IF(O$6<$G64,0,IF(O$6>$I64,1,(O$6-$G64+1)/($I64-$G64+1)))) -> 0 | P64: =IF($G64=0,0,IF(P$6<$G64,0,IF(P$6>$I64,1,(P$6-$G64+1)/($I64-$G64+1)))) -> 0 | Q64: =IF($G64=0,0,IF(Q$6<$G64,0,IF(Q$6>$I64,1,(Q$6-$G64+1)/($I64-$G64+1)))) -> 0 | R64: =IF($G64=0,0,IF(R$6<$G64,0,IF(R$6>$I64,1,(R$6-$G64+1)/($I64-$G64+1)))) -> 0 | ... BQ64: =IF($G64=0,0,IF(BQ$6<$G64,0,IF(BQ$6>$I64,1,(BQ$6-$G64+1)/($I64-$G64+1)))) -> 1 | BR64: =+AVERAGE(K64:BQ64) -> 0.86440678
B65: 9.3.2 | C65: ESCARIFICADO Y LIMPIEZA DEL RECUBRIMIENTO WP46 | D65: 4 días | E65: =VLOOKUP(B65,'Cuadro Control'!C70:J1995,8,FALSE) -> 2.3077754e+08 | F65: 0.25 | G65: 46269 | I65: 46275 | J65: =+INDEX($K65:$BQ65,1,MATCH(I65,$K$6:$BQ$6,1)) -> 0.14285714 | K65: =IF($G65=0,0,IF(K$6<$G65,0,IF(K$6>$I65,1,(K$6-$G65+1)/($I65-$G65+1)))) -> 0 | L65: =IF($G65=0,0,IF(L$6<$G65,0,IF(L$6>$I65,1,(L$6-$G65+1)/($I65-$G65+1)))) -> 0 | M65: =IF($G65=0,0,IF(M$6<$G65,0,IF(M$6>$I65,1,(M$6-$G65+1)/($I65-$G65+1)))) -> 0 | N65: =IF($G65=0,0,IF(N$6<$G65,0,IF(N$6>$I65,1,(N$6-$G65+1)/($I65-$G65+1)))) -> 0 | O65: =IF($G65=0,0,IF(O$6<$G65,0,IF(O$6>$I65,1,(O$6-$G65+1)/($I65-$G65+1)))) -> 0 | P65: =IF($G65=0,0,IF(P$6<$G65,0,IF(P$6>$I65,1,(P$6-$G65+1)/($I65-$G65+1)))) -> 0 | Q65: =IF($G65=0,0,IF(Q$6<$G65,0,IF(Q$6>$I65,1,(Q$6-$G65+1)/($I65-$G65+1)))) -> 0 | R65: =IF($G65=0,0,IF(R$6<$G65,0,IF(R$6>$I65,1,(R$6-$G65+1)/($I65-$G65+1)))) -> 0 | ... BQ65: =IF($G65=0,0,IF(BQ$6<$G65,0,IF(BQ$6>$I65,1,(BQ$6-$G65+1)/($I65-$G65+1)))) -> 1 | BR65: =+AVERAGE(K65:BQ65) -> 0.84987893
B66: 9.3.3 | C66: CORTE Y FIGURADO DE ACERO WP46 | D66: 4 días | E66: =VLOOKUP(B66,'Cuadro Control'!C71:J1996,8,FALSE) -> 82420550 | F66: 0.09 | G66: 46275 | I66: 46279 | J66: =+INDEX($K66:$BQ66,1,MATCH(I66,$K$6:$BQ$6,1)) -> 0.4 | K66: =IF($G66=0,0,IF(K$6<$G66,0,IF(K$6>$I66,1,(K$6-$G66+1)/($I66-$G66+1)))) -> 0 | L66: =IF($G66=0,0,IF(L$6<$G66,0,IF(L$6>$I66,1,(L$6-$G66+1)/($I66-$G66+1)))) -> 0 | M66: =IF($G66=0,0,IF(M$6<$G66,0,IF(M$6>$I66,1,(M$6-$G66+1)/($I66-$G66+1)))) -> 0 | N66: =IF($G66=0,0,IF(N$6<$G66,0,IF(N$6>$I66,1,(N$6-$G66+1)/($I66-$G66+1)))) -> 0 | O66: =IF($G66=0,0,IF(O$6<$G66,0,IF(O$6>$I66,1,(O$6-$G66+1)/($I66-$G66+1)))) -> 0 | P66: =IF($G66=0,0,IF(P$6<$G66,0,IF(P$6>$I66,1,(P$6-$G66+1)/($I66-$G66+1)))) -> 0 | Q66: =IF($G66=0,0,IF(Q$6<$G66,0,IF(Q$6>$I66,1,(Q$6-$G66+1)/($I66-$G66+1)))) -> 0 | R66: =IF($G66=0,0,IF(R$6<$G66,0,IF(R$6>$I66,1,(R$6-$G66+1)/($I66-$G66+1)))) -> 0 | ... BQ66: =IF($G66=0,0,IF(BQ$6<$G66,0,IF(BQ$6>$I66,1,(BQ$6-$G66+1)/($I66-$G66+1)))) -> 1 | BR66: =+AVERAGE(K66:BQ66) -> 0.83728814
B67: 9.3.4 | C67: APLICACIÓN DE EPOXICO Y FIJACIÓN DEL ACERO WP46 | D67: 4 días | E67: =VLOOKUP(B67,'Cuadro Control'!C72:J1997,8,FALSE) -> 2.3077754e+08 | F67: 0.25 | G67: 46311 | I67: 46316 | J67: =+INDEX($K67:$BQ67,1,MATCH(I67,$K$6:$BQ$6,1)) -> 0.16666667 | K67: =IF($G67=0,0,IF(K$6<$G67,0,IF(K$6>$I67,1,(K$6-$G67+1)/($I67-$G67+1)))) -> 0 | L67: =IF($G67=0,0,IF(L$6<$G67,0,IF(L$6>$I67,1,(L$6-$G67+1)/($I67-$G67+1)))) -> 0 | M67: =IF($G67=0,0,IF(M$6<$G67,0,IF(M$6>$I67,1,(M$6-$G67+1)/($I67-$G67+1)))) -> 0 | N67: =IF($G67=0,0,IF(N$6<$G67,0,IF(N$6>$I67,1,(N$6-$G67+1)/($I67-$G67+1)))) -> 0 | O67: =IF($G67=0,0,IF(O$6<$G67,0,IF(O$6>$I67,1,(O$6-$G67+1)/($I67-$G67+1)))) -> 0 | P67: =IF($G67=0,0,IF(P$6<$G67,0,IF(P$6>$I67,1,(P$6-$G67+1)/($I67-$G67+1)))) -> 0 | Q67: =IF($G67=0,0,IF(Q$6<$G67,0,IF(Q$6>$I67,1,(Q$6-$G67+1)/($I67-$G67+1)))) -> 0 | R67: =IF($G67=0,0,IF(R$6<$G67,0,IF(R$6>$I67,1,(R$6-$G67+1)/($I67-$G67+1)))) -> 0 | ... BQ67: =IF($G67=0,0,IF(BQ$6<$G67,0,IF(BQ$6>$I67,1,(BQ$6-$G67+1)/($I67-$G67+1)))) -> 1 | BR67: =+AVERAGE(K67:BQ67) -> 0.74858757
B68: 9.3.5 | C68: ENCONFRADO WP46 | D68: 1 día | E68: =VLOOKUP(B68,'Cuadro Control'!C73:J1998,8,FALSE) -> 49452330 | F68: 0.05 | G68: 46316 | I68: 46317 | J68: =+INDEX($K68:$BQ68,1,MATCH(I68,$K$6:$BQ$6,1)) -> 0 | K68: =IF($G68=0,0,IF(K$6<$G68,0,IF(K$6>$I68,1,(K$6-$G68+1)/($I68-$G68+1)))) -> 0 | L68: =IF($G68=0,0,IF(L$6<$G68,0,IF(L$6>$I68,1,(L$6-$G68+1)/($I68-$G68+1)))) -> 0 | M68: =IF($G68=0,0,IF(M$6<$G68,0,IF(M$6>$I68,1,(M$6-$G68+1)/($I68-$G68+1)))) -> 0 | N68: =IF($G68=0,0,IF(N$6<$G68,0,IF(N$6>$I68,1,(N$6-$G68+1)/($I68-$G68+1)))) -> 0 | O68: =IF($G68=0,0,IF(O$6<$G68,0,IF(O$6>$I68,1,(O$6-$G68+1)/($I68-$G68+1)))) -> 0 | P68: =IF($G68=0,0,IF(P$6<$G68,0,IF(P$6>$I68,1,(P$6-$G68+1)/($I68-$G68+1)))) -> 0 | Q68: =IF($G68=0,0,IF(Q$6<$G68,0,IF(Q$6>$I68,1,(Q$6-$G68+1)/($I68-$G68+1)))) -> 0 | R68: =IF($G68=0,0,IF(R$6<$G68,0,IF(R$6>$I68,1,(R$6-$G68+1)/($I68-$G68+1)))) -> 0 | ... BQ68: =IF($G68=0,0,IF(BQ$6<$G68,0,IF(BQ$6>$I68,1,(BQ$6-$G68+1)/($I68-$G68+1)))) -> 1 | BR68: =+AVERAGE(K68:BQ68) -> 0.74576271
B69: 9.3.6 | C69: VACIADO DE CONCRETO (APLICACIÓN PUENTE DE ADHERENCIA) WP46 | D69: 1 día | E69: =VLOOKUP(B69,'Cuadro Control'!C74:J1999,8,FALSE) -> 1.4011493e+08 | F69: 0.15 | G69: 46317 | I69: 46318 | J69: =+INDEX($K69:$BQ69,1,MATCH(I69,$K$6:$BQ$6,1)) -> 1 | K69: =IF($G69=0,0,IF(K$6<$G69,0,IF(K$6>$I69,1,(K$6-$G69+1)/($I69-$G69+1)))) -> 0 | L69: =IF($G69=0,0,IF(L$6<$G69,0,IF(L$6>$I69,1,(L$6-$G69+1)/($I69-$G69+1)))) -> 0 | M69: =IF($G69=0,0,IF(M$6<$G69,0,IF(M$6>$I69,1,(M$6-$G69+1)/($I69-$G69+1)))) -> 0 | N69: =IF($G69=0,0,IF(N$6<$G69,0,IF(N$6>$I69,1,(N$6-$G69+1)/($I69-$G69+1)))) -> 0 | O69: =IF($G69=0,0,IF(O$6<$G69,0,IF(O$6>$I69,1,(O$6-$G69+1)/($I69-$G69+1)))) -> 0 | P69: =IF($G69=0,0,IF(P$6<$G69,0,IF(P$6>$I69,1,(P$6-$G69+1)/($I69-$G69+1)))) -> 0 | Q69: =IF($G69=0,0,IF(Q$6<$G69,0,IF(Q$6>$I69,1,(Q$6-$G69+1)/($I69-$G69+1)))) -> 0 | R69: =IF($G69=0,0,IF(R$6<$G69,0,IF(R$6>$I69,1,(R$6-$G69+1)/($I69-$G69+1)))) -> 0 | ... BQ69: =IF($G69=0,0,IF(BQ$6<$G69,0,IF(BQ$6>$I69,1,(BQ$6-$G69+1)/($I69-$G69+1)))) -> 1 | BR69: =+AVERAGE(K69:BQ69) -> 0.74576271
B70: 9.3.7 | C70: ADECUACIONES E INSTALACIONES ELECTRICAS REQUERIDAS WP46 | D70: 3 días | E70: =VLOOKUP(B70,'Cuadro Control'!C75:J2000,8,FALSE) -> 52335716 | F70: 0.06 | G70: 46324 | I70: 46329 | J70: =+INDEX($K70:$BQ70,1,MATCH(I70,$K$6:$BQ$6,1)) -> 0.33333333 | K70: =IF($G70=0,0,IF(K$6<$G70,0,IF(K$6>$I70,1,(K$6-$G70+1)/($I70-$G70+1)))) -> 0 | L70: =IF($G70=0,0,IF(L$6<$G70,0,IF(L$6>$I70,1,(L$6-$G70+1)/($I70-$G70+1)))) -> 0 | M70: =IF($G70=0,0,IF(M$6<$G70,0,IF(M$6>$I70,1,(M$6-$G70+1)/($I70-$G70+1)))) -> 0 | N70: =IF($G70=0,0,IF(N$6<$G70,0,IF(N$6>$I70,1,(N$6-$G70+1)/($I70-$G70+1)))) -> 0 | O70: =IF($G70=0,0,IF(O$6<$G70,0,IF(O$6>$I70,1,(O$6-$G70+1)/($I70-$G70+1)))) -> 0 | P70: =IF($G70=0,0,IF(P$6<$G70,0,IF(P$6>$I70,1,(P$6-$G70+1)/($I70-$G70+1)))) -> 0 | Q70: =IF($G70=0,0,IF(Q$6<$G70,0,IF(Q$6>$I70,1,(Q$6-$G70+1)/($I70-$G70+1)))) -> 0 | R70: =IF($G70=0,0,IF(R$6<$G70,0,IF(R$6>$I70,1,(R$6-$G70+1)/($I70-$G70+1)))) -> 0 | ... BQ70: =IF($G70=0,0,IF(BQ$6<$G70,0,IF(BQ$6>$I70,1,(BQ$6-$G70+1)/($I70-$G70+1)))) -> 1 | BR70: =+AVERAGE(K70:BQ70) -> 0.71751412
B71: 9.3.8 | C71: INSTALACION DE GROUT Y MORTERO AUTOCOMPACTANTE DE ALTA RESISTENCIA WP46 | D71: 2 días | E71: =VLOOKUP(B71,'Cuadro Control'!C76:J2001,8,FALSE) -> 46410609 | F71: 0.05 | G71: 46329 | I71: 46330 | J71: =+INDEX($K71:$BQ71,1,MATCH(I71,$K$6:$BQ$6,1)) -> 0 | K71: =IF($G71=0,0,IF(K$6<$G71,0,IF(K$6>$I71,1,(K$6-$G71+1)/($I71-$G71+1)))) -> 0 | L71: =IF($G71=0,0,IF(L$6<$G71,0,IF(L$6>$I71,1,(L$6-$G71+1)/($I71-$G71+1)))) -> 0 | M71: =IF($G71=0,0,IF(M$6<$G71,0,IF(M$6>$I71,1,(M$6-$G71+1)/($I71-$G71+1)))) -> 0 | N71: =IF($G71=0,0,IF(N$6<$G71,0,IF(N$6>$I71,1,(N$6-$G71+1)/($I71-$G71+1)))) -> 0 | O71: =IF($G71=0,0,IF(O$6<$G71,0,IF(O$6>$I71,1,(O$6-$G71+1)/($I71-$G71+1)))) -> 0 | P71: =IF($G71=0,0,IF(P$6<$G71,0,IF(P$6>$I71,1,(P$6-$G71+1)/($I71-$G71+1)))) -> 0 | Q71: =IF($G71=0,0,IF(Q$6<$G71,0,IF(Q$6>$I71,1,(Q$6-$G71+1)/($I71-$G71+1)))) -> 0 | R71: =IF($G71=0,0,IF(R$6<$G71,0,IF(R$6>$I71,1,(R$6-$G71+1)/($I71-$G71+1)))) -> 0 | ... BQ71: =IF($G71=0,0,IF(BQ$6<$G71,0,IF(BQ$6>$I71,1,(BQ$6-$G71+1)/($I71-$G71+1)))) -> 1 | BR71: =+AVERAGE(K71:BQ71) -> 0.71186441
B72: 9.4 | C72: RECALCE 4 WP47 | D72: 53 días | E72: =SUM(E73:E80) -> 9.2295182e+08 | F72: =IFERROR(E72/$E$44,0) -> 0.14285714 | G72: 46275 | I72: 46336 | J72: =+INDEX($K72:$BQ72,1,MATCH(I72,$K$6:$BQ$6,1)) -> 0.95 | K72: =SUMPRODUCT($F73:$F80,K73:K80) -> 0 | L72: =SUMPRODUCT($F73:$F80,L73:L80) -> 0 | M72: =SUMPRODUCT($F73:$F80,M73:M80) -> 0 | N72: =SUMPRODUCT($F73:$F80,N73:N80) -> 0 | O72: =SUMPRODUCT($F73:$F80,O73:O80) -> 0 | P72: =SUMPRODUCT($F73:$F80,P73:P80) -> 0 | Q72: =SUMPRODUCT($F73:$F80,Q73:Q80) -> 0 | R72: =SUMPRODUCT($F73:$F80,R73:R80) -> 0 | ... BQ72: =SUMPRODUCT($F73:$F80,BQ73:BQ80) -> 1 | BR72: =+AVERAGE(K72:BQ72) -> 0.77152542
B73: 9.4.1 | C73: LOCALIZACIÓN DEL ACERO WP47 | D73: 1 día | E73: =VLOOKUP(B73,'Cuadro Control'!C78:J2003,8,FALSE) -> 90662605 | F73: 0.1 | G73: 46275 | I73: 46276 | J73: =+INDEX($K73:$BQ73,1,MATCH(I73,$K$6:$BQ$6,1)) -> 1 | K73: =IF($G73=0,0,IF(K$6<$G73,0,IF(K$6>$I73,1,(K$6-$G73+1)/($I73-$G73+1)))) -> 0 | L73: =IF($G73=0,0,IF(L$6<$G73,0,IF(L$6>$I73,1,(L$6-$G73+1)/($I73-$G73+1)))) -> 0 | M73: =IF($G73=0,0,IF(M$6<$G73,0,IF(M$6>$I73,1,(M$6-$G73+1)/($I73-$G73+1)))) -> 0 | N73: =IF($G73=0,0,IF(N$6<$G73,0,IF(N$6>$I73,1,(N$6-$G73+1)/($I73-$G73+1)))) -> 0 | O73: =IF($G73=0,0,IF(O$6<$G73,0,IF(O$6>$I73,1,(O$6-$G73+1)/($I73-$G73+1)))) -> 0 | P73: =IF($G73=0,0,IF(P$6<$G73,0,IF(P$6>$I73,1,(P$6-$G73+1)/($I73-$G73+1)))) -> 0 | Q73: =IF($G73=0,0,IF(Q$6<$G73,0,IF(Q$6>$I73,1,(Q$6-$G73+1)/($I73-$G73+1)))) -> 0 | R73: =IF($G73=0,0,IF(R$6<$G73,0,IF(R$6>$I73,1,(R$6-$G73+1)/($I73-$G73+1)))) -> 0 | ... BQ73: =IF($G73=0,0,IF(BQ$6<$G73,0,IF(BQ$6>$I73,1,(BQ$6-$G73+1)/($I73-$G73+1)))) -> 1 | BR73: =+AVERAGE(K73:BQ73) -> 0.84745763
B74: 9.4.2 | C74: ESCARIFICADO Y LIMPIEZA DEL RECUBRIMIENTO WP47 | D74: 4 días | E74: =VLOOKUP(B74,'Cuadro Control'!C79:J2004,8,FALSE) -> 2.3077754e+08 | F74: 0.25 | G74: 46277 | I74: 46282 | J74: =+INDEX($K74:$BQ74,1,MATCH(I74,$K$6:$BQ$6,1)) -> 0 | K74: =IF($G74=0,0,IF(K$6<$G74,0,IF(K$6>$I74,1,(K$6-$G74+1)/($I74-$G74+1)))) -> 0 | L74: =IF($G74=0,0,IF(L$6<$G74,0,IF(L$6>$I74,1,(L$6-$G74+1)/($I74-$G74+1)))) -> 0 | M74: =IF($G74=0,0,IF(M$6<$G74,0,IF(M$6>$I74,1,(M$6-$G74+1)/($I74-$G74+1)))) -> 0 | N74: =IF($G74=0,0,IF(N$6<$G74,0,IF(N$6>$I74,1,(N$6-$G74+1)/($I74-$G74+1)))) -> 0 | O74: =IF($G74=0,0,IF(O$6<$G74,0,IF(O$6>$I74,1,(O$6-$G74+1)/($I74-$G74+1)))) -> 0 | P74: =IF($G74=0,0,IF(P$6<$G74,0,IF(P$6>$I74,1,(P$6-$G74+1)/($I74-$G74+1)))) -> 0 | Q74: =IF($G74=0,0,IF(Q$6<$G74,0,IF(Q$6>$I74,1,(Q$6-$G74+1)/($I74-$G74+1)))) -> 0 | R74: =IF($G74=0,0,IF(R$6<$G74,0,IF(R$6>$I74,1,(R$6-$G74+1)/($I74-$G74+1)))) -> 0 | ... BQ74: =IF($G74=0,0,IF(BQ$6<$G74,0,IF(BQ$6>$I74,1,(BQ$6-$G74+1)/($I74-$G74+1)))) -> 1 | BR74: =+AVERAGE(K74:BQ74) -> 0.83050847
B75: 9.4.3 | C75: CORTE Y FIGURADO DE ACERO WP47 | D75: 4 días | E75: =VLOOKUP(B75,'Cuadro Control'!C80:J2005,8,FALSE) -> 82420550 | F75: 0.09 | G75: 46282 | I75: 46287 | J75: =+INDEX($K75:$BQ75,1,MATCH(I75,$K$6:$BQ$6,1)) -> 0.33333333 | K75: =IF($G75=0,0,IF(K$6<$G75,0,IF(K$6>$I75,1,(K$6-$G75+1)/($I75-$G75+1)))) -> 0 | L75: =IF($G75=0,0,IF(L$6<$G75,0,IF(L$6>$I75,1,(L$6-$G75+1)/($I75-$G75+1)))) -> 0 | M75: =IF($G75=0,0,IF(M$6<$G75,0,IF(M$6>$I75,1,(M$6-$G75+1)/($I75-$G75+1)))) -> 0 | N75: =IF($G75=0,0,IF(N$6<$G75,0,IF(N$6>$I75,1,(N$6-$G75+1)/($I75-$G75+1)))) -> 0 | O75: =IF($G75=0,0,IF(O$6<$G75,0,IF(O$6>$I75,1,(O$6-$G75+1)/($I75-$G75+1)))) -> 0 | P75: =IF($G75=0,0,IF(P$6<$G75,0,IF(P$6>$I75,1,(P$6-$G75+1)/($I75-$G75+1)))) -> 0 | Q75: =IF($G75=0,0,IF(Q$6<$G75,0,IF(Q$6>$I75,1,(Q$6-$G75+1)/($I75-$G75+1)))) -> 0 | R75: =IF($G75=0,0,IF(R$6<$G75,0,IF(R$6>$I75,1,(R$6-$G75+1)/($I75-$G75+1)))) -> 0 | ... BQ75: =IF($G75=0,0,IF(BQ$6<$G75,0,IF(BQ$6>$I75,1,(BQ$6-$G75+1)/($I75-$G75+1)))) -> 1 | BR75: =+AVERAGE(K75:BQ75) -> 0.81920904
